TP2/rtl/debounce.v
// debounce: filtro anti-ruido generico e parametrizavel.
// Considera a entrada estavel somente apos N_CYCLES ciclos de clock
// consecutivos com o mesmo valor (contador que satura e reinicia a
// qualquer transicao).
module debounce #(
    parameter N_CYCLES = 8   // ciclos consecutivos estaveis exigidos
) (
    input  wire clk,
    input  wire rst_n,
    input  wire in_raw,      // entrada assincrona/ruidosa
    output reg  out_stable   // saida filtrada
);
    localparam CNT_W = $clog2(N_CYCLES + 1);

    reg [CNT_W-1:0] contador;
    reg             in_sync;   // 1 flip-flop de sincronizacao (evita metaestabilidade)

    always @(posedge clk or negedge rst_n) begin
        if (!rst_n) begin
            in_sync    <= 1'b0;
            contador   <= {CNT_W{1'b0}};
            out_stable <= 1'b0;
        end else begin
            in_sync <= in_raw;

            if (in_sync == out_stable) begin
                contador <= {CNT_W{1'b0}};
            end else if (contador >= N_CYCLES - 1) begin
                out_stable <= in_sync;
                contador   <= {CNT_W{1'b0}};
            end else begin
                contador <= contador + 1'b1;
            end
        end
    end
endmodule

TP2/rtl/botao_pedestre.v
// botao_pedestre: debounce do botao de pedestre + latch de solicitacao.
// A solicitacao fica travada (mesmo apos soltar o botao) at ser liberada
// externamente por "limpa_solicitacao" (a FSM do TP3 usa esse sinal ao
// entrar na fase de pedestre verde).
module botao_pedestre #(
    parameter N_CYCLES = 8
) (
    input  wire clk,
    input  wire rst_n,
    input  wire botao_raw,
    input  wire limpa_solicitacao,
    output wire botao_estavel,
    output reg  solicitacao_pedestre
);
    wire pressionado_pulso;
    reg  estavel_ant;

    debounce #(.N_CYCLES(N_CYCLES)) u_debounce (
        .clk(clk), .rst_n(rst_n),
        .in_raw(botao_raw), .out_stable(botao_estavel)
    );

    always @(posedge clk or negedge rst_n) begin
        if (!rst_n)
            estavel_ant <= 1'b0;
        else
            estavel_ant <= botao_estavel;
    end

    assign pressionado_pulso = botao_estavel & ~estavel_ant;

    always @(posedge clk or negedge rst_n) begin
        if (!rst_n)
            solicitacao_pedestre <= 1'b0;
        else if (limpa_solicitacao)
            solicitacao_pedestre <= 1'b0;
        else if (pressionado_pulso)
            solicitacao_pedestre <= 1'b1;
    end
endmodule

TP4/tb/tb_botao_pedestre.v
`timescale 1ns/1ps
module tb_botao_pedestre;
    localparam N = 4;
    reg clk, rst_n, botao_raw, limpa;
    wire botao_estavel, solicitacao;
    integer erros;

    botao_pedestre #(.N_CYCLES(N)) dut (
        .clk(clk), .rst_n(rst_n), .botao_raw(botao_raw),
        .limpa_solicitacao(limpa),
        .botao_estavel(botao_estavel), .solicitacao_pedestre(solicitacao)
    );

    always #5 clk = ~clk;

    task espera_ciclos(input integer n);
        integer i;
        begin
            for (i = 0; i < n; i = i + 1) @(posedge clk);
        end
    endtask

    initial begin
        clk = 0; rst_n = 0; botao_raw = 0; limpa = 0; erros = 0;
        $dumpfile("tb_botao_pedestre.vcd");
        $dumpvars(0, tb_botao_pedestre);

        espera_ciclos(2); rst_n = 1; espera_ciclos(2);

        // pressiona rapido e solta -- deve travar a solicitacao (latch)
        botao_raw = 1; espera_ciclos(N + 2);
        botao_raw = 0; espera_ciclos(N + 2);

        if (solicitacao !== 1'b1) begin
            erros = erros + 1;
            $display("[FALHA] solicitacao nao foi travada apos pressionar o botao");
        end else begin
            $display("[OK]    solicitacao travada mesmo apos soltar o botao");
        end

        // limpa a solicitacao (simula FSM entrando na fase pedestre verde)
        limpa = 1; espera_ciclos(1); limpa = 0;

        if (solicitacao !== 1'b0) begin
            erros = erros + 1;
            $display("[FALHA] solicitacao nao foi limpa por limpa_solicitacao");
        end else begin
            $display("[OK]    solicitacao limpa corretamente");
        end

        if (erros == 0)
            $display("RESULTADO: TODOS OS CASOS PASSARAM (2/2)");
        else
            $display("RESULTADO: %0d CASO(S) FALHARAM", erros);
        $finish;
    end
endmodule

TP2/docs/evidencias/tb_botao_pedestre.vcd
$date
	Wed Sep 16 01:57:28 2026
$end
$version
	Icarus Verilog
$end
$timescale
	1ps
$end
$scope module tb_botao_pedestre $end
$var wire 1 ! solicitacao $end
$var wire 1 " botao_estavel $end
$var parameter 32 # N $end
$var reg 1 $ botao_raw $end
$var reg 1 % clk $end
$var reg 1 & limpa $end
$var reg 1 ' rst_n $end
$var integer 32 ( erros [31:0] $end
$scope module dut $end
$var wire 1 $ botao_raw $end
$var wire 1 % clk $end
$var wire 1 & limpa_solicitacao $end
$var wire 1 ) pressionado_pulso $end
$var wire 1 ' rst_n $end
$var wire 1 " botao_estavel $end
$var parameter 32 * N_CYCLES $end
$var reg 1 + estavel_ant $end
$var reg 1 ! solicitacao_pedestre $end
$scope module u_debounce $end
$var wire 1 % clk $end
$var wire 1 $ in_raw $end
$var wire 1 ' rst_n $end
$var parameter 32 , CNT_W $end
$var parameter 32 - N_CYCLES $end
$var reg 3 . contador [2:0] $end
$var reg 1 / in_sync $end
$var reg 1 " out_stable $end
$upscope $end
$upscope $end
$scope task espera_ciclos $end
$var integer 32 0 i [31:0] $end
$var integer 32 1 n [31:0] $end
$upscope $end
$upscope $end
$enddefinitions $end
$comment Show the parameter values. $end
$dumpall
b100 -
b11 ,
b100 *
b100 #
$end
#0
$dumpvars
b10 1
b0 0
0/
b0 .
0+
0)
b0 (
0'
0&
0%
0$
0"
0!
$end
#5000
b1 0
1%
#10000
0%
#15000
1'
b0 0
1%
#20000
0%
#25000
b1 0
1%
#30000
0%
#35000
1/
b110 1
1$
b0 0
1%
#40000
0%
#45000
b1 .
b1 0
1%
#50000
0%
#55000
b10 .
b10 0
1%
#60000
0%
#65000
b11 .
b11 0
1%
#70000
0%
#75000
1)
b0 .
1"
b100 0
1%
#80000
0%
#85000
0)
1!
1+
b101 0
1%
#90000
0%
#95000
0/
0$
b0 0
1%
#100000
0%
#105000
b1 .
b1 0
1%
#110000
0%
#115000
b10 .
b10 0
1%
#120000
0%
#125000
b11 .
b11 0
1%
#130000
0%
#135000
b0 .
0"
b100 0
1%
#140000
0%
#145000
0+
b101 0
1%
#150000
0%
#155000
0!
b1 1
1&
b0 0
1%
#160000
0%
#165000
0&
b1 0
1%
