TP2/rtl/debounce.v
// debounce: filtro anti-ruido generico e parametrizavel.
// Considera a entrada estavel somente apos N_CYCLES ciclos de clock
// consecutivos com o mesmo valor (contador que satura e reinicia a
// qualquer transicao).
module debounce #(
    parameter N_CYCLES = 8   // ciclos consecutivos estaveis exigidos
) (
    input  wire clk,
    input  wire rst_n,
    input  wire in_raw,      // entrada assincrona/ruidosa
    output reg  out_stable   // saida filtrada
);
    localparam CNT_W = $clog2(N_CYCLES + 1);

    reg [CNT_W-1:0] contador;
    reg             in_sync;   // 1 flip-flop de sincronizacao (evita metaestabilidade)

    always @(posedge clk or negedge rst_n) begin
        if (!rst_n) begin
            in_sync    <= 1'b0;
            contador   <= {CNT_W{1'b0}};
            out_stable <= 1'b0;
        end else begin
            in_sync <= in_raw;

            if (in_sync == out_stable) begin
                contador <= {CNT_W{1'b0}};
            end else if (contador >= N_CYCLES - 1) begin
                out_stable <= in_sync;
                contador   <= {CNT_W{1'b0}};
            end else begin
                contador <= contador + 1'b1;
            end
        end
    end
endmodule

TP3/tb/tb_debounce.v
// Testbench do debounce: aplica ruido (varias transicoes rapidas) e depois
// um nivel estavel, conferindo que out_stable so acompanha a entrada apos
// N_CYCLES ciclos consecutivos sem transicao.
`timescale 1ns/1ps

module tb_debounce;
    localparam N = 4;
    reg clk, rst_n, in_raw;
    wire out_stable;
    integer erros;

    debounce #(.N_CYCLES(N)) dut (
        .clk(clk), .rst_n(rst_n), .in_raw(in_raw), .out_stable(out_stable)
    );

    always #5 clk = ~clk; // periodo de 10ns

    task espera_ciclos(input integer n);
        integer i;
        begin
            for (i = 0; i < n; i = i + 1) @(posedge clk);
        end
    endtask

    initial begin
        clk = 0; rst_n = 0; in_raw = 0; erros = 0;
        $dumpfile("tb_debounce.vcd");
        $dumpvars(0, tb_debounce);

        espera_ciclos(2);
        rst_n = 1;
        espera_ciclos(2);

        // Caso 1: ruido de "bouncing" -- varias transicoes rapidas, nao deve estabilizar
        in_raw = 1; espera_ciclos(1);
        in_raw = 0; espera_ciclos(1);
        in_raw = 1; espera_ciclos(1);
        in_raw = 0; espera_ciclos(1);
        if (out_stable !== 1'b0) begin
            erros = erros + 1;
            $display("[FALHA] ruido de bouncing produziu out_stable=1 antes da hora");
        end else begin
            $display("[OK]    ruido de bouncing ignorado (out_stable ainda em 0)");
        end

        // Caso 2: nivel estavel por N_CYCLES -> deve propagar para out_stable
        in_raw = 1;
        espera_ciclos(N + 1);
        if (out_stable !== 1'b1) begin
            erros = erros + 1;
            $display("[FALHA] nivel estavel em 1 nao propagou para out_stable");
        end else begin
            $display("[OK]    nivel estavel em 1 propagou para out_stable apos %0d ciclos", N);
        end

        // Caso 3: volta a 0 e permanece estavel -> out_stable deve acompanhar
        in_raw = 0;
        espera_ciclos(N + 1);
        if (out_stable !== 1'b0) begin
            erros = erros + 1;
            $display("[FALHA] nivel estavel em 0 nao propagou para out_stable");
        end else begin
            $display("[OK]    nivel estavel em 0 propagou para out_stable apos %0d ciclos", N);
        end

        if (erros == 0)
            $display("RESULTADO: TODOS OS CASOS PASSARAM (3/3)");
        else
            $display("RESULTADO: %0d CASO(S) FALHARAM", erros);

        $finish;
    end
endmodule

TP2/docs/evidencias/tb_debounce.vcd
$date
	Wed Sep 16 01:57:27 2026
$end
$version
	Icarus Verilog
$end
$timescale
	1ps
$end
$scope module tb_debounce $end
$var wire 1 ! out_stable $end
$var parameter 32 " N $end
$var reg 1 # clk $end
$var reg 1 $ in_raw $end
$var reg 1 % rst_n $end
$var integer 32 & erros [31:0] $end
$scope module dut $end
$var wire 1 # clk $end
$var wire 1 $ in_raw $end
$var wire 1 % rst_n $end
$var parameter 32 ' CNT_W $end
$var parameter 32 ( N_CYCLES $end
$var reg 3 ) contador [2:0] $end
$var reg 1 * in_sync $end
$var reg 1 ! out_stable $end
$upscope $end
$scope task espera_ciclos $end
$var integer 32 + i [31:0] $end
$var integer 32 , n [31:0] $end
$upscope $end
$upscope $end
$enddefinitions $end
$comment Show the parameter values. $end
$dumpall
b100 (
b11 '
b100 "
$end
#0
$dumpvars
b10 ,
b0 +
0*
b0 )
b0 &
0%
0$
0#
0!
$end
#5000
b1 +
1#
#10000
0#
#15000
1%
b0 +
1#
#20000
0#
#25000
b1 +
1#
#30000
0#
#35000
1*
b1 ,
1$
b0 +
1#
#40000
0#
#45000
b1 )
0*
0$
b0 +
1#
#50000
0#
#55000
b0 )
1*
1$
b0 +
1#
#60000
0#
#65000
b1 )
0*
0$
b0 +
1#
#70000
0#
#75000
b0 )
1*
b101 ,
1$
b0 +
1#
#80000
0#
#85000
b1 )
b1 +
1#
#90000
0#
#95000
b10 )
b10 +
1#
#100000
0#
#105000
b11 )
b11 +
1#
#110000
0#
#115000
b0 )
1!
b100 +
1#
#120000
0#
#125000
0*
0$
b0 +
1#
#130000
0#
#135000
b1 )
b1 +
1#
#140000
0#
#145000
b10 )
b10 +
1#
#150000
0#
#155000
b11 )
b11 +
1#
#160000
0#
#165000
b0 )
0!
b100 +
1#
#170000
0#
#175000
b101 +
1#
