final_project/rtl/bram_historico.v
// bram_historico: historico circular de 256 amostras de fluxo (veiculos
// contados por janela de medicao), mapeado em um bloco BSRAM da Tang Nano
// 4K. top_semaforo grava cada amostra nova e le a amostra que esta saindo
// da janela da media movel (media_movel_dsp).
//
// A memoria nao tem reset (requisito para virar BSRAM); quem garante que
// conteudo antigo nao entra na media e' o contador de amostras validas
// do media_movel_dsp.
//
// Portas:
//   escreve          - 1 ciclo em 1: grava dado_escrita e avanca o ponteiro
//   dado_escrita     - amostra a gravar
//   endereco_leitura - posicao a ler
//   dado_leitura     - conteudo de endereco_leitura (leitura sincrona: 1 ciclo de atraso)
//   ponteiro_escrita - posicao onde a proxima amostra sera gravada (volta a 0 apos 255)
module bram_historico (
    input  wire       clk,
    input  wire       rst_n,
    input  wire       escreve,
    input  wire [7:0] dado_escrita,
    input  wire [7:0] endereco_leitura,
    output reg  [7:0] dado_leitura,
    output reg  [7:0] ponteiro_escrita
);
    (* ram_style = "block", syn_ramstyle = "block_ram" *)
    reg [7:0] memoria [0:255];   // 256 amostras de 8 bits

    always @(posedge clk) begin
        if (escreve)
            memoria[ponteiro_escrita] <= dado_escrita;
        dado_leitura <= memoria[endereco_leitura];
    end

    always @(posedge clk or negedge rst_n) begin
        if (!rst_n)
            ponteiro_escrita <= 8'd0;
        else if (escreve)
            ponteiro_escrita <= ponteiro_escrita + 8'd1;
    end
endmodule

final_project/tb/tb_bram_historico.v
// tb_bram_historico: grava 6 amostras, confere o avanco do ponteiro e le
// cada posicao de volta (leitura sincrona, 1 ciclo de atraso).
`timescale 1ns/1ps
module tb_bram_historico;
    reg        clk, rst_n, escreve;
    reg  [7:0] dado_escrita, endereco_leitura;
    wire [7:0] dado_leitura, ponteiro_escrita;
    integer i, erros;

    bram_historico dut (
        .clk(clk), .rst_n(rst_n), .escreve(escreve),
        .dado_escrita(dado_escrita), .endereco_leitura(endereco_leitura),
        .dado_leitura(dado_leitura), .ponteiro_escrita(ponteiro_escrita)
    );

    always #5 clk = ~clk;

    task espera(input integer n);
        integer j;
        for (j = 0; j < n; j = j + 1) begin @(posedge clk); #1; end
    endtask

    initial begin
        $dumpfile("build/tb_bram_historico.vcd");
        $dumpvars(0, tb_bram_historico);
        clk = 0; rst_n = 0; escreve = 0; dado_escrita = 0; endereco_leitura = 0; erros = 0;
        espera(2); rst_n = 1; espera(1);

        // grava 10, 20, ..., 60 nas posicoes 0..5; termina apos a 6a escrita
        for (i = 0; i < 6; i = i + 1) begin
            dado_escrita = 10 * (i + 1); escreve = 1; espera(1);
        end
        escreve = 0;

        if (ponteiro_escrita !== 8'd6) begin
            erros = erros + 1;
            $display("[FALHA] ponteiro=%0d, esperado 6", ponteiro_escrita);
        end else
            $display("[OK]    ponteiro avancou para 6");

        // le de volta cada posicao; termina apos ler a posicao 5
        for (i = 0; i < 6; i = i + 1) begin
            endereco_leitura = i; espera(1);
            if (dado_leitura !== 10 * (i + 1)) begin
                erros = erros + 1;
                $display("[FALHA] memoria[%0d]=%0d, esperado %0d", i, dado_leitura, 10 * (i + 1));
            end else
                $display("[OK]    memoria[%0d]=%0d", i, dado_leitura);
        end

        if (erros == 0) $display("RESULTADO: TODOS OS CASOS PASSARAM");
        else            $display("RESULTADO: %0d CASO(S) FALHARAM", erros);
        $finish;
    end
endmodule

final_project/docs/evidencias/tb_bram_historico.vcd
$date
	Sun Sep 20 21:23:00 2026
$end
$version
	Icarus Verilog
$end
$timescale
	1ps
$end
$scope module tb_bram_historico $end
$var wire 8 ! ponteiro_escrita [7:0] $end
$var wire 8 " dado_leitura [7:0] $end
$var reg 1 # clk $end
$var reg 8 $ dado_escrita [7:0] $end
$var reg 8 % endereco_leitura [7:0] $end
$var reg 1 & escreve $end
$var reg 1 ' rst_n $end
$var integer 32 ( erros [31:0] $end
$var integer 32 ) i [31:0] $end
$scope module dut $end
$var wire 1 # clk $end
$var wire 8 * dado_escrita [7:0] $end
$var wire 8 + endereco_leitura [7:0] $end
$var wire 1 & escreve $end
$var wire 1 ' rst_n $end
$var reg 8 , dado_leitura [7:0] $end
$var reg 8 - ponteiro_escrita [7:0] $end
$upscope $end
$scope task espera_ciclos $end
$var integer 32 . j [31:0] $end
$var integer 32 / n [31:0] $end
$upscope $end
$upscope $end
$enddefinitions $end
$comment Show the parameter values. $end
$dumpall
$end
#0
$dumpvars
b10 /
b0 .
b0 -
bx ,
b0 +
b0 *
bx )
b0 (
0'
0&
b0 %
b0 $
0#
bx "
b0 !
$end
#5000
1#
#6000
b1 .
#10000
0#
#15000
1#
#16000
b1 /
1'
b0 .
#20000
0#
#25000
1#
#26000
1&
b1010 $
b1010 *
b0 )
b0 .
#30000
0#
#35000
b1 !
b1 -
1#
#36000
0&
b0 .
#40000
0#
#45000
b1010 "
b1010 ,
1#
#46000
1&
b10100 $
b10100 *
b1 )
b0 .
#50000
0#
#55000
b10 !
b10 -
1#
#56000
0&
b0 .
#60000
0#
#65000
1#
#66000
1&
b11110 $
b11110 *
b10 )
b0 .
#70000
0#
#75000
b11 !
b11 -
1#
#76000
0&
b0 .
#80000
0#
#85000
1#
#86000
1&
b101000 $
b101000 *
b11 )
b0 .
#90000
0#
#95000
b100 !
b100 -
1#
#96000
0&
b0 .
#100000
0#
#105000
1#
#106000
b0 )
b0 .
#110000
0#
#115000
1#
#116000
b1 %
b1 +
b1 )
b0 .
#120000
0#
#125000
b10100 "
b10100 ,
1#
#126000
b10 %
b10 +
b10 )
b0 .
#130000
0#
#135000
b11110 "
b11110 ,
1#
#136000
b11 %
b11 +
b11 )
b0 .
#140000
0#
#145000
b101000 "
b101000 ,
1#
#146000
b100 )
b1 .
