final_project/rtl/protocolo_serial.v
// protocolo_serial: protocolo final de comunicacao ARM<->FPGA (substitui o
// barramento paralelo do TP3/TP4 por uma interface serial sincrona, estilo
// SPI simplificado), com handshaking completo e telemetria bidirecional.
//
// Sinais:
//   sclk  (entrada, gerado pelo ARM)  -- clock serial da transferencia
//   cs_n  (entrada, gerado pelo ARM)  -- chip-select ativo em nivel baixo;
//                                        tambem funciona como handshake de
//                                        inicio/fim de quadro (frame)
//   mosi  (entrada)                   -- ARM -> FPGA: byte de comando
//   miso  (saida, high-Z quando cs_n=1) -- FPGA -> ARM: byte de telemetria
//                                        (fase do semaforo + contagem
//                                        regressiva -- ver formato abaixo)
//   busy  (saida)                     -- pulsa por 1 ciclo de "clk" ao fim
//                                        de cada quadro completo (8 bits),
//                                        sinalizando que o comando foi
//                                        aplicado e a telemetria enviada
//
// Formato do comando (mosi, MSB primeiro): identico ao protocolo_paralelo
//   [7:6]=opcode  [5:0]=valor
// Formato da telemetria (miso, MSB primeiro) -- para o
// log de countdown em tempo real da Raspberry Pi:
//   [7:6]=fase_carro_atual (00=vermelho/pedestre-verde, 01=amarelo,
//         10=verde -- espelha "estado_carro" da fsm_semaforo)
//   [5:0]=contagem_regressiva (0-63, ciclos restantes na fase corrente,
//         vindo direto do contador da fsm_semaforo -- e' o valor que a
//         Raspberry Pi usa pra mostrar "fecha em Ns")
module protocolo_serial (
    input  wire clk,          // clock interno da FPGA (27 MHz)
    input  wire rst_n,
    input  wire sclk,         // clock serial (gerado pelo ARM, ja sincronizado a "clk")
    input  wire cs_n,
    input  wire mosi,
    input  wire [1:0] fase_carro_atual,
    input  wire [5:0] contagem_regressiva,
    output wire miso,
    output reg  busy,
    output reg  [7:0] comando_recebido,
    output reg        comando_valido    // pulsa 1 ciclo quando um novo comando chegou
);
    reg [2:0] bit_cnt;
    reg [7:0] shift_in;
    reg [7:0] shift_out;
    reg       sclk_ant;
    wire      sclk_borda_subida;
    reg       miso_reg;

    assign sclk_borda_subida = sclk & ~sclk_ant;
    // OE (output-enable) do pino MISO: so' dirige o barramento durante o
    // quadro (cs_n=0); em repouso fica em alta impedancia (Hi-Z), permitindo
    // que o mesmo pino fisico seja compartilhado com outros perifericos.
    assign miso = cs_n ? 1'bz : miso_reg;

    always @(posedge clk or negedge rst_n) begin
        if (!rst_n) begin
            sclk_ant          <= 1'b0;
            bit_cnt            <= 3'd0;
            shift_in           <= 8'd0;
            shift_out          <= 8'd0;
            miso_reg           <= 1'b0;
            busy               <= 1'b0;
            comando_recebido   <= 8'd0;
            comando_valido     <= 1'b0;
        end else begin
            sclk_ant       <= sclk;
            comando_valido <= 1'b0;
            busy           <= 1'b0;

            if (cs_n) begin
                // fora do quadro: prepara o proximo byte de telemetria a
                // ser transmitido assim que cs_n descer
                bit_cnt   <= 3'd0;
                shift_out <= {fase_carro_atual, contagem_regressiva};
                miso_reg  <= fase_carro_atual[1]; // bit mais significativo do byte de telemetria
            end else if (sclk_borda_subida) begin
                // desloca 1 bit para dentro (mosi) e 1 bit para fora (miso)
                shift_in  <= {shift_in[6:0], mosi};
                shift_out <= {shift_out[6:0], 1'b0};
                miso_reg  <= shift_out[6];
                bit_cnt   <= bit_cnt + 3'd1;

                if (bit_cnt == 3'd7) begin
                    comando_recebido <= {shift_in[6:0], mosi};
                    comando_valido   <= 1'b1;
                    busy             <= 1'b1;
                end
            end
        end
    end
endmodule

final_project/tb/tb_protocolo_serial.v
// Testbench do protocolo_serial: confere alta impedancia de MISO fora do
// quadro, handshake de inicio/fim via cs_n, MSB da telemetria disponivel
// antes do primeiro pulso de sclk, e captura correta do comando apos 8 bits.
`timescale 1ns/1ps
module tb_protocolo_serial;
    reg clk, rst_n, sclk, cs_n, mosi;
    reg [1:0] fase_carro_atual;
    reg [5:0] contagem_regressiva;
    wire miso, busy;
    wire [7:0] comando_recebido;
    wire comando_valido;
    integer erros;

    protocolo_serial dut (
        .clk(clk), .rst_n(rst_n), .sclk(sclk), .cs_n(cs_n), .mosi(mosi),
        .fase_carro_atual(fase_carro_atual), .contagem_regressiva(contagem_regressiva),
        .miso(miso), .busy(busy),
        .comando_recebido(comando_recebido), .comando_valido(comando_valido)
    );

    always #5 clk = ~clk;   // clock interno da FPGA: periodo 10ns (rapido)

    task espera_clk(input integer n);
        integer j;
        begin
            for (j = 0; j < n; j = j + 1) begin
                @(posedge clk);
                #1;
            end
        end
    endtask

    // gera 1 pulso de sclk (0->1->0), com varios ciclos de "clk" internos
    // entre as bordas, simulando um sclk bem mais lento que o clock interno
    task pulso_sclk(input valor_mosi);
        begin
            mosi = valor_mosi;
            espera_clk(2);
            sclk = 1'b1;
            espera_clk(2);   // da tempo para o clk interno amostrar a borda de subida
            sclk = 1'b0;
            espera_clk(2);
        end
    endtask

    integer k;
    reg [7:0] comando_enviado;
    reg [7:0] telemetria_esperada;

    initial begin
        clk = 0; rst_n = 0; sclk = 0; cs_n = 1; mosi = 0;
        fase_carro_atual = 2'b01; contagem_regressiva = 6'b101010; // 42
        erros = 0;
        $dumpfile("tb_protocolo_serial.vcd");
        $dumpvars(0, tb_protocolo_serial);

        espera_clk(2); rst_n = 1; espera_clk(2);

        // ---- Caso 1: MISO em alta impedancia fora do quadro (cs_n=1) ----
        if (miso !== 1'bz) begin
            erros = erros + 1;
            $display("[FALHA] miso nao esta em alta impedancia com cs_n=1 (miso=%b)", miso);
        end else $display("[OK]    miso em alta impedancia (Hi-Z) fora do quadro");

        // ---- inicia o quadro (handshake: cs_n desce) ----
        cs_n = 0;
        espera_clk(2);

        telemetria_esperada = {fase_carro_atual, contagem_regressiva}; // 0b01101010

        if (miso !== telemetria_esperada[7]) begin
            erros = erros + 1;
            $display("[FALHA] MSB da telemetria incorreto logo apos cs_n=0 (miso=%b esperado=%b)",
                      miso, telemetria_esperada[7]);
        end else $display("[OK]    MISO ja apresenta o MSB da telemetria ao iniciar o quadro (handshake)");

        // ---- envia o comando (opcode=10 valor=000101 -> 0x85) ----
        comando_enviado = 8'b10000101;
        for (k = 7; k >= 0; k = k - 1)
            pulso_sclk(comando_enviado[k]);

        espera_clk(1);

        if (comando_recebido !== comando_enviado) begin
            erros = erros + 1;
            $display("[FALHA] comando_recebido=0x%h, esperado 0x%h", comando_recebido, comando_enviado);
        end else $display("[OK]    comando_recebido=0x%h corretamente apos 8 pulsos de sclk", comando_recebido);

        // ---- fim do quadro (handshake: cs_n sobe) ----
        cs_n = 1;
        espera_clk(1);
        if (miso !== 1'bz) begin
            erros = erros + 1;
            $display("[FALHA] miso nao voltou a alta impedancia ao fim do quadro");
        end else $display("[OK]    miso volta a alta impedancia ao fim do quadro (handshake completo)");

        if (erros == 0)
            $display("RESULTADO: TODOS OS CASOS PASSARAM (4/4)");
        else
            $display("RESULTADO: %0d CASO(S) FALHARAM", erros);
        $finish;
    end
endmodule

final_project/docs/evidencias/tb_protocolo_serial.vcd
$date
	Wed Sep 16 20:30:41 2026
$end
$version
	Icarus Verilog
$end
$timescale
	1ps
$end
$scope module tb_protocolo_serial $end
$var wire 1 ! miso $end
$var wire 1 " comando_valido $end
$var wire 8 # comando_recebido [7:0] $end
$var wire 1 $ busy $end
$var reg 1 % clk $end
$var reg 8 & comando_enviado [7:0] $end
$var reg 6 ' contagem_regressiva [5:0] $end
$var reg 1 ( cs_n $end
$var reg 2 ) fase_carro_atual [1:0] $end
$var reg 1 * mosi $end
$var reg 1 + rst_n $end
$var reg 1 , sclk $end
$var reg 8 - telemetria_esperada [7:0] $end
$var integer 32 . erros [31:0] $end
$var integer 32 / k [31:0] $end
$scope module dut $end
$var wire 1 % clk $end
$var wire 6 0 contagem_regressiva [5:0] $end
$var wire 1 ( cs_n $end
$var wire 2 1 fase_carro_atual [1:0] $end
$var wire 1 * mosi $end
$var wire 1 + rst_n $end
$var wire 1 , sclk $end
$var wire 1 2 sclk_borda_subida $end
$var wire 1 ! miso $end
$var reg 3 3 bit_cnt [2:0] $end
$var reg 1 $ busy $end
$var reg 8 4 comando_recebido [7:0] $end
$var reg 1 " comando_valido $end
$var reg 1 5 miso_reg $end
$var reg 1 6 sclk_ant $end
$var reg 8 7 shift_in [7:0] $end
$var reg 8 8 shift_out [7:0] $end
$upscope $end
$scope task espera_clk $end
$var integer 32 9 j [31:0] $end
$var integer 32 : n [31:0] $end
$upscope $end
$scope task pulso_sclk $end
$var reg 1 ; valor_mosi $end
$upscope $end
$upscope $end
$enddefinitions $end
$comment Show the parameter values. $end
$dumpall
$end
#0
$dumpvars
x;
b10 :
b0 9
b0 8
b0 7
06
05
b0 4
b0 3
02
b1 1
b101010 0
bx /
b0 .
bx -
0,
0+
0*
b1 )
1(
b101010 '
bx &
0%
0$
b0 #
0"
z!
$end
#5000
1%
#6000
b1 9
#10000
0%
#15000
1%
#16000
1+
b0 9
#20000
0%
#25000
b1101010 8
1%
#26000
b1 9
#30000
0%
#35000
1%
#36000
0!
0(
b0 9
#40000
0%
#45000
1%
#46000
b1 9
#50000
0%
#55000
1%
#56000
1*
1;
b111 /
b10000101 &
b1101010 -
b0 9
#60000
0%
#65000
1%
#66000
b1 9
#70000
0%
#75000
1%
#76000
12
1,
b0 9
#80000
0%
#85000
02
1!
b1 3
15
b11010100 8
b1 7
16
1%
#86000
b1 9
#90000
0%
#95000
1%
#96000
0,
b0 9
#100000
0%
#105000
06
1%
#106000
b1 9
#110000
0%
#115000
1%
#116000
0*
0;
b110 /
b0 9
#120000
0%
#125000
1%
#126000
b1 9
#130000
0%
#135000
1%
#136000
12
1,
b0 9
#140000
0%
#145000
02
b10 3
b10101000 8
b10 7
16
1%
#146000
b1 9
#150000
0%
#155000
1%
#156000
0,
b0 9
#160000
0%
#165000
06
1%
#166000
b1 9
#170000
0%
#175000
1%
#176000
b101 /
b0 9
#180000
0%
#185000
1%
#186000
b1 9
#190000
0%
#195000
1%
#196000
12
1,
b0 9
#200000
0%
#205000
02
0!
b11 3
05
b1010000 8
b100 7
16
1%
#206000
b1 9
#210000
0%
#215000
1%
#216000
0,
b0 9
#220000
0%
#225000
06
1%
#226000
b1 9
#230000
0%
#235000
1%
#236000
b100 /
b0 9
#240000
0%
#245000
1%
#246000
b1 9
#250000
0%
#255000
1%
#256000
12
1,
b0 9
#260000
0%
#265000
02
1!
b100 3
15
b10100000 8
b1000 7
16
1%
#266000
b1 9
#270000
0%
#275000
1%
#276000
0,
b0 9
#280000
0%
#285000
06
1%
#286000
b1 9
#290000
0%
#295000
1%
#296000
b11 /
b0 9
#300000
0%
#305000
1%
#306000
b1 9
#310000
0%
#315000
1%
#316000
12
1,
b0 9
#320000
0%
#325000
02
0!
b101 3
05
b1000000 8
b10000 7
16
1%
#326000
b1 9
#330000
0%
#335000
1%
#336000
0,
b0 9
#340000
0%
#345000
06
1%
#346000
b1 9
#350000
0%
#355000
1%
#356000
1*
1;
b10 /
b0 9
#360000
0%
#365000
1%
#366000
b1 9
#370000
0%
#375000
1%
#376000
12
1,
b0 9
#380000
0%
#385000
02
1!
b110 3
15
b10000000 8
b100001 7
16
1%
#386000
b1 9
#390000
0%
#395000
1%
#396000
0,
b0 9
#400000
0%
#405000
06
1%
#406000
b1 9
#410000
0%
#415000
1%
#416000
0*
0;
b1 /
b0 9
#420000
0%
#425000
1%
#426000
b1 9
#430000
0%
#435000
1%
#436000
12
1,
b0 9
#440000
0%
#445000
02
0!
b111 3
05
b0 8
b1000010 7
16
1%
#446000
b1 9
#450000
0%
#455000
1%
#456000
0,
b0 9
#460000
0%
#465000
06
1%
#466000
b1 9
#470000
0%
#475000
1%
#476000
1*
1;
b0 /
b0 9
#480000
0%
#485000
1%
#486000
b1 9
#490000
0%
#495000
1%
#496000
12
1,
b0 9
#500000
0%
#505000
02
1$
1"
b10000101 #
b10000101 4
b0 3
b10000101 7
16
1%
#506000
b1 9
#510000
0%
#515000
0$
0"
1%
#516000
0,
b0 9
#520000
0%
#525000
06
1%
#526000
b1 9
#530000
0%
#535000
1%
#536000
b1 :
b11111111111111111111111111111111 /
b0 9
#540000
0%
#545000
1%
#546000
z!
1(
b0 9
#550000
0%
#555000
b1101010 8
1%
#556000
b1 9
