TP4/rtl/protocolo_paralelo.v
// protocolo_paralelo: interface de comunicacao ARM->FPGA via barramento
// paralelo de 8 bits + linha de strobe, com linha de ack de confirmacao.
// Formato do comando (dados[7:0]):
//   dados[7:6] = opcode  (00=tempo_min 01=tempo_amarelo 10=limiar_baixo 11=limiar_alto)
//   dados[5:0] = valor   (0-63)
// A cada borda de subida de "strobe" (ja filtrada por debounce fora deste
// modulo, pois strobe e' gerado digitalmente pela Raspberry Pi via GPIO),
// o valor e' decodificado e latched no registrador correspondente, e "ack"
// e' pulsado por 1 ciclo confirmando o recebimento.
module protocolo_paralelo (
    input  wire       clk,
    input  wire       rst_n,
    input  wire [7:0] dados,
    input  wire       strobe,
    output reg        ack,
    output reg  [5:0] tempo_min_reg,
    output reg  [5:0] tempo_amarelo_reg,
    output reg  [5:0] limiar_baixo_reg,
    output reg  [5:0] limiar_alto_reg
);
    localparam OP_TEMPO_MIN     = 2'b00;
    localparam OP_TEMPO_AMARELO = 2'b01;
    localparam OP_LIMIAR_BAIXO  = 2'b10;
    localparam OP_LIMIAR_ALTO   = 2'b11;

    reg strobe_ant;
    wire strobe_borda;

    always @(posedge clk or negedge rst_n) begin
        if (!rst_n) strobe_ant <= 1'b0;
        else        strobe_ant <= strobe;
    end
    assign strobe_borda = strobe & ~strobe_ant;

    always @(posedge clk or negedge rst_n) begin
        if (!rst_n) begin
            ack               <= 1'b0;
            tempo_min_reg      <= 6'd10; // valores padrao de seguranca
            tempo_amarelo_reg  <= 6'd3;
            limiar_baixo_reg   <= 6'd3;
            limiar_alto_reg    <= 6'd8;
        end else if (strobe_borda) begin
            ack <= 1'b1;
            case (dados[7:6])
                OP_TEMPO_MIN:     tempo_min_reg     <= dados[5:0];
                OP_TEMPO_AMARELO: tempo_amarelo_reg <= dados[5:0];
                OP_LIMIAR_BAIXO:  limiar_baixo_reg  <= dados[5:0];
                OP_LIMIAR_ALTO:   limiar_alto_reg   <= dados[5:0];
            endcase
        end else begin
            ack <= 1'b0;
        end
    end
endmodule

final_project/tb/tb_protocolo_paralelo.v
// Testbench do protocolo_paralelo: confere valores padrao no reset,
// aplicacao de comandos OP_TEMPO_MIN/OP_LIMIAR_ALTO via strobe, e retorno
// de ack ao repouso entre comandos.
`timescale 1ns/1ps
module tb_protocolo_paralelo;
    reg clk, rst_n, strobe;
    reg [7:0] dados;
    wire ack;
    wire [5:0] tempo_min_reg, tempo_amarelo_reg, limiar_baixo_reg, limiar_alto_reg;
    integer erros;

    protocolo_paralelo dut (
        .clk(clk), .rst_n(rst_n), .dados(dados), .strobe(strobe), .ack(ack),
        .tempo_min_reg(tempo_min_reg), .tempo_amarelo_reg(tempo_amarelo_reg),
        .limiar_baixo_reg(limiar_baixo_reg), .limiar_alto_reg(limiar_alto_reg)
    );

    always #5 clk = ~clk;

    task espera_ciclos(input integer n);
        integer i;
        begin
            for (i = 0; i < n; i = i + 1) begin
                @(posedge clk);
                #1;
            end
        end
    endtask

    task envia_comando(input [1:0] opcode, input [5:0] valor);
        begin
            dados = {opcode, valor};
            strobe = 1'b1;
            espera_ciclos(1);
            strobe = 1'b0;
            espera_ciclos(1);
        end
    endtask

    initial begin
        clk = 0; rst_n = 0; strobe = 0; dados = 0; erros = 0;
        $dumpfile("tb_protocolo_paralelo.vcd");
        $dumpvars(0, tb_protocolo_paralelo);

        espera_ciclos(2); rst_n = 1; espera_ciclos(1);

        if (tempo_min_reg !== 6'd10 || tempo_amarelo_reg !== 6'd3) begin
            erros = erros + 1;
            $display("[FALHA] valores padrao incorretos apos reset");
        end else $display("[OK]    valores padrao de seguranca carregados apos reset");

        envia_comando(2'b00, 6'd20); // OP_TEMPO_MIN = 20
        if (tempo_min_reg !== 6'd20) begin
            erros = erros + 1;
            $display("[FALHA] tempo_min_reg nao atualizou (valor=%0d)", tempo_min_reg);
        end else $display("[OK]    comando OP_TEMPO_MIN=20 aplicado corretamente");

        envia_comando(2'b11, 6'd15); // OP_LIMIAR_ALTO = 15
        if (limiar_alto_reg !== 6'd15) begin
            erros = erros + 1;
            $display("[FALHA] limiar_alto_reg nao atualizou (valor=%0d)", limiar_alto_reg);
        end else $display("[OK]    comando OP_LIMIAR_ALTO=15 aplicado corretamente");

        // ack deve ter pulsado por exatamente 1 ciclo a cada comando (checado indiretamente
        // pelo fato de os registradores terem mudado); checa que ack volta a 0 em repouso
        if (ack !== 1'b0) begin
            erros = erros + 1;
            $display("[FALHA] ack nao retornou a 0 em repouso");
        end else $display("[OK]    ack em repouso = 0 (pulso de 1 ciclo por comando)");

        if (erros == 0)
            $display("RESULTADO: TODOS OS CASOS PASSARAM (4/4)");
        else
            $display("RESULTADO: %0d CASO(S) FALHARAM", erros);
        $finish;
    end
endmodule

final_project/docs/evidencias/tb_protocolo_paralelo.vcd
$date
	Sun Sep 20 21:23:00 2026
$end
$version
	Icarus Verilog
$end
$timescale
	1ps
$end
$scope module tb_protocolo_paralelo $end
$var wire 6 ! tempo_min_reg [5:0] $end
$var wire 6 " tempo_amarelo_reg [5:0] $end
$var wire 6 # limiar_baixo_reg [5:0] $end
$var wire 6 $ limiar_alto_reg [5:0] $end
$var wire 1 % ack $end
$var reg 1 & clk $end
$var reg 8 ' dados [7:0] $end
$var reg 1 ( rst_n $end
$var reg 1 ) strobe $end
$var integer 32 * erros [31:0] $end
$scope module dut $end
$var wire 1 & clk $end
$var wire 8 + dados [7:0] $end
$var wire 1 ( rst_n $end
$var wire 1 ) strobe $end
$var wire 1 , strobe_borda $end
$var parameter 2 - OP_LIMIAR_ALTO $end
$var parameter 2 . OP_LIMIAR_BAIXO $end
$var parameter 2 / OP_TEMPO_AMARELO $end
$var parameter 2 0 OP_TEMPO_MIN $end
$var reg 1 % ack $end
$var reg 6 1 limiar_alto_reg [5:0] $end
$var reg 6 2 limiar_baixo_reg [5:0] $end
$var reg 1 3 strobe_ant $end
$var reg 6 4 tempo_amarelo_reg [5:0] $end
$var reg 6 5 tempo_min_reg [5:0] $end
$upscope $end
$scope task envia_comando $end
$var reg 2 6 opcode [1:0] $end
$var reg 6 7 valor [5:0] $end
$upscope $end
$scope task espera_ciclos $end
$var integer 32 8 i [31:0] $end
$var integer 32 9 n [31:0] $end
$upscope $end
$upscope $end
$enddefinitions $end
$comment Show the parameter values. $end
$dumpall
b0 0
b1 /
b10 .
b11 -
$end
#0
$dumpvars
b10 9
b0 8
bx 7
bx 6
b1010 5
b11 4
03
b11 2
b1000 1
0,
b0 +
b0 *
0)
0(
b0 '
0&
0%
b1000 $
b11 #
b11 "
b1010 !
$end
#5000
1&
#6000
b1 8
#10000
0&
#15000
1&
#16000
b1 9
1(
b0 8
#20000
0&
#25000
1&
#26000
1,
1)
b10100 '
b10100 +
b10100 7
b0 6
b0 8
#30000
0&
#35000
0,
13
b10100 !
b10100 5
1%
1&
#36000
0)
b0 8
#40000
0&
#45000
0%
03
1&
#46000
1,
1)
b11001111 '
b11001111 +
b1111 7
b11 6
b0 8
#50000
0&
#55000
0,
13
b1111 $
b1111 1
1%
1&
#56000
0)
b0 8
#60000
0&
#65000
0%
03
1&
#66000
b1 8
