TP2/rtl/debounce.v
// debounce: filtro anti-ruido generico e parametrizavel.
// Considera a entrada estavel somente apos N_CYCLES ciclos de clock
// consecutivos com o mesmo valor (contador que satura e reinicia a
// qualquer transicao).
module debounce #(
    parameter N_CYCLES = 8   // ciclos consecutivos estaveis exigidos
) (
    input  wire clk,
    input  wire rst_n,
    input  wire in_raw,      // entrada assincrona/ruidosa
    output reg  out_stable   // saida filtrada
);
    localparam CNT_W = $clog2(N_CYCLES + 1);

    reg [CNT_W-1:0] contador;
    reg             in_sync;   // 1 flip-flop de sincronizacao (evita metaestabilidade)

    always @(posedge clk or negedge rst_n) begin
        if (!rst_n) begin
            in_sync    <= 1'b0;
            contador   <= {CNT_W{1'b0}};
            out_stable <= 1'b0;
        end else begin
            in_sync <= in_raw;

            if (in_sync == out_stable) begin
                contador <= {CNT_W{1'b0}};
            end else if (contador >= N_CYCLES - 1) begin
                out_stable <= in_sync;
                contador   <= {CNT_W{1'b0}};
            end else begin
                contador <= contador + 1'b1;
            end
        end
    end
endmodule

TP2/rtl/sensor_veiculo.v
// sensor_veiculo: encapsula o debounce do sensor de veiculos (sensor de
// obstaculo reflexivo infravermelho -- saida digital direta, sem trigger/echo,
// compativel com 3,3V) e gera um pulso de 1 ciclo a cada deteccao (borda de
// subida do sinal filtrado), usado para contagem.
module sensor_veiculo #(
    parameter N_CYCLES = 8
) (
    input  wire clk,
    input  wire rst_n,
    input  wire sensor_raw,
    output wire sensor_estavel,
    output wire veiculo_pulso     // pulso de 1 ciclo por veiculo detectado
);
    reg estavel_ant;

    debounce #(.N_CYCLES(N_CYCLES)) u_debounce (
        .clk(clk), .rst_n(rst_n),
        .in_raw(sensor_raw), .out_stable(sensor_estavel)
    );

    always @(posedge clk or negedge rst_n) begin
        if (!rst_n)
            estavel_ant <= 1'b0;
        else
            estavel_ant <= sensor_estavel;
    end

    assign veiculo_pulso = sensor_estavel & ~estavel_ant; // deteccao de borda de subida
endmodule

final_project/tb/tb_sensor_veiculo.v
// Testbench do sensor_veiculo: gera ruido curto (ignorado) e dois sinais
// estaveis, confirmando exatamente 2 pulsos de deteccao.
`timescale 1ns/1ps
module tb_sensor_veiculo;
    localparam N = 4;
    reg clk, rst_n, sensor_raw;
    wire sensor_estavel, veiculo_pulso;
    integer erros, pulsos;

    sensor_veiculo #(.N_CYCLES(N)) dut (
        .clk(clk), .rst_n(rst_n), .sensor_raw(sensor_raw),
        .sensor_estavel(sensor_estavel), .veiculo_pulso(veiculo_pulso)
    );

    always #5 clk = ~clk;

    task espera_ciclos(input integer n);
        integer i;
        begin
            for (i = 0; i < n; i = i + 1) @(posedge clk);
        end
    endtask

    always @(posedge clk)
        if (veiculo_pulso) pulsos = pulsos + 1;

    initial begin
        clk = 0; rst_n = 0; sensor_raw = 0; erros = 0; pulsos = 0;
        $dumpfile("tb_sensor_veiculo.vcd");
        $dumpvars(0, tb_sensor_veiculo);

        espera_ciclos(2); rst_n = 1; espera_ciclos(2);

        // ruido rapido, nao deve gerar pulso
        sensor_raw = 1; espera_ciclos(1);
        sensor_raw = 0; espera_ciclos(1);

        // veiculo 1: sinal estavel por N+1 ciclos
        sensor_raw = 1; espera_ciclos(N + 2);
        sensor_raw = 0; espera_ciclos(N + 2);

        // veiculo 2: outro sinal estavel
        sensor_raw = 1; espera_ciclos(N + 2);
        sensor_raw = 0; espera_ciclos(N + 2);

        if (pulsos == 2) begin
            $display("[OK]    2 veiculos detectados corretamente (pulsos=%0d)", pulsos);
        end else begin
            erros = erros + 1;
            $display("[FALHA] esperado 2 pulsos, obtido %0d", pulsos);
        end

        if (erros == 0)
            $display("RESULTADO: TODOS OS CASOS PASSARAM (1/1)");
        else
            $display("RESULTADO: %0d CASO(S) FALHARAM", erros);
        $finish;
    end
endmodule

final_project/docs/evidencias/tb_sensor_veiculo.vcd
$date
	Sun Sep 20 21:23:00 2026
$end
$version
	Icarus Verilog
$end
$timescale
	1ps
$end
$scope module tb_sensor_veiculo $end
$var wire 1 ! veiculo_pulso $end
$var wire 1 " sensor_estavel $end
$var parameter 32 # N $end
$var reg 1 $ clk $end
$var reg 1 % rst_n $end
$var reg 1 & sensor_raw $end
$var integer 32 ' erros [31:0] $end
$var integer 32 ( pulsos [31:0] $end
$scope module dut $end
$var wire 1 $ clk $end
$var wire 1 % rst_n $end
$var wire 1 & sensor_raw $end
$var wire 1 ! veiculo_pulso $end
$var wire 1 " sensor_estavel $end
$var parameter 32 ) N_CYCLES $end
$var reg 1 * estavel_ant $end
$scope module u_debounce $end
$var wire 1 $ clk $end
$var wire 1 & in_raw $end
$var wire 1 % rst_n $end
$var parameter 32 + CNT_W $end
$var parameter 32 , N_CYCLES $end
$var reg 3 - contador [2:0] $end
$var reg 1 . in_sync $end
$var reg 1 " out_stable $end
$upscope $end
$upscope $end
$scope task espera_ciclos $end
$var integer 32 / i [31:0] $end
$var integer 32 0 n [31:0] $end
$upscope $end
$upscope $end
$enddefinitions $end
$comment Show the parameter values. $end
$dumpall
b100 ,
b11 +
b100 )
b100 #
$end
#0
$dumpvars
b10 0
b0 /
0.
b0 -
0*
b0 (
b0 '
0&
0%
0$
0"
0!
$end
#5000
b1 /
1$
#10000
0$
#15000
1%
b0 /
1$
#20000
0$
#25000
b1 /
1$
#30000
0$
#35000
1.
b1 0
1&
b0 /
1$
#40000
0$
#45000
b1 -
0.
0&
b0 /
1$
#50000
0$
#55000
b0 -
1.
b110 0
1&
b0 /
1$
#60000
0$
#65000
b1 -
b1 /
1$
#70000
0$
#75000
b10 -
b10 /
1$
#80000
0$
#85000
b11 -
b11 /
1$
#90000
0$
#95000
1!
b0 -
1"
b100 /
1$
#100000
0$
#105000
0!
1*
b1 (
b101 /
1$
#110000
0$
#115000
0.
0&
b0 /
1$
#120000
0$
#125000
b1 -
b1 /
1$
#130000
0$
#135000
b10 -
b10 /
1$
#140000
0$
#145000
b11 -
b11 /
1$
#150000
0$
#155000
b0 -
0"
b100 /
1$
#160000
0$
#165000
0*
b101 /
1$
#170000
0$
#175000
1.
1&
b0 /
1$
#180000
0$
#185000
b1 -
b1 /
1$
#190000
0$
#195000
b10 -
b10 /
1$
#200000
0$
#205000
b11 -
b11 /
1$
#210000
0$
#215000
1!
b0 -
1"
b100 /
1$
#220000
0$
#225000
0!
1*
b10 (
b101 /
1$
#230000
0$
#235000
0.
0&
b0 /
1$
#240000
0$
#245000
b1 -
b1 /
1$
#250000
0$
#255000
b10 -
b10 /
1$
#260000
0$
#265000
b11 -
b11 /
1$
#270000
0$
#275000
b0 -
0"
b100 /
1$
#280000
0$
#285000
0*
b101 /
1$
#290000
0$
#295000
b110 /
1$
