final_project/rtl/bram_historico.v
// bram_historico: buffer circular de 256 amostras (inferido em BRAM pelo
// Gowin EDA, por ser uma memoria sincrona com porta de escrita e porta de
// leitura independentes e enderecos de 8 bits). Guarda a contagem de
// veiculos de cada intervalo de amostragem, para uso pelo filtro de media
// movel e por telemetria futura (TP5).
module bram_historico (
    input  wire       clk,
    input  wire       rst_n,
    input  wire        escreve,          // pulso: grava dado_escrita e avanca o ponteiro
    input  wire [7:0]  dado_escrita,
    input  wire [7:0]  endereco_leitura, // endereco livre para leitura (ex.: dump via protocolo)
    output reg  [7:0]  dado_leitura,
    output reg  [7:0]  ponteiro_escrita  // posicao da proxima escrita (util para telemetria)
);
    reg [7:0] memoria [0:255];

    always @(posedge clk or negedge rst_n) begin
        if (!rst_n) begin
            ponteiro_escrita <= 8'd0;
        end else if (escreve) begin
            memoria[ponteiro_escrita] <= dado_escrita;
            ponteiro_escrita <= ponteiro_escrita + 8'd1; // circular (wrap natural em 8 bits)
        end
    end

    // leitura sincrona (padrao para inferencia de BRAM real no Gowin EDA)
    always @(posedge clk) begin
        dado_leitura <= memoria[endereco_leitura];
    end
endmodule

TP4/tb/tb_bram_historico.v
`timescale 1ns/1ps
module tb_bram_historico;
    reg clk, rst_n, escreve;
    reg [7:0] dado_escrita, endereco_leitura;
    wire [7:0] dado_leitura, ponteiro_escrita;
    integer erros, i;

    bram_historico dut (
        .clk(clk), .rst_n(rst_n), .escreve(escreve),
        .dado_escrita(dado_escrita), .endereco_leitura(endereco_leitura),
        .dado_leitura(dado_leitura), .ponteiro_escrita(ponteiro_escrita)
    );

    always #5 clk = ~clk;

    task espera_ciclos(input integer n);
        integer j;
        begin
            for (j = 0; j < n; j = j + 1) begin
                @(posedge clk);
                #1;
            end
        end
    endtask

    initial begin
        clk = 0; rst_n = 0; escreve = 0; dado_escrita = 0; endereco_leitura = 0; erros = 0;
        $dumpfile("tb_bram_historico.vcd");
        $dumpvars(0, tb_bram_historico);

        espera_ciclos(2); rst_n = 1; espera_ciclos(1);

        // escreve 4 amostras conhecidas: 10, 20, 30, 40
        for (i = 0; i < 4; i = i + 1) begin
            dado_escrita = (i + 1) * 10;
            escreve = 1;
            espera_ciclos(1);
            escreve = 0;
            espera_ciclos(1);
        end

        if (ponteiro_escrita !== 8'd4) begin
            erros = erros + 1;
            $display("[FALHA] ponteiro_escrita=%0d, esperado 4", ponteiro_escrita);
        end else $display("[OK]    ponteiro_escrita avancou para 4 apos 4 escritas");

        for (i = 0; i < 4; i = i + 1) begin
            endereco_leitura = i;
            espera_ciclos(1); // leitura sincrona: 1 ciclo de latencia
            if (dado_leitura !== (i + 1) * 10) begin
                erros = erros + 1;
                $display("[FALHA] endereco %0d: lido %0d, esperado %0d", i, dado_leitura, (i+1)*10);
            end else begin
                $display("[OK]    endereco %0d: lido %0d corretamente", i, dado_leitura);
            end
        end

        if (erros == 0)
            $display("RESULTADO: TODOS OS CASOS PASSARAM (5/5)");
        else
            $display("RESULTADO: %0d CASO(S) FALHARAM", erros);
        $finish;
    end
endmodule

TP4/docs/evidencias/tb_bram_historico.vcd
$date
	Wed Sep 16 02:13:20 2026
$end
$version
	Icarus Verilog
$end
$timescale
	1ps
$end
$scope module tb_bram_historico $end
$var wire 8 ! ponteiro_escrita [7:0] $end
$var wire 8 " dado_leitura [7:0] $end
$var reg 1 # clk $end
$var reg 8 $ dado_escrita [7:0] $end
$var reg 8 % endereco_leitura [7:0] $end
$var reg 1 & escreve $end
$var reg 1 ' rst_n $end
$var integer 32 ( erros [31:0] $end
$var integer 32 ) i [31:0] $end
$scope module dut $end
$var wire 1 # clk $end
$var wire 8 * dado_escrita [7:0] $end
$var wire 8 + endereco_leitura [7:0] $end
$var wire 1 & escreve $end
$var wire 1 ' rst_n $end
$var reg 8 , dado_leitura [7:0] $end
$var reg 8 - ponteiro_escrita [7:0] $end
$upscope $end
$scope task espera_ciclos $end
$var integer 32 . j [31:0] $end
$var integer 32 / n [31:0] $end
$upscope $end
$upscope $end
$enddefinitions $end
$comment Show the parameter values. $end
$dumpall
$end
#0
$dumpvars
b10 /
b0 .
b0 -
bx ,
b0 +
b0 *
bx )
b0 (
0'
0&
b0 %
b0 $
0#
bx "
b0 !
$end
#5000
1#
#6000
b1 .
#10000
0#
#15000
1#
#16000
b1 /
1'
b0 .
#20000
0#
#25000
1#
#26000
1&
b1010 $
b1010 *
b0 )
b0 .
#30000
0#
#35000
b1 !
b1 -
1#
#36000
0&
b0 .
#40000
0#
#45000
b1010 "
b1010 ,
1#
#46000
1&
b10100 $
b10100 *
b1 )
b0 .
#50000
0#
#55000
b10 !
b10 -
1#
#56000
0&
b0 .
#60000
0#
#65000
1#
#66000
1&
b11110 $
b11110 *
b10 )
b0 .
#70000
0#
#75000
b11 !
b11 -
1#
#76000
0&
b0 .
#80000
0#
#85000
1#
#86000
1&
b101000 $
b101000 *
b11 )
b0 .
#90000
0#
#95000
b100 !
b100 -
1#
#96000
0&
b0 .
#100000
0#
#105000
1#
#106000
b0 )
b0 .
#110000
0#
#115000
1#
#116000
b1 %
b1 +
b1 )
b0 .
#120000
0#
#125000
b10100 "
b10100 ,
1#
#126000
b10 %
b10 +
b10 )
b0 .
#130000
0#
#135000
b11110 "
b11110 ,
1#
#136000
b11 %
b11 +
b11 )
b0 .
#140000
0#
#145000
b101000 "
b101000 ,
1#
#146000
b100 )
b1 .
