final_project/rtl/media_movel_dsp.v
// media_movel_dsp: filtro de media movel sobre uma janela de 5 amostras,
// usando um multiplicador (mapeado para o bloco DSP nativo da Tang Nano
// 4K pelo Gowin EDA) para calcular soma*(1/5) em ponto fixo, em vez de
// uma divisao (mais cara em FPGA). Classifica o nivel de fluxo comparando
// a media com os limiares recebidos do protocolo_paralelo.
module media_movel_dsp (
    input  wire       clk,
    input  wire       rst_n,
    input  wire        nova_amostra,     // pulso: uma nova contagem de intervalo chegou
    input  wire [7:0]  amostra,
    input  wire [5:0]  limiar_baixo,
    input  wire [5:0]  limiar_alto,
    output reg  [7:0]  media,
    output reg  [1:0]  nivel_fluxo       // 00=baixo 01=medio 10=alto
);
    localparam N_JANELA = 5;
    localparam RECIPROCO_Q16 = 17'd13107; // round(65536/5), ponto fixo Q16

    reg  [7:0]  janela [0:N_JANELA-1];
    reg  [10:0] soma;                     // 5 amostras de 8 bits: max 1275, cabe em 11 bits
    wire [10:0] soma_novo;
    wire [27:0] produto;                  // soma_novo(11) * reciproco(17) -> mapeia para DSP
    wire [27:0] produto_arred;             // produto + meio-LSB (arredondamento Q16)

    integer i;

    // soma ja incluindo a amostra que esta entrando (e removendo a mais antiga)
    assign soma_novo = soma - janela[N_JANELA-1] + amostra;
    assign produto    = soma_novo * RECIPROCO_Q16; // multiplicacao (bloco DSP)
    assign produto_arred = produto + 28'd32768;      // arredondamento (+0.5 em Q16) antes do shift

    always @(posedge clk or negedge rst_n) begin
        if (!rst_n) begin
            for (i = 0; i < N_JANELA; i = i + 1)
                janela[i] <= 8'd0;
            soma        <= 11'd0;
            media       <= 8'd0;
            nivel_fluxo <= 2'b00;
        end else if (nova_amostra) begin
            for (i = N_JANELA - 1; i > 0; i = i - 1)
                janela[i] <= janela[i-1];
            janela[0] <= amostra;

            soma  <= soma_novo;
            media <= produto_arred[23:16]; // >> 16 arredondado -> soma/5 aproximado

            if (produto_arred[23:16] <= {2'b00, limiar_baixo})
                nivel_fluxo <= 2'b00; // baixo
            else if (produto_arred[23:16] <= {2'b00, limiar_alto})
                nivel_fluxo <= 2'b01; // medio
            else
                nivel_fluxo <= 2'b10; // alto
        end
    end
endmodule

final_project/tb/tb_media_movel_dsp.v
`timescale 1ns/1ps
module tb_media_movel_dsp;
    reg clk, rst_n, nova_amostra;
    reg [7:0] amostra;
    reg [5:0] limiar_baixo, limiar_alto;
    wire [7:0] media;
    wire [1:0] nivel_fluxo;
    integer erros;

    media_movel_dsp dut (
        .clk(clk), .rst_n(rst_n), .nova_amostra(nova_amostra), .amostra(amostra),
        .limiar_baixo(limiar_baixo), .limiar_alto(limiar_alto),
        .media(media), .nivel_fluxo(nivel_fluxo)
    );

    always #5 clk = ~clk;

    task espera_ciclos(input integer n);
        integer j;
        begin
            for (j = 0; j < n; j = j + 1) begin
                @(posedge clk);
                #1;
            end
        end
    endtask

    task envia_amostra(input [7:0] v);
        begin
            amostra = v;
            nova_amostra = 1;
            espera_ciclos(1);
            nova_amostra = 0;
            espera_ciclos(1);
        end
    endtask

    initial begin
        clk = 0; rst_n = 0; nova_amostra = 0; amostra = 0; erros = 0;
        limiar_baixo = 15; limiar_alto = 25;
        $dumpfile("tb_media_movel_dsp.vcd");
        $dumpvars(0, tb_media_movel_dsp);

        espera_ciclos(2); rst_n = 1; espera_ciclos(1);

        // preenche a janela com 5 amostras de valor 10 -> media esperada = 10
        envia_amostra(10); envia_amostra(10); envia_amostra(10);
        envia_amostra(10); envia_amostra(10);

        if (media !== 8'd10) begin
            erros = erros + 1;
            $display("[FALHA] media=%0d, esperado 10 (janela de 5x10)", media);
        end else $display("[OK]    media=10 com janela de 5 amostras iguais a 10");

        if (nivel_fluxo !== 2'b00) begin
            erros = erros + 1;
            $display("[FALHA] nivel_fluxo=%b, esperado BAIXO (00) com media=10<=15", nivel_fluxo);
        end else $display("[OK]    nivel_fluxo=BAIXO conforme limiar_baixo=15");

        // entra uma amostra alta (60), saindo o 10 mais antigo -> soma=100, media=20
        envia_amostra(60);
        if (media !== 8'd20) begin
            erros = erros + 1;
            $display("[FALHA] media=%0d, esperado 20 apos nova amostra 60", media);
        end else $display("[OK]    media=20 apos deslizar a janela com nova amostra 60");

        if (nivel_fluxo !== 2'b01) begin
            erros = erros + 1;
            $display("[FALHA] nivel_fluxo=%b, esperado MEDIO (01) com 15<media=20<=25", nivel_fluxo);
        end else $display("[OK]    nivel_fluxo=MEDIO conforme limiares");

        if (erros == 0)
            $display("RESULTADO: TODOS OS CASOS PASSARAM (4/4)");
        else
            $display("RESULTADO: %0d CASO(S) FALHARAM", erros);
        $finish;
    end
endmodule

TP4/docs/evidencias/tb_media_movel_dsp.vcd
$date
	Wed Sep 16 02:13:20 2026
$end
$version
	Icarus Verilog
$end
$timescale
	1ps
$end
$scope module tb_media_movel_dsp $end
$var wire 2 ! nivel_fluxo [1:0] $end
$var wire 8 " media [7:0] $end
$var reg 8 # amostra [7:0] $end
$var reg 1 $ clk $end
$var reg 6 % limiar_alto [5:0] $end
$var reg 6 & limiar_baixo [5:0] $end
$var reg 1 ' nova_amostra $end
$var reg 1 ( rst_n $end
$var integer 32 ) erros [31:0] $end
$scope module dut $end
$var wire 8 * amostra [7:0] $end
$var wire 1 $ clk $end
$var wire 6 + limiar_alto [5:0] $end
$var wire 6 , limiar_baixo [5:0] $end
$var wire 1 ' nova_amostra $end
$var wire 1 ( rst_n $end
$var wire 11 - soma_novo [10:0] $end
$var wire 28 . produto_arred [27:0] $end
$var wire 28 / produto [27:0] $end
$var parameter 32 0 N_JANELA $end
$var parameter 17 1 RECIPROCO_Q16 $end
$var reg 8 2 media [7:0] $end
$var reg 2 3 nivel_fluxo [1:0] $end
$var reg 11 4 soma [10:0] $end
$var integer 32 5 i [31:0] $end
$upscope $end
$scope task envia_amostra $end
$var reg 8 6 v [7:0] $end
$upscope $end
$scope task espera_ciclos $end
$var integer 32 7 j [31:0] $end
$var integer 32 8 n [31:0] $end
$upscope $end
$upscope $end
$enddefinitions $end
$comment Show the parameter values. $end
$dumpall
b11001100110011 1
b101 0
$end
#0
$dumpvars
b10 8
b0 7
bx 6
b101 5
b0 4
b0 3
b0 2
b0 /
b1000000000000000 .
b0 -
b1111 ,
b11001 +
b0 *
b0 )
0(
0'
b1111 &
b11001 %
0$
b0 #
b0 "
b0 !
$end
#5000
b101 5
1$
#6000
b1 7
#10000
0$
#15000
b101 5
1$
#16000
b1 8
1(
b0 7
#20000
0$
#25000
1$
#26000
1'
b100111111111111110 .
b11111111111111110 /
b1010 -
b1010 #
b1010 *
b1010 6
b0 7
#30000
0$
#35000
b10 "
b10 2
b1000111111111111100 .
b111111111111111100 /
b10100 -
b1010 4
b0 5
1$
#36000
0'
b0 7
#40000
0$
#45000
1$
#46000
1'
b0 7
#50000
0$
#55000
b100 "
b100 2
b1100111111111111010 .
b1011111111111111010 /
b11110 -
b10100 4
b0 5
1$
#56000
0'
b0 7
#60000
0$
#65000
1$
#66000
1'
b0 7
#70000
0$
#75000
b110 "
b110 2
b10000111111111111000 .
b1111111111111111000 /
b101000 -
b11110 4
b0 5
1$
#76000
0'
b0 7
#80000
0$
#85000
1$
#86000
1'
b0 7
#90000
0$
#95000
b1000 "
b1000 2
b10100111111111110110 .
b10011111111111110110 /
b110010 -
b101000 4
b0 5
1$
#96000
0'
b0 7
#100000
0$
#105000
1$
#106000
1'
b0 7
#110000
0$
#115000
b1010 "
b1010 2
b110010 4
b10100111111111110110 .
b10011111111111110110 /
b110010 -
b0 5
1$
#116000
0'
b0 7
#120000
0$
#125000
1$
#126000
1'
b101000111111111101100 .
b100111111111111101100 /
b1100100 -
b111100 #
b111100 *
b111100 6
b0 7
#130000
0$
#135000
b1 !
b1 3
b10100 "
b10100 2
b111100111111111100010 .
b111011111111111100010 /
b10010110 -
b1100100 4
b0 5
1$
#136000
0'
b0 7
#140000
0$
#145000
1$
#146000
b1 7
