TP3/rtl/contador_tempo.v
// contador_tempo: temporizador decrescente generico, usado pela FSM do
// semaforo para os tempos minimos de cada fase. Carrega "valor_inicial"
// quando "carrega" = 1; decrementa 1 por ciclo enquanto "habilita" = 1;
// "zerou" fica em 1 quando a contagem chega a 0.
module contador_tempo #(
    parameter LARGURA = 16
) (
    input  wire                  clk,
    input  wire                  rst_n,
    input  wire                  carrega,
    input  wire                  habilita,
    input  wire [LARGURA-1:0]    valor_inicial,
    output reg  [LARGURA-1:0]    valor_atual,
    output wire                  zerou
);
    always @(posedge clk or negedge rst_n) begin
        if (!rst_n)
            valor_atual <= {LARGURA{1'b0}};
        else if (carrega)
            valor_atual <= valor_inicial;
        else if (habilita && valor_atual != 0)
            valor_atual <= valor_atual - 1'b1;
    end

    assign zerou = (valor_atual == 0);
endmodule

TP4/tb/tb_contador_tempo.v
`timescale 1ns/1ps
module tb_contador_tempo;
    localparam W = 8;
    reg clk, rst_n, carrega, habilita;
    reg [W-1:0] valor_inicial;
    wire [W-1:0] valor_atual;
    wire zerou;
    integer erros;

    contador_tempo #(.LARGURA(W)) dut (
        .clk(clk), .rst_n(rst_n), .carrega(carrega), .habilita(habilita),
        .valor_inicial(valor_inicial), .valor_atual(valor_atual), .zerou(zerou)
    );

    always #5 clk = ~clk;

    task espera_ciclos(input integer n);
        integer i;
        begin
            for (i = 0; i < n; i = i + 1) @(posedge clk);
        end
    endtask

    initial begin
        clk = 0; rst_n = 0; carrega = 0; habilita = 0; valor_inicial = 0; erros = 0;
        $dumpfile("tb_contador_tempo.vcd");
        $dumpvars(0, tb_contador_tempo);

        espera_ciclos(2); rst_n = 1; espera_ciclos(1);

        valor_inicial = 5; carrega = 1; espera_ciclos(1); carrega = 0;
        if (valor_atual !== 5) begin
            erros = erros + 1;
            $display("[FALHA] carga nao funcionou: valor_atual=%0d (esperado 5)", valor_atual);
        end else $display("[OK]    carga do valor inicial (5) funcionou");

        habilita = 1;
        espera_ciclos(5);
        if (zerou !== 1'b1) begin
            erros = erros + 1;
            $display("[FALHA] contador nao zerou apos 5 ciclos habilitado (valor_atual=%0d)", valor_atual);
        end else $display("[OK]    contador zerou apos 5 ciclos, como esperado");

        espera_ciclos(3);
        if (valor_atual !== 0) begin
            erros = erros + 1;
            $display("[FALHA] contador nao deveria decrementar abaixo de zero (valor_atual=%0d)", valor_atual);
        end else $display("[OK]    contador satura em zero corretamente");

        if (erros == 0)
            $display("RESULTADO: TODOS OS CASOS PASSARAM (3/3)");
        else
            $display("RESULTADO: %0d CASO(S) FALHARAM", erros);
        $finish;
    end
endmodule

TP3/docs/evidencias/tb_contador_tempo.vcd
$date
	Wed Sep 16 02:07:43 2026
$end
$version
	Icarus Verilog
$end
$timescale
	1ps
$end
$scope module tb_contador_tempo $end
$var wire 1 ! zerou $end
$var wire 8 " valor_atual [7:0] $end
$var parameter 32 # W $end
$var reg 1 $ carrega $end
$var reg 1 % clk $end
$var reg 1 & habilita $end
$var reg 1 ' rst_n $end
$var reg 8 ( valor_inicial [7:0] $end
$var integer 32 ) erros [31:0] $end
$scope module dut $end
$var wire 1 $ carrega $end
$var wire 1 % clk $end
$var wire 1 & habilita $end
$var wire 1 ' rst_n $end
$var wire 8 * valor_inicial [7:0] $end
$var wire 1 ! zerou $end
$var parameter 32 + LARGURA $end
$var reg 8 , valor_atual [7:0] $end
$upscope $end
$scope task espera_ciclos $end
$var integer 32 - i [31:0] $end
$var integer 32 . n [31:0] $end
$upscope $end
$upscope $end
$enddefinitions $end
$comment Show the parameter values. $end
$dumpall
b1000 +
b1000 #
$end
#0
$dumpvars
b10 .
b0 -
b0 ,
b0 *
b0 )
b0 (
0'
0&
0%
0$
b0 "
1!
$end
#5000
b1 -
1%
#10000
0%
#15000
b1 .
1'
b0 -
1%
#20000
0%
#25000
0!
b101 "
b101 ,
1$
b101 (
b101 *
b0 -
1%
#30000
0%
#35000
b100 "
b100 ,
b101 .
1&
0$
b0 -
1%
#40000
0%
#45000
b11 "
b11 ,
b1 -
1%
#50000
0%
#55000
b10 "
b10 ,
b10 -
1%
#60000
0%
#65000
b1 "
b1 ,
b11 -
1%
#70000
0%
#75000
1!
b0 "
b0 ,
b100 -
1%
#80000
0%
#85000
b11 .
b0 -
1%
#90000
0%
#95000
b1 -
1%
#100000
0%
#105000
b10 -
1%
#110000
0%
#115000
b11 -
1%
