TP3/rtl/contador_tempo.v
// contador_tempo: temporizador decrescente generico, usado pela FSM do
// semaforo para os tempos minimos de cada fase. Carrega "valor_inicial"
// quando "carrega" = 1; decrementa 1 por ciclo enquanto "habilita" = 1;
// "zerou" fica em 1 quando a contagem chega a 0.
module contador_tempo #(
    parameter LARGURA = 16
) (
    input  wire                  clk,
    input  wire                  rst_n,
    input  wire                  carrega,
    input  wire                  habilita,
    input  wire [LARGURA-1:0]    valor_inicial,
    output reg  [LARGURA-1:0]    valor_atual,
    output wire                  zerou
);
    always @(posedge clk or negedge rst_n) begin
        if (!rst_n)
            valor_atual <= {LARGURA{1'b0}};
        else if (carrega)
            valor_atual <= valor_inicial;
        else if (habilita && valor_atual != 0)
            valor_atual <= valor_atual - 1'b1;
    end

    assign zerou = (valor_atual == 0);
endmodule

TP4/rtl/fsm_semaforo.v
// fsm_semaforo: maquina de estados finitos do semaforo, hierarquica
// (instancia contador_tempo para os tempos minimos de cada fase).
// Estados: CARRO_VERDE -> CARRO_AMARELO -> PEDESTRE_VERDE -> CARRO_VERDE
// A solicitacao do pedestre so e atendida apos o tempo minimo de verde
// dos veiculos ter decorrido (ONF-08: seguranca do cruzamento).
module fsm_semaforo #(
    parameter LARGURA_TEMPO = 16
) (
    input  wire                      clk,
    input  wire                      rst_n,
    input  wire                      solicitacao_pedestre,
    input  wire [LARGURA_TEMPO-1:0]  tempo_min_verde,
    input  wire [LARGURA_TEMPO-1:0]  tempo_amarelo,
    input  wire [LARGURA_TEMPO-1:0]  tempo_pedestre,
    output reg  [1:0]                estado_carro,     // 00=vermelho 01=amarelo 10=verde
    output reg                       verde_pedestre,
    output reg                       limpa_solicitacao
);
    localparam CARRO_VERDE    = 2'd0;
    localparam CARRO_AMARELO  = 2'd1;
    localparam PEDESTRE_VERDE = 2'd2;

    reg [1:0] estado, prox_estado;
    reg       carrega_cont;
    reg [LARGURA_TEMPO-1:0] valor_inicial_cont;
    wire [LARGURA_TEMPO-1:0] valor_atual_cont;
    wire      tempo_esgotado;
    reg       iniciou;   // forca a 1a carga do contador logo apos o reset

    contador_tempo #(.LARGURA(LARGURA_TEMPO)) u_contador (
        .clk(clk), .rst_n(rst_n),
        .carrega(carrega_cont), .habilita(1'b1),
        .valor_inicial(valor_inicial_cont),
        .valor_atual(valor_atual_cont), .zerou(tempo_esgotado)
    );

    always @(posedge clk or negedge rst_n) begin
        if (!rst_n) begin
            estado  <= CARRO_VERDE;
            iniciou <= 1'b0;
        end else begin
            estado  <= prox_estado;
            iniciou <= 1'b1;
        end
    end

    // 1) decide a transicao de estado (saidas tipo Moore, dependem so de "estado")
    always @(*) begin
        prox_estado     = estado;
        estado_carro     = 2'b00;
        verde_pedestre    = 1'b0;
        limpa_solicitacao = 1'b0;

        case (estado)
            CARRO_VERDE: begin
                estado_carro = 2'b10; // verde
                if (tempo_esgotado && solicitacao_pedestre)
                    prox_estado = CARRO_AMARELO;
            end
            CARRO_AMARELO: begin
                estado_carro = 2'b01; // amarelo
                if (tempo_esgotado)
                    prox_estado = PEDESTRE_VERDE;
            end
            PEDESTRE_VERDE: begin
                estado_carro   = 2'b00; // vermelho para os veiculos
                verde_pedestre  = 1'b1;
                if (tempo_esgotado) begin
                    prox_estado       = CARRO_VERDE;
                    limpa_solicitacao = 1'b1;
                end
            end
            default: prox_estado = CARRO_VERDE;
        endcase
    end

    // 2) valor a carregar no contador = duracao da fase que esta SENDO
    // ENTRADA (prox_estado), nao da fase atual -- evita carregar a
    // duracao errada no ciclo de transicao.
    always @(*) begin
        case (prox_estado)
            CARRO_VERDE:    valor_inicial_cont = tempo_min_verde;
            CARRO_AMARELO:  valor_inicial_cont = tempo_amarelo;
            PEDESTRE_VERDE: valor_inicial_cont = tempo_pedestre;
            default:        valor_inicial_cont = tempo_min_verde;
        endcase
        carrega_cont = (prox_estado != estado) || !iniciou;
    end
endmodule

final_project/tb/tb_fsm_semaforo.v
`timescale 1ns/1ps
module tb_fsm_semaforo;
    localparam W = 8;
    reg clk, rst_n, solicitacao;
    reg [W-1:0] t_verde, t_amarelo, t_pedestre;
    wire [1:0] estado_carro;
    wire verde_pedestre, limpa_solicitacao;
    integer erros;

    fsm_semaforo #(.LARGURA_TEMPO(W)) dut (
        .clk(clk), .rst_n(rst_n),
        .solicitacao_pedestre(solicitacao),
        .tempo_min_verde(t_verde), .tempo_amarelo(t_amarelo), .tempo_pedestre(t_pedestre),
        .estado_carro(estado_carro), .verde_pedestre(verde_pedestre),
        .limpa_solicitacao(limpa_solicitacao)
    );

    always #5 clk = ~clk;

    task espera_ciclos(input integer n);
        integer i;
        begin
            // #1 apos cada posedge garante que os registradores (NBA) e a
            // logica combinacional ja se estabilizaram antes de checar
            // qualquer sinal (evita corrida de simulacao com o proprio clock).
            for (i = 0; i < n; i = i + 1) begin
                @(posedge clk);
                #1;
            end
        end
    endtask

    initial begin
        clk = 0; rst_n = 0; solicitacao = 0;
        t_verde = 5; t_amarelo = 3; t_pedestre = 4; erros = 0;
        $dumpfile("tb_fsm_semaforo.vcd");
        $dumpvars(0, tb_fsm_semaforo);

        espera_ciclos(2); rst_n = 1; espera_ciclos(1);

        // Caso 1: logo apos reset, deve estar em CARRO_VERDE (10)
        if (estado_carro !== 2'b10) begin
            erros = erros + 1;
            $display("[FALHA] estado inicial nao e CARRO_VERDE (estado_carro=%b)", estado_carro);
        end else $display("[OK]    estado inicial = CARRO_VERDE");

        // Caso 2: sem solicitacao, mesmo apos o tempo minimo, permanece em verde (ONF-08)
        espera_ciclos(t_verde + 3);
        if (estado_carro !== 2'b10) begin
            erros = erros + 1;
            $display("[FALHA] sem solicitacao, saiu de CARRO_VERDE indevidamente");
        end else $display("[OK]    sem solicitacao pendente, permanece em CARRO_VERDE (seguranca)");

        // Caso 3: com solicitacao pendente e tempo minimo ja decorrido, deve ir para AMARELO
        solicitacao = 1;
        espera_ciclos(1);
        if (estado_carro !== 2'b01) begin
            erros = erros + 1;
            $display("[FALHA] nao transicionou para CARRO_AMARELO com solicitacao pendente (estado_carro=%b)", estado_carro);
        end else $display("[OK]    transicionou para CARRO_AMARELO ao registrar solicitacao");

        // Caso 4: apos tempo_amarelo ciclos, deve ir para PEDESTRE_VERDE
        // (+1 ciclo: o contador zera em t_amarelo ciclos, e a FSM so
        // registra a transicao no ciclo seguinte, ao amostrar "zerou")
        espera_ciclos(t_amarelo + 1);
        if (estado_carro !== 2'b00 || verde_pedestre !== 1'b1) begin
            erros = erros + 1;
            $display("[FALHA] nao entrou em PEDESTRE_VERDE apos tempo_amarelo (estado_carro=%b verde_pedestre=%b)",
                      estado_carro, verde_pedestre);
        end else $display("[OK]    entrou em PEDESTRE_VERDE apos tempo_amarelo, com verde_pedestre=1");

        // Caso 5: apos tempo_pedestre ciclos, deve limpar a solicitacao e voltar para CARRO_VERDE
        // limpa_solicitacao e' combinacional e fica em 1 durante o ULTIMO
        // ciclo de PEDESTRE_VERDE (quando tempo_esgotado ja e' 1 mas o
        // estado registrado ainda nao mudou) -- por isso e' checado aqui,
        // ANTES do ciclo extra que efetivamente latch a transicao.
        espera_ciclos(t_pedestre);
        if (limpa_solicitacao !== 1'b1) begin
            erros = erros + 1;
            $display("[FALHA] limpa_solicitacao nao foi pulsado ao fim de PEDESTRE_VERDE");
        end else $display("[OK]    limpa_solicitacao pulsado corretamente");
        espera_ciclos(1);
        if (estado_carro !== 2'b10) begin
            erros = erros + 1;
            $display("[FALHA] nao retornou para CARRO_VERDE apos PEDESTRE_VERDE (estado_carro=%b)", estado_carro);
        end else $display("[OK]    retornou para CARRO_VERDE, ciclo completo validado");

        if (erros == 0)
            $display("RESULTADO: TODOS OS CASOS PASSARAM (5/5)");
        else
            $display("RESULTADO: %0d CASO(S) FALHARAM", erros);
        $finish;
    end
endmodule

TP3/docs/evidencias/tb_fsm_semaforo.vcd
$date
	Wed Sep 16 02:07:43 2026
$end
$version
	Icarus Verilog
$end
$timescale
	1ps
$end
$scope module tb_fsm_semaforo $end
$var wire 1 ! verde_pedestre $end
$var wire 1 " limpa_solicitacao $end
$var wire 2 # estado_carro [1:0] $end
$var parameter 32 $ W $end
$var reg 1 % clk $end
$var reg 1 & rst_n $end
$var reg 1 ' solicitacao $end
$var reg 8 ( t_amarelo [7:0] $end
$var reg 8 ) t_pedestre [7:0] $end
$var reg 8 * t_verde [7:0] $end
$var integer 32 + erros [31:0] $end
$scope module dut $end
$var wire 1 % clk $end
$var wire 1 & rst_n $end
$var wire 1 ' solicitacao_pedestre $end
$var wire 8 , tempo_amarelo [7:0] $end
$var wire 8 - tempo_min_verde [7:0] $end
$var wire 8 . tempo_pedestre [7:0] $end
$var wire 8 / valor_atual_cont [7:0] $end
$var wire 1 0 tempo_esgotado $end
$var parameter 2 1 CARRO_AMARELO $end
$var parameter 2 2 CARRO_VERDE $end
$var parameter 32 3 LARGURA_TEMPO $end
$var parameter 2 4 PEDESTRE_VERDE $end
$var reg 1 5 carrega_cont $end
$var reg 2 6 estado [1:0] $end
$var reg 2 7 estado_carro [1:0] $end
$var reg 1 8 iniciou $end
$var reg 1 " limpa_solicitacao $end
$var reg 2 9 prox_estado [1:0] $end
$var reg 8 : valor_inicial_cont [7:0] $end
$var reg 1 ! verde_pedestre $end
$scope module u_contador $end
$var wire 1 5 carrega $end
$var wire 1 % clk $end
$var wire 1 ; habilita $end
$var wire 1 & rst_n $end
$var wire 8 < valor_inicial [7:0] $end
$var wire 1 0 zerou $end
$var parameter 32 = LARGURA $end
$var reg 8 > valor_atual [7:0] $end
$upscope $end
$upscope $end
$scope task espera_ciclos $end
$var integer 32 ? i [31:0] $end
$var integer 32 @ n [31:0] $end
$upscope $end
$upscope $end
$enddefinitions $end
$comment Show the parameter values. $end
$dumpall
b1000 =
b10 4
b1000 3
b0 2
b1 1
b1000 $
$end
#0
$dumpvars
b10 @
b0 ?
b0 >
b101 <
1;
b101 :
b0 9
08
b10 7
b0 6
15
10
b0 /
b100 .
b101 -
b11 ,
b0 +
b101 *
b100 )
b11 (
0'
0&
0%
b10 #
0"
0!
$end
#5000
1%
#6000
b1 ?
#10000
0%
#15000
1%
#16000
b1 @
1&
b0 ?
#20000
0%
#25000
05
b10 #
b10 7
18
00
b101 /
b101 >
1%
#26000
b1000 @
b0 ?
#30000
0%
#35000
b100 /
b100 >
1%
#36000
b1 ?
#40000
0%
#45000
b11 /
b11 >
1%
#46000
b10 ?
#50000
0%
#55000
b10 /
b10 >
1%
#56000
b11 ?
#60000
0%
#65000
b1 /
b1 >
1%
#66000
b100 ?
#70000
0%
#75000
b10 #
b10 7
10
b0 /
b0 >
1%
#76000
b101 ?
#80000
0%
#85000
1%
#86000
b110 ?
#90000
0%
#95000
1%
#96000
b111 ?
#100000
0%
#105000
1%
#106000
15
b11 :
b11 <
b1 9
b10 #
b10 7
b1 @
1'
b0 ?
#110000
0%
#115000
05
b1 #
b1 7
00
b11 /
b11 >
b1 6
1%
#116000
b100 @
b0 ?
#120000
0%
#125000
b10 /
b10 >
1%
#126000
b1 ?
#130000
0%
#135000
b1 /
b1 >
1%
#136000
b10 ?
#140000
0%
#145000
15
b100 :
b100 <
b10 9
b1 #
b1 7
10
b0 /
b0 >
1%
#146000
b11 ?
#150000
0%
#155000
05
1!
b0 #
b0 7
00
b100 /
b100 >
b10 6
1%
#156000
b0 ?
#160000
0%
#165000
b11 /
b11 >
1%
#166000
b1 ?
#170000
0%
#175000
b10 /
b10 >
1%
#176000
b10 ?
#180000
0%
#185000
b1 /
b1 >
1%
#186000
b11 ?
#190000
0%
#195000
15
b101 :
b101 <
1"
b0 9
1!
10
b0 /
b0 >
1%
#196000
b1 @
b0 ?
#200000
0%
#205000
05
b10 #
b10 7
0"
0!
b0 6
00
b101 /
b101 >
1%
#206000
b1 ?
