final_project/rtl/debounce.v
// debounce: filtra uma entrada mecanica/ruidosa (botao ou sensor IR).
// Sincroniza a entrada assincrona com 2 flip-flops (evita metaestabilidade)
// e so' muda a saida depois que a entrada fica N_CICLOS ciclos seguidos
// no novo nivel. Usado por botao_pedestre e sensor_veiculo.
//
// Parametro:
//   N_CICLOS - ciclos de clk que a entrada precisa ficar estavel
//              (ex.: 540_000 ciclos = 20 ms a 27 MHz)
// Portas:
//   entrada - sinal bruto, ativo em nivel ALTO (assincrono ao clk)
//   saida   - sinal filtrado e sincronizado ao clk (repouso = 0)
module debounce #(
    parameter integer N_CICLOS = 540_000
) (
    input  wire clk,
    input  wire rst_n,
    input  wire entrada,
    output reg  saida
);
    localparam integer LARGURA_CONT = $clog2(N_CICLOS + 1);

    reg [1:0]              sinc;      // cadeia de sincronizacao; sinc[1] = entrada ja sincronizada
    reg [LARGURA_CONT-1:0] contador;  // ciclos seguidos em que sinc[1] difere de saida

    always @(posedge clk or negedge rst_n) begin
        if (!rst_n) begin
            sinc     <= 2'b00;
            contador <= {LARGURA_CONT{1'b0}};
            saida    <= 1'b0;
        end else begin
            sinc <= {sinc[0], entrada};

            if (sinc[1] == saida)
                contador <= {LARGURA_CONT{1'b0}};       // qualquer repique reinicia a contagem
            else if (contador == N_CICLOS - 1) begin
                saida    <= sinc[1];                    // estavel tempo suficiente: aceita o novo nivel
                contador <= {LARGURA_CONT{1'b0}};
            end else
                contador <= contador + 1'b1;
        end
    end
endmodule

final_project/rtl/botao_pedestre.v
// botao_pedestre: le o botao de travessia, filtra com debounce e guarda o
// pedido (latch) ate a FSM atender. O pedido continua ativo mesmo depois
// que o botao e' solto, e so' e' apagado por limpa_solicitacao, que a
// fsm_semaforo gera ao fim da fase de pedestre.
//
// Parametro:
//   N_CICLOS - ciclos de estabilidade exigidos pelo debounce
// Portas:
//   botao_ativo          - botao ja convertido para ativo em ALTO (1 = apertado)
//   limpa_solicitacao    - 1 ciclo em 1: apaga o pedido (vem da FSM)
//   solicitacao_pedestre - 1 enquanto ha pedido de travessia pendente
module botao_pedestre #(
    parameter integer N_CICLOS = 540_000
) (
    input  wire clk,
    input  wire rst_n,
    input  wire botao_ativo,
    input  wire limpa_solicitacao,
    output reg  solicitacao_pedestre
);
    wire botao_estavel;      // botao filtrado (1 enquanto apertado)
    reg  estavel_ant;        // botao_estavel no ciclo anterior
    wire pressionado_pulso;  // 1 ciclo em 1 no instante em que o botao e' apertado

    debounce #(.N_CICLOS(N_CICLOS)) u_debounce (
        .clk(clk), .rst_n(rst_n),
        .entrada(botao_ativo), .saida(botao_estavel)
    );

    always @(posedge clk or negedge rst_n) begin
        if (!rst_n)
            estavel_ant <= 1'b0;
        else
            estavel_ant <= botao_estavel;
    end

    assign pressionado_pulso = botao_estavel & ~estavel_ant;

    // limpa tem prioridade: um aperto no mesmo ciclo do fim da fase de
    // pedestre e' descartado (a travessia acabou de acontecer)
    always @(posedge clk or negedge rst_n) begin
        if (!rst_n)
            solicitacao_pedestre <= 1'b0;
        else if (limpa_solicitacao)
            solicitacao_pedestre <= 1'b0;
        else if (pressionado_pulso)
            solicitacao_pedestre <= 1'b1;
    end
endmodule

final_project/tb/tb_botao_pedestre.v
// tb_botao_pedestre: verifica que o pedido fica guardado depois que o
// botao e' solto, que limpa_solicitacao o apaga e que repique nao gera pedido.
`timescale 1ns/1ps
module tb_botao_pedestre;
    localparam integer N = 4;

    reg  clk, rst_n, botao_ativo, limpa;
    wire solicitacao;
    integer erros;

    botao_pedestre #(.N_CICLOS(N)) dut (
        .clk(clk), .rst_n(rst_n), .botao_ativo(botao_ativo),
        .limpa_solicitacao(limpa), .solicitacao_pedestre(solicitacao)
    );

    always #5 clk = ~clk;

    task espera(input integer n);
        integer i;
        for (i = 0; i < n; i = i + 1) begin @(posedge clk); #1; end
    endtask

    task confere(input esperado, input [8*48-1:0] descricao);
        if (solicitacao !== esperado) begin
            erros = erros + 1;
            $display("[FALHA] %0s (solicitacao=%b)", descricao, solicitacao);
        end else
            $display("[OK]    %0s", descricao);
    endtask

    initial begin
        $dumpfile("build/tb_botao_pedestre.vcd");
        $dumpvars(0, tb_botao_pedestre);
        clk = 0; rst_n = 0; botao_ativo = 0; limpa = 0; erros = 0;
        espera(2); rst_n = 1; espera(2);

        botao_ativo = 1; espera(1); botao_ativo = 0; espera(N + 4);
        confere(1'b0, "toque curto (repique) nao gera pedido");

        botao_ativo = 1; espera(N + 4); botao_ativo = 0; espera(N + 4);
        confere(1'b1, "pedido continua ativo apos soltar o botao");

        limpa = 1; espera(1); limpa = 0; espera(1);
        confere(1'b0, "limpa_solicitacao apaga o pedido");

        if (erros == 0) $display("RESULTADO: TODOS OS CASOS PASSARAM");
        else            $display("RESULTADO: %0d CASO(S) FALHARAM", erros);
        $finish;
    end
endmodule

final_project/build/tb_botao_pedestre.vcd
$date
	Tue Oct  6 20:22:25 2026
$end
$version
	Icarus Verilog
$end
$timescale
	1ps
$end
$scope module tb_botao_pedestre $end
$var wire 1 ! solicitacao $end
$var parameter 32 " N $end
$var reg 1 # botao_ativo $end
$var reg 1 $ clk $end
$var reg 1 % limpa $end
$var reg 1 & rst_n $end
$var integer 32 ' erros [31:0] $end
$scope module dut $end
$var wire 1 # botao_ativo $end
$var wire 1 $ clk $end
$var wire 1 % limpa_solicitacao $end
$var wire 1 ( pressionado_pulso $end
$var wire 1 & rst_n $end
$var wire 1 ) botao_estavel $end
$var parameter 32 * N_CICLOS $end
$var reg 1 + estavel_ant $end
$var reg 1 ! solicitacao_pedestre $end
$scope module u_debounce $end
$var wire 1 $ clk $end
$var wire 1 # entrada $end
$var wire 1 & rst_n $end
$var parameter 32 , LARGURA_CONT $end
$var parameter 32 - N_CICLOS $end
$var reg 3 . contador [2:0] $end
$var reg 1 ) saida $end
$var reg 2 / sinc [1:0] $end
$upscope $end
$upscope $end
$scope task confere $end
$var reg 384 0 descricao [383:0] $end
$var reg 1 1 esperado $end
$upscope $end
$scope task espera $end
$var integer 32 2 i [31:0] $end
$var integer 32 3 n [31:0] $end
$upscope $end
$upscope $end
$enddefinitions $end
$comment Show the parameter values. $end
$dumpall
b100 -
b11 ,
b100 *
b100 "
$end
#0
$dumpvars
b10 3
b0 2
x1
bx 0
b0 /
b0 .
0+
0)
0(
b0 '
0&
0%
0$
0#
0!
$end
#5000
1$
#6000
b1 2
#10000
0$
#15000
1$
#16000
1&
b0 2
#20000
0$
#25000
1$
#26000
b1 2
#30000
0$
#35000
1$
#36000
b1 3
1#
b0 2
#40000
0$
#45000
b1 /
1$
#46000
b1000 3
0#
b0 2
#50000
0$
#55000
b10 /
1$
#56000
b1 2
#60000
0$
#65000
b1 .
b0 /
1$
#66000
b10 2
#70000
0$
#75000
b0 .
1$
#76000
b11 2
#80000
0$
#85000
1$
#86000
b100 2
#90000
0$
#95000
1$
#96000
b101 2
#100000
0$
#105000
1$
#106000
b110 2
#110000
0$
#115000
1$
#116000
b111 2
#120000
0$
#125000
1$
#126000
1#
b1110100011011110111000101110101011001010010000001100011011101010111001001110100011011110010000000101000011100100110010101110000011010010111000101110101011001010010100100100000011011100110000101101111001000000110011101100101011100100110000100100000011100000110010101100100011010010110010001101111 0
01
b0 2
#130000
0$
#135000
b1 /
1$
#136000
b1 2
#140000
0$
#145000
b11 /
1$
#146000
b10 2
#150000
0$
#155000
b1 .
1$
#156000
b11 2
#160000
0$
#165000
b10 .
1$
#166000
b100 2
#170000
0$
#175000
b11 .
1$
#176000
b101 2
#180000
0$
#185000
1(
b0 .
1)
1$
#186000
b110 2
#190000
0$
#195000
0(
1+
1!
1$
#196000
b111 2
#200000
0$
#205000
1$
#206000
0#
b0 2
#210000
0$
#215000
b10 /
1$
#216000
b1 2
#220000
0$
#225000
b0 /
1$
#226000
b10 2
#230000
0$
#235000
b1 .
1$
#236000
b11 2
#240000
0$
#245000
b10 .
1$
#246000
b100 2
#250000
0$
#255000
b11 .
1$
#256000
b101 2
#260000
0$
#265000
b0 .
0)
1$
#266000
b110 2
#270000
0$
#275000
0+
1$
#276000
b111 2
#280000
0$
#285000
1$
#286000
b1 3
1%
b111000001100101011001000110100101100100011011110010000001100011011011110110111001110100011010010110111001110101011000010010000001100001011101000110100101110110011011110010000001100001011100000110111101110011001000000111001101101111011011000111010001100001011100100010000001101111001000000110001001101111011101000110000101101111 0
11
b0 2
#290000
0$
#295000
0!
1$
#296000
0%
b0 2
#300000
0$
#305000
1$
#306000
b110110001101001011011010111000001100001010111110111001101101111011011000110100101100011011010010111010001100001011000110110000101101111001000000110000101110000011000010110011101100001001000000110111100100000011100000110010101100100011010010110010001101111 0
01
b1 2
