final_project/rtl/contador_tempo.v
// contador_tempo: temporizador decrescente usado pela fsm_semaforo para
// medir a duracao de cada fase, em ticks (segundos).
//
// Parametro:
//   LARGURA - bits do contador
// Portas:
//   carrega       - 1: copia valor_inicial para o contador (prioridade sobre habilita)
//   habilita      - 1: decrementa 1 (ligado ao tick de 1 s); para em 0
//   valor_inicial - duracao a carregar
//   valor_atual   - tempo restante da fase
//   zerou         - 1 quando valor_atual == 0 (tempo da fase esgotado)
module contador_tempo #(
    parameter integer LARGURA = 6
) (
    input  wire               clk,
    input  wire               rst_n,
    input  wire               carrega,
    input  wire               habilita,
    input  wire [LARGURA-1:0] valor_inicial,
    output reg  [LARGURA-1:0] valor_atual,
    output wire               zerou
);
    always @(posedge clk or negedge rst_n) begin
        if (!rst_n)
            valor_atual <= {LARGURA{1'b0}};
        else if (carrega)
            valor_atual <= valor_inicial;
        else if (habilita && valor_atual != 0)
            valor_atual <= valor_atual - 1'b1;
    end

    assign zerou = (valor_atual == 0);
endmodule

final_project/tb/tb_contador_tempo.v
// tb_contador_tempo: verifica carga, decremento so' com habilita, parada
// em zero e prioridade de carrega sobre habilita.
`timescale 1ns/1ps
module tb_contador_tempo;
    reg        clk, rst_n, carrega, habilita;
    reg  [5:0] valor_inicial;
    wire [5:0] valor_atual;
    wire       zerou;
    integer erros;

    contador_tempo #(.LARGURA(6)) dut (
        .clk(clk), .rst_n(rst_n), .carrega(carrega), .habilita(habilita),
        .valor_inicial(valor_inicial), .valor_atual(valor_atual), .zerou(zerou)
    );

    always #5 clk = ~clk;

    task espera(input integer n);
        integer i;
        for (i = 0; i < n; i = i + 1) begin @(posedge clk); #1; end
    endtask

    task confere(input [5:0] esperado, input [8*40-1:0] descricao);
        if (valor_atual !== esperado || zerou !== (esperado == 0)) begin
            erros = erros + 1;
            $display("[FALHA] %0s (valor=%0d zerou=%b)", descricao, valor_atual, zerou);
        end else
            $display("[OK]    %0s (valor=%0d)", descricao, valor_atual);
    endtask

    initial begin
        $dumpfile("build/tb_contador_tempo.vcd");
        $dumpvars(0, tb_contador_tempo);
        clk = 0; rst_n = 0; carrega = 0; habilita = 0; valor_inicial = 6'd3; erros = 0;
        espera(2); rst_n = 1; espera(1);
        confere(6'd0, "zerado apos reset");

        carrega = 1; espera(1); carrega = 0;
        confere(6'd3, "carrega valor_inicial");

        espera(4);
        confere(6'd3, "sem habilita, nao decrementa");

        habilita = 1; espera(2);
        confere(6'd1, "decrementa 1 por ciclo habilitado");
        espera(3);
        confere(6'd0, "para em zero");

        carrega = 1; espera(1); carrega = 0; habilita = 0;
        confere(6'd3, "carrega tem prioridade sobre habilita");

        if (erros == 0) $display("RESULTADO: TODOS OS CASOS PASSARAM");
        else            $display("RESULTADO: %0d CASO(S) FALHARAM", erros);
        $finish;
    end
endmodule

final_project/build/tb_contador_tempo.vcd
$date
	Tue Oct  6 20:22:25 2026
$end
$version
	Icarus Verilog
$end
$timescale
	1ps
$end
$scope module tb_contador_tempo $end
$var wire 1 ! zerou $end
$var wire 6 " valor_atual [5:0] $end
$var reg 1 # carrega $end
$var reg 1 $ clk $end
$var reg 1 % habilita $end
$var reg 1 & rst_n $end
$var reg 6 ' valor_inicial [5:0] $end
$var integer 32 ( erros [31:0] $end
$scope module dut $end
$var wire 1 # carrega $end
$var wire 1 $ clk $end
$var wire 1 % habilita $end
$var wire 1 & rst_n $end
$var wire 6 ) valor_inicial [5:0] $end
$var wire 1 ! zerou $end
$var parameter 32 * LARGURA $end
$var reg 6 + valor_atual [5:0] $end
$upscope $end
$scope task confere $end
$var reg 320 , descricao [319:0] $end
$var reg 6 - esperado [5:0] $end
$upscope $end
$scope task espera $end
$var integer 32 . i [31:0] $end
$var integer 32 / n [31:0] $end
$upscope $end
$upscope $end
$enddefinitions $end
$comment Show the parameter values. $end
$dumpall
b110 *
$end
#0
$dumpvars
b10 /
b0 .
bx -
bx ,
b0 +
b11 )
b0 (
b11 '
0&
0%
0$
0#
b0 "
1!
$end
#5000
1$
#6000
b1 .
#10000
0$
#15000
1$
#16000
b1 /
1&
b0 .
#20000
0$
#25000
1$
#26000
1#
b111101001100101011100100110000101100100011011110010000001100001011100000110111101110011001000000111001001100101011100110110010101110100 ,
b0 -
b0 .
#30000
0$
#35000
0!
b11 "
b11 +
1$
#36000
b100 /
b11000110110000101110010011100100110010101100111011000010010000001110110011000010110110001101111011100100101111101101001011011100110100101100011011010010110000101101100 ,
b11 -
0#
b0 .
#40000
0$
#45000
1$
#46000
b1 .
#50000
0$
#55000
1$
#56000
b10 .
#60000
0$
#65000
1$
#66000
b11 .
#70000
0$
#75000
1$
#76000
b10 /
1%
b1110011011001010110110100100000011010000110000101100010011010010110110001101001011101000110000100101100001000000110111001100001011011110010000001100100011001010110001101110010011001010110110101100101011011100111010001100001 ,
b0 .
#80000
0$
#85000
b10 "
b10 +
1$
#86000
b1 .
#90000
0$
#95000
b1 "
b1 +
1$
#96000
b11 /
b11001000110010101100011011100100110010101101101011001010110111001110100011000010010000000110001001000000111000001101111011100100010000001100011011010010110001101101100011011110010000001101000011000010110001001101001011011000110100101110100011000010110010001101111 ,
b1 -
b0 .
#100000
0$
#105000
1!
b0 "
b0 +
1$
#106000
b1 .
#110000
0$
#115000
1$
#116000
b10 .
#120000
0$
#125000
1$
#126000
b1 /
1#
b11100000110000101110010011000010010000001100101011011010010000001111010011001010111001001101111 ,
b0 -
b0 .
#130000
0$
#135000
0!
b11 "
b11 +
1$
#136000
b1100011011000010111001001110010011001010110011101100001001000000111010001100101011011010010000001110000011100100110100101101111011100100110100101100100011000010110010001100101001000000111001101101111011000100111001001100101001000000110100001100001011000100110100101101100011010010111010001100001 ,
b11 -
0%
0#
b1 .
