final_project/rtl/debounce.v
// debounce: filtra uma entrada mecanica/ruidosa (botao ou sensor IR).
// Sincroniza a entrada assincrona com 2 flip-flops (evita metaestabilidade)
// e so' muda a saida depois que a entrada fica N_CICLOS ciclos seguidos
// no novo nivel. Usado por botao_pedestre e sensor_veiculo.
//
// Parametro:
//   N_CICLOS - ciclos de clk que a entrada precisa ficar estavel
//              (ex.: 540_000 ciclos = 20 ms a 27 MHz)
// Portas:
//   entrada - sinal bruto, ativo em nivel ALTO (assincrono ao clk)
//   saida   - sinal filtrado e sincronizado ao clk (repouso = 0)
module debounce #(
    parameter integer N_CICLOS = 540_000
) (
    input  wire clk,
    input  wire rst_n,
    input  wire entrada,
    output reg  saida
);
    localparam integer LARGURA_CONT = $clog2(N_CICLOS + 1);

    reg [1:0]              sinc;      // cadeia de sincronizacao; sinc[1] = entrada ja sincronizada
    reg [LARGURA_CONT-1:0] contador;  // ciclos seguidos em que sinc[1] difere de saida

    always @(posedge clk or negedge rst_n) begin
        if (!rst_n) begin
            sinc     <= 2'b00;
            contador <= {LARGURA_CONT{1'b0}};
            saida    <= 1'b0;
        end else begin
            sinc <= {sinc[0], entrada};

            if (sinc[1] == saida)
                contador <= {LARGURA_CONT{1'b0}};       // qualquer repique reinicia a contagem
            else if (contador == N_CICLOS - 1) begin
                saida    <= sinc[1];                    // estavel tempo suficiente: aceita o novo nivel
                contador <= {LARGURA_CONT{1'b0}};
            end else
                contador <= contador + 1'b1;
        end
    end
endmodule

final_project/tb/tb_debounce.v
// tb_debounce: verifica que repiques curtos sao ignorados e que um nivel
// estavel por N_CICLOS ciclos chega a saida (nos dois sentidos).
`timescale 1ns/1ps
module tb_debounce;
    localparam integer N = 4;   // ciclos de estabilidade usados no teste

    reg  clk, rst_n, entrada;
    wire saida;
    integer erros;              // casos que falharam

    debounce #(.N_CICLOS(N)) dut (.clk(clk), .rst_n(rst_n), .entrada(entrada), .saida(saida));

    always #5 clk = ~clk;

    // espera n bordas de subida de clk (e 1 ns para os registradores assentarem)
    task espera(input integer n);
        integer i;
        for (i = 0; i < n; i = i + 1) begin @(posedge clk); #1; end
    endtask

    task confere(input esperado, input [8*48-1:0] descricao);
        if (saida !== esperado) begin
            erros = erros + 1;
            $display("[FALHA] %0s (saida=%b)", descricao, saida);
        end else
            $display("[OK]    %0s", descricao);
    endtask

    initial begin
        $dumpfile("build/tb_debounce.vcd");
        $dumpvars(0, tb_debounce);
        clk = 0; rst_n = 0; entrada = 0; erros = 0;
        espera(2); rst_n = 1; espera(2);

        // repique: alterna a cada ciclo, nunca fica estavel N ciclos
        entrada = 1; espera(1); entrada = 0; espera(1);
        entrada = 1; espera(2); entrada = 0; espera(1);
        espera(N + 3);
        confere(1'b0, "repique ignorado");

        // nivel estavel: chega a saida apos 2 (sincronizador) + N ciclos
        entrada = 1; espera(N + 1);
        confere(1'b0, "saida ainda nao muda antes de N + 2 ciclos");
        espera(2);
        confere(1'b1, "nivel 1 estavel chega a saida");

        entrada = 0; espera(N + 3);
        confere(1'b0, "nivel 0 estavel chega a saida");

        if (erros == 0) $display("RESULTADO: TODOS OS CASOS PASSARAM");
        else            $display("RESULTADO: %0d CASO(S) FALHARAM", erros);
        $finish;
    end
endmodule

final_project/build/tb_debounce.vcd
$date
	Tue Oct  6 20:22:25 2026
$end
$version
	Icarus Verilog
$end
$timescale
	1ps
$end
$scope module tb_debounce $end
$var wire 1 ! saida $end
$var parameter 32 " N $end
$var reg 1 # clk $end
$var reg 1 $ entrada $end
$var reg 1 % rst_n $end
$var integer 32 & erros [31:0] $end
$scope module dut $end
$var wire 1 # clk $end
$var wire 1 $ entrada $end
$var wire 1 % rst_n $end
$var parameter 32 ' LARGURA_CONT $end
$var parameter 32 ( N_CICLOS $end
$var reg 3 ) contador [2:0] $end
$var reg 1 ! saida $end
$var reg 2 * sinc [1:0] $end
$upscope $end
$scope task confere $end
$var reg 384 + descricao [383:0] $end
$var reg 1 , esperado $end
$upscope $end
$scope task espera $end
$var integer 32 - i [31:0] $end
$var integer 32 . n [31:0] $end
$upscope $end
$upscope $end
$enddefinitions $end
$comment Show the parameter values. $end
$dumpall
b100 (
b11 '
b100 "
$end
#0
$dumpvars
b10 .
b0 -
x,
bx +
b0 *
b0 )
b0 &
0%
0$
0#
0!
$end
#5000
1#
#6000
b1 -
#10000
0#
#15000
1#
#16000
1%
b0 -
#20000
0#
#25000
1#
#26000
b1 -
#30000
0#
#35000
1#
#36000
b1 .
1$
b0 -
#40000
0#
#45000
b1 *
1#
#46000
0$
b0 -
#50000
0#
#55000
b10 *
1#
#56000
b10 .
1$
b0 -
#60000
0#
#65000
b1 )
b1 *
1#
#66000
b1 -
#70000
0#
#75000
b0 )
b11 *
1#
#76000
b1 .
0$
b0 -
#80000
0#
#85000
b1 )
b10 *
1#
#86000
b111 .
b0 -
#90000
0#
#95000
b10 )
b0 *
1#
#96000
b1 -
#100000
0#
#105000
b0 )
1#
#106000
b10 -
#110000
0#
#115000
1#
#116000
b11 -
#120000
0#
#125000
1#
#126000
b100 -
#130000
0#
#135000
1#
#136000
b101 -
#140000
0#
#145000
1#
#146000
b110 -
#150000
0#
#155000
1#
#156000
b101 .
1$
b1110010011001010111000001101001011100010111010101100101001000000110100101100111011011100110111101110010011000010110010001101111 +
0,
b0 -
#160000
0#
#165000
b1 *
1#
#166000
b1 -
#170000
0#
#175000
b11 *
1#
#176000
b10 -
#180000
0#
#185000
b1 )
1#
#186000
b11 -
#190000
0#
#195000
b10 )
1#
#196000
b100 -
#200000
0#
#205000
b11 )
1#
#206000
b10 .
b11100110110000101101001011001000110000100100000011000010110100101101110011001000110000100100000011011100110000101101111001000000110110101110101011001000110000100100000011000010110111001110100011001010111001100100000011001000110010100100000010011100010000000101011001000000011001000100000011000110110100101100011011011000110111101110011 +
b0 -
#210000
0#
#215000
b0 )
1!
1#
#216000
b1 -
#220000
0#
#225000
1#
#226000
b111 .
0$
b110111001101001011101100110010101101100001000000011000100100000011001010111001101110100011000010111011001100101011011000010000001100011011010000110010101100111011000010010000001100001001000000111001101100001011010010110010001100001 +
1,
b0 -
#230000
0#
#235000
b10 *
1#
#236000
b1 -
#240000
0#
#245000
b0 *
1#
#246000
b10 -
#250000
0#
#255000
b1 )
1#
#256000
b11 -
#260000
0#
#265000
b10 )
1#
#266000
b100 -
#270000
0#
#275000
b11 )
1#
#276000
b101 -
#280000
0#
#285000
b0 )
0!
1#
#286000
b110 -
#290000
0#
#295000
1#
#296000
b110111001101001011101100110010101101100001000000011000000100000011001010111001101110100011000010111011001100101011011000010000001100011011010000110010101100111011000010010000001100001001000000111001101100001011010010110010001100001 +
0,
b111 -
