final_project/rtl/contador_tempo.v
// contador_tempo: temporizador decrescente usado pela fsm_semaforo para
// medir a duracao de cada fase, em ticks (segundos).
//
// Parametro:
//   LARGURA - bits do contador
// Portas:
//   carrega       - 1: copia valor_inicial para o contador (prioridade sobre habilita)
//   habilita      - 1: decrementa 1 (ligado ao tick de 1 s); para em 0
//   valor_inicial - duracao a carregar
//   valor_atual   - tempo restante da fase
//   zerou         - 1 quando valor_atual == 0 (tempo da fase esgotado)
module contador_tempo #(
    parameter integer LARGURA = 6
) (
    input  wire               clk,
    input  wire               rst_n,
    input  wire               carrega,
    input  wire               habilita,
    input  wire [LARGURA-1:0] valor_inicial,
    output reg  [LARGURA-1:0] valor_atual,
    output wire               zerou
);
    always @(posedge clk or negedge rst_n) begin
        if (!rst_n)
            valor_atual <= {LARGURA{1'b0}};
        else if (carrega)
            valor_atual <= valor_inicial;
        else if (habilita && valor_atual != 0)
            valor_atual <= valor_atual - 1'b1;
    end

    assign zerou = (valor_atual == 0);
endmodule

final_project/rtl/fsm_semaforo.v
// fsm_semaforo: maquina de estados do cruzamento.
//
//   CARRO_VERDE --(pedido pendente e tempo de verde esgotado)--> CARRO_AMARELO
//   CARRO_AMARELO --(tempo_amarelo esgotado)--> PEDESTRE_VERDE
//   PEDESTRE_VERDE --(tempo_pedestre esgotado)--> CARRO_VERDE (apaga o pedido)
//
// Sem pedido, os carros ficam em verde indefinidamente. O tempo de verde
// (tempo_verde, que top_semaforo calcula a partir do fluxo medido) e'
// aplicado em dois momentos:
//   - ao entrar em CARRO_VERDE: verde minimo garantido aos carros;
//   - quando chega um pedido novo: o pedestre espera pelo menos
//     tempo_verde a partir do aperto (se ja faltava mais que isso, nada muda).
// Assim, fluxo baixo libera o pedestre mais rapido e fluxo alto o faz
// esperar mais, mesmo que o verde ja esteja aceso ha muito tempo.
//
// Seguranca: pedestre_verde so' e' 1 no estado PEDESTRE_VERDE, onde
// cor_carro e' forcada a vermelho. Estado invalido volta para CARRO_VERDE
// passando um ciclo com os dois sinais em vermelho.
//
// Parametro:
//   LARGURA_TEMPO - bits dos tempos e do contador (6 bits = ate 63 s)
// Portas:
//   tick                 - 1 pulso por segundo (prescaler)
//   solicitacao_pedestre - 1 enquanto ha pedido de travessia pendente
//   tempo_verde          - segundos de verde para os carros (depende do fluxo)
//   tempo_amarelo        - segundos de amarelo
//   tempo_pedestre       - segundos de verde para o pedestre
//   cor_carro            - cor dos carros: 00 = vermelho, 01 = amarelo, 10 = verde
//   pedestre_verde       - 1 = pedestre verde, 0 = pedestre vermelho
//   limpa_solicitacao    - 1 ciclo em 1 ao fim da travessia (apaga o pedido)
//   contagem_atual       - segundos restantes da fase corrente
module fsm_semaforo #(
    parameter integer LARGURA_TEMPO = 6
) (
    input  wire                     clk,
    input  wire                     rst_n,
    input  wire                     tick,
    input  wire                     solicitacao_pedestre,
    input  wire [LARGURA_TEMPO-1:0] tempo_verde,
    input  wire [LARGURA_TEMPO-1:0] tempo_amarelo,
    input  wire [LARGURA_TEMPO-1:0] tempo_pedestre,
    output reg  [1:0]               cor_carro,
    output reg                      pedestre_verde,
    output reg                      limpa_solicitacao,
    output wire [LARGURA_TEMPO-1:0] contagem_atual
);
    // codificacao dos estados
    localparam [1:0] CARRO_VERDE    = 2'd0;
    localparam [1:0] CARRO_AMARELO  = 2'd1;
    localparam [1:0] PEDESTRE_VERDE = 2'd2;

    // codificacao de cor_carro (a mesma usada no pacote de telemetria)
    localparam [1:0] COR_VERMELHO = 2'b00;
    localparam [1:0] COR_AMARELO  = 2'b01;
    localparam [1:0] COR_VERDE    = 2'b10;

    reg  [1:0]               estado;          // estado atual
    reg  [1:0]               prox_estado;     // estado do proximo ciclo
    reg                      iniciou;         // 0 so' no 1o ciclo apos reset: forca a 1a carga do contador
    reg                      solicitacao_ant; // solicitacao_pedestre no ciclo anterior
    wire                     pedido_novo;     // 1 no ciclo em que o pedido acabou de chegar
    reg                      carrega_cont;    // 1: recarrega o contador neste ciclo
    reg  [LARGURA_TEMPO-1:0] valor_carga;     // valor carregado quando carrega_cont = 1
    wire                     tempo_esgotado;  // contador da fase chegou a 0

    contador_tempo #(.LARGURA(LARGURA_TEMPO)) u_contador (
        .clk(clk), .rst_n(rst_n),
        .carrega(carrega_cont), .habilita(tick),
        .valor_inicial(valor_carga),
        .valor_atual(contagem_atual), .zerou(tempo_esgotado)
    );

    assign pedido_novo = solicitacao_pedestre & ~solicitacao_ant;

    always @(posedge clk or negedge rst_n) begin
        if (!rst_n) begin
            estado          <= CARRO_VERDE;
            iniciou         <= 1'b0;
            solicitacao_ant <= 1'b0;
        end else begin
            estado          <= prox_estado;
            iniciou         <= 1'b1;
            solicitacao_ant <= solicitacao_pedestre;
        end
    end

    // proximo estado e saidas (Moore: as cores dependem so' de "estado")
    always @(*) begin
        prox_estado       = estado;
        cor_carro         = COR_VERMELHO;
        pedestre_verde    = 1'b0;
        limpa_solicitacao = 1'b0;

        case (estado)
            CARRO_VERDE: begin
                cor_carro = COR_VERDE;
                // pedido_novo bloqueia a troca no ciclo em que o pedido
                // chega, para dar tempo de recarregar a espera do pedestre
                if (tempo_esgotado && solicitacao_pedestre && !pedido_novo)
                    prox_estado = CARRO_AMARELO;
            end
            CARRO_AMARELO: begin
                cor_carro = COR_AMARELO;
                if (tempo_esgotado)
                    prox_estado = PEDESTRE_VERDE;
            end
            PEDESTRE_VERDE: begin
                cor_carro      = COR_VERMELHO;
                pedestre_verde = 1'b1;
                if (tempo_esgotado) begin
                    prox_estado       = CARRO_VERDE;
                    limpa_solicitacao = 1'b1;
                end
            end
            default: prox_estado = CARRO_VERDE;   // estado invalido: tudo vermelho por 1 ciclo
        endcase
    end

    // carga do contador: duracao da fase que esta COMECANDO (prox_estado),
    // ou a espera do pedestre quando um pedido novo chega durante o verde
    always @(*) begin
        case (prox_estado)
            CARRO_AMARELO:  valor_carga = tempo_amarelo;
            PEDESTRE_VERDE: valor_carga = tempo_pedestre;
            default:        valor_carga = tempo_verde;
        endcase

        carrega_cont = !iniciou
                    || (prox_estado != estado)
                    || (estado == CARRO_VERDE && pedido_novo && contagem_atual < tempo_verde);
    end
endmodule

final_project/tb/tb_fsm_semaforo.v
// tb_fsm_semaforo: verifica a maquina de estados com tick a cada ciclo
// (1 ciclo = 1 "segundo"):
//   - estado inicial e permanencia em verde sem pedido;
//   - pedido com o verde ja longo: o pedestre espera tempo_verde;
//   - pedido logo no inicio do verde: a espera nao soma com o verde minimo;
//   - duracao do amarelo e da travessia, e o pedido apagado no fim;
//   - durante todo o teste, nunca pedestre verde com carro fora do vermelho.
`timescale 1ns/1ps
module tb_fsm_semaforo;
    localparam integer T_VERDE    = 5;
    localparam integer T_AMARELO  = 3;
    localparam integer T_PEDESTRE = 4;

    localparam [1:0] VERMELHO = 2'b00, AMARELO = 2'b01, VERDE = 2'b10;

    reg        clk, rst_n;
    reg        solicitacao;      // modela o latch do botao_pedestre
    wire [1:0] cor_carro;
    wire       pedestre_verde, limpa_solicitacao;
    wire [5:0] contagem;
    integer    erros, violacoes, ciclos;

    fsm_semaforo #(.LARGURA_TEMPO(6)) dut (
        .clk(clk), .rst_n(rst_n), .tick(1'b1),
        .solicitacao_pedestre(solicitacao),
        .tempo_verde(T_VERDE[5:0]), .tempo_amarelo(T_AMARELO[5:0]), .tempo_pedestre(T_PEDESTRE[5:0]),
        .cor_carro(cor_carro), .pedestre_verde(pedestre_verde),
        .limpa_solicitacao(limpa_solicitacao), .contagem_atual(contagem)
    );

    always #5 clk = ~clk;

    // o pedido e' apagado pela FSM, como no botao_pedestre
    always @(posedge clk) if (limpa_solicitacao) solicitacao <= 1'b0;

    // invariante de seguranca, conferido em todo ciclo
    always @(negedge clk)
        if (rst_n && pedestre_verde && cor_carro !== VERMELHO) violacoes = violacoes + 1;

    task espera(input integer n);
        integer i;
        for (i = 0; i < n; i = i + 1) begin @(posedge clk); #1; end
    endtask

    // conta ciclos ate cor_carro mudar; termina na mudanca ou apos 200 ciclos
    task mede_fase(output integer n);
        reg [1:0] cor_inicial;
        begin
            cor_inicial = cor_carro; n = 0;
            while (cor_carro === cor_inicial && n < 200) begin espera(1); n = n + 1; end
        end
    endtask

    task confere(input ok, input [8*64-1:0] descricao);
        if (!ok) begin
            erros = erros + 1;
            $display("[FALHA] %0s (cor_carro=%b pedestre_verde=%b ciclos=%0d)",
                     descricao, cor_carro, pedestre_verde, ciclos);
        end else
            $display("[OK]    %0s", descricao);
    endtask

    initial begin
        $dumpfile("build/tb_fsm_semaforo.vcd");
        $dumpvars(0, tb_fsm_semaforo);
        clk = 0; rst_n = 0; solicitacao = 0; erros = 0; violacoes = 0; ciclos = 0;
        espera(2); rst_n = 1; espera(1);

        confere(cor_carro == VERDE && !pedestre_verde, "inicia com carros verdes e pedestre vermelho");

        espera(4 * T_VERDE);
        confere(cor_carro == VERDE, "sem pedido, carros continuam verdes");

        // pedido com o verde minimo ja cumprido: espera tempo_verde a partir do aperto
        solicitacao = 1;
        mede_fase(ciclos);
        confere(cor_carro == AMARELO && ciclos >= T_VERDE && ciclos <= T_VERDE + 2,
                "pedido tardio: carros ficam mais tempo_verde em verde");

        mede_fase(ciclos);
        confere(cor_carro == VERMELHO && pedestre_verde && ciclos >= T_AMARELO && ciclos <= T_AMARELO + 1,
                "amarelo dura tempo_amarelo e abre para o pedestre");

        mede_fase(ciclos);
        confere(cor_carro == VERDE && !pedestre_verde && ciclos >= T_PEDESTRE && ciclos <= T_PEDESTRE + 1,
                "travessia dura tempo_pedestre e volta ao verde");
        confere(solicitacao == 0, "pedido apagado ao fim da travessia");

        // pedido 1 ciclo apos o inicio do verde: a espera e' tempo_verde a
        // partir do aperto (+2 ciclos de latencia), e nao verde minimo + espera
        espera(1); solicitacao = 1;
        mede_fase(ciclos);
        confere(cor_carro == AMARELO && ciclos >= T_VERDE && ciclos <= T_VERDE + 2,
                "pedido no inicio do verde nao soma esperas");

        espera(T_AMARELO + T_PEDESTRE + 4);
        confere(violacoes == 0, "nunca pedestre verde com carro fora do vermelho");

        if (erros == 0) $display("RESULTADO: TODOS OS CASOS PASSARAM");
        else            $display("RESULTADO: %0d CASO(S) FALHARAM", erros);
        $finish;
    end
endmodule

final_project/build/tb_fsm_semaforo.vcd
$date
	Tue Oct  6 23:32:54 2026
$end
$version
	Icarus Verilog
$end
$timescale
	1ps
$end
$scope module tb_fsm_semaforo $end
$var wire 1 ! pedestre_verde $end
$var wire 1 " limpa_solicitacao $end
$var wire 2 # cor_carro [1:0] $end
$var wire 6 $ contagem [5:0] $end
$var parameter 2 % AMARELO $end
$var parameter 32 & T_AMARELO $end
$var parameter 32 ' T_PEDESTRE $end
$var parameter 32 ( T_VERDE $end
$var parameter 2 ) VERDE $end
$var parameter 2 * VERMELHO $end
$var reg 1 + clk $end
$var reg 1 , rst_n $end
$var reg 1 - solicitacao $end
$var integer 32 . ciclos [31:0] $end
$var integer 32 / erros [31:0] $end
$var integer 32 0 violacoes [31:0] $end
$scope module dut $end
$var wire 1 + clk $end
$var wire 1 1 pedido_novo $end
$var wire 1 , rst_n $end
$var wire 1 - solicitacao_pedestre $end
$var wire 6 2 tempo_amarelo [5:0] $end
$var wire 6 3 tempo_pedestre [5:0] $end
$var wire 6 4 tempo_verde [5:0] $end
$var wire 1 5 tick $end
$var wire 1 6 tempo_esgotado $end
$var wire 6 7 contagem_atual [5:0] $end
$var parameter 2 8 CARRO_AMARELO $end
$var parameter 2 9 CARRO_VERDE $end
$var parameter 2 : COR_AMARELO $end
$var parameter 2 ; COR_VERDE $end
$var parameter 2 < COR_VERMELHO $end
$var parameter 32 = LARGURA_TEMPO $end
$var parameter 2 > PEDESTRE_VERDE $end
$var reg 1 ? carrega_cont $end
$var reg 2 @ cor_carro [1:0] $end
$var reg 2 A estado [1:0] $end
$var reg 1 B iniciou $end
$var reg 1 " limpa_solicitacao $end
$var reg 1 ! pedestre_verde $end
$var reg 2 C prox_estado [1:0] $end
$var reg 1 D solicitacao_ant $end
$var reg 6 E valor_carga [5:0] $end
$scope module u_contador $end
$var wire 1 ? carrega $end
$var wire 1 + clk $end
$var wire 1 5 habilita $end
$var wire 1 , rst_n $end
$var wire 6 F valor_inicial [5:0] $end
$var wire 1 6 zerou $end
$var parameter 32 G LARGURA $end
$var reg 6 H valor_atual [5:0] $end
$upscope $end
$upscope $end
$scope task confere $end
$var reg 512 I descricao [511:0] $end
$var reg 1 J ok $end
$upscope $end
$scope task espera $end
$var integer 32 K i [31:0] $end
$var integer 32 L n [31:0] $end
$upscope $end
$scope task mede_fase $end
$var reg 2 M cor_inicial [1:0] $end
$var integer 32 N n [31:0] $end
$upscope $end
$upscope $end
$enddefinitions $end
$comment Show the parameter values. $end
$dumpall
b110 G
b10 >
b110 =
b0 <
b10 ;
b1 :
b0 9
b1 8
b0 *
b10 )
b101 (
b100 '
b11 &
b1 %
$end
#0
$dumpvars
bx N
bx M
b10 L
b0 K
xJ
bx I
b0 H
b101 F
b101 E
0D
b0 C
0B
b0 A
b10 @
1?
b0 7
16
15
b101 4
b100 3
b11 2
01
b0 0
b0 /
b0 .
0-
0,
0+
b0 $
b10 #
0"
0!
$end
#5000
1+
#6000
b1 K
#10000
0+
#15000
1+
#16000
b1 L
1,
b0 K
#20000
0+
#25000
b10 #
b10 @
0?
1B
06
b101 $
b101 7
b101 H
1+
#26000
b10100 L
b110100101101110011010010110001101101001011000010010000001100011011011110110110100100000011000110110000101110010011100100110111101110011001000000111011001100101011100100110010001100101011100110010000001100101001000000111000001100101011001000110010101110011011101000111001001100101001000000111011001100101011100100110110101100101011011000110100001101111 I
1J
b0 K
#30000
0+
#35000
b100 $
b100 7
b100 H
1+
#36000
b1 K
#40000
0+
#45000
b11 $
b11 7
b11 H
1+
#46000
b10 K
#50000
0+
#55000
b10 $
b10 7
b10 H
1+
#56000
b11 K
#60000
0+
#65000
b1 $
b1 7
b1 H
1+
#66000
b100 K
#70000
0+
#75000
b10 #
b10 @
16
b0 $
b0 7
b0 H
1+
#76000
b101 K
#80000
0+
#85000
1+
#86000
b110 K
#90000
0+
#95000
1+
#96000
b111 K
#100000
0+
#105000
1+
#106000
b1000 K
#110000
0+
#115000
1+
#116000
b1001 K
#120000
0+
#125000
1+
#126000
b1010 K
#130000
0+
#135000
1+
#136000
b1011 K
#140000
0+
#145000
1+
#146000
b1100 K
#150000
0+
#155000
1+
#156000
b1101 K
#160000
0+
#165000
1+
#166000
b1110 K
#170000
0+
#175000
1+
#176000
b1111 K
#180000
0+
#185000
1+
#186000
b10000 K
#190000
0+
#195000
1+
#196000
b10001 K
#200000
0+
#205000
1+
#206000
b10010 K
#210000
0+
#215000
1+
#216000
b10011 K
#220000
0+
#225000
1+
#226000
1?
b101 E
b101 F
11
b0 C
b10 #
b10 @
b1 L
b0 N
b10 M
1-
b111001101100101011011010010000001110000011001010110010001101001011001000110111100101100001000000110001101100001011100100111001001101111011100110010000001100011011011110110111001110100011010010110111001110101011000010110110100100000011101100110010101110010011001000110010101110011 I
b0 K
#230000
0+
#235000
01
b10 #
b10 @
0?
06
b101 $
b101 7
b101 H
1D
1+
#236000
b1 N
b0 K
#240000
0+
#245000
b100 $
b100 7
b100 H
1+
#246000
b10 N
b0 K
#250000
0+
#255000
b11 $
b11 7
b11 H
1+
#256000
b11 N
b0 K
#260000
0+
#265000
b10 $
b10 7
b10 H
1+
#266000
b100 N
b0 K
#270000
0+
#275000
b1 $
b1 7
b1 H
1+
#276000
b101 N
b0 K
#280000
0+
#285000
1?
b11 E
b11 F
b1 C
b10 #
b10 @
16
b0 $
b0 7
b0 H
1+
#286000
b110 N
b0 K
#290000
0+
#295000
0?
b1 #
b1 @
06
b11 $
b11 7
b11 H
b1 A
1+
#296000
b1 M
b111000001100101011001000110100101100100011011110010000001110100011000010111001001100100011010010110111100111010001000000110001101100001011100100111001001101111011100110010000001100110011010010110001101100001011011010010000001101101011000010110100101110011001000000111010001100101011011010111000001101111010111110111011001100101011100100110010001100101001000000110010101101101001000000111011001100101011100100110010001100101 I
b111 .
b0 N
b0 K
#300000
0+
#305000
b10 $
b10 7
b10 H
1+
#306000
b1 N
b0 K
#310000
0+
#315000
b1 $
b1 7
b1 H
1+
#316000
b10 N
b0 K
#320000
0+
#325000
1?
b100 E
b100 F
b10 C
b1 #
b1 @
16
b0 $
b0 7
b0 H
1+
#326000
b11 N
b0 K
#330000
0+
#335000
0?
1!
b0 #
b0 @
06
b100 $
b100 7
b100 H
b10 A
1+
#336000
b0 M
b1100001011011010110000101110010011001010110110001101111001000000110010001110101011100100110000100100000011101000110010101101101011100000110111101011111011000010110110101100001011100100110010101101100011011110010000001100101001000000110000101100010011100100110010100100000011100000110000101110010011000010010000001101111001000000111000001100101011001000110010101110011011101000111001001100101 I
b100 .
b0 N
b0 K
#340000
0+
#345000
b11 $
b11 7
b11 H
1+
#346000
b1 N
b0 K
#350000
0+
#355000
b10 $
b10 7
b10 H
1+
#356000
b10 N
b0 K
#360000
0+
#365000
b1 $
b1 7
b1 H
1+
#366000
b11 N
b0 K
#370000
0+
#375000
1?
b101 E
b101 F
1"
b0 C
1!
16
b0 $
b0 7
b0 H
1+
#376000
b100 N
b0 K
#380000
0+
#385000
0?
b10 #
b10 @
0"
0!
b0 A
06
b101 $
b101 7
b101 H
0-
1+
#386000
b1110000011001010110010001101001011001000110111100100000011000010111000001100001011001110110000101100100011011110010000001100001011011110010000001100110011010010110110100100000011001000110000100100000011101000111001001100001011101100110010101110011011100110110100101100001 I
b101 .
b101 N
b0 K
#390000
0+
#395000
b100 $
b100 7
b100 H
0D
1+
#396000
1?
11
b10 #
b10 @
b0 N
b10 M
1-
b0 K
#400000
0+
#405000
b10 #
b10 @
01
0?
1D
b101 $
b101 7
b101 H
1+
#406000
b1 N
b0 K
#410000
0+
#415000
b100 $
b100 7
b100 H
1+
#416000
b10 N
b0 K
#420000
0+
#425000
b11 $
b11 7
b11 H
1+
#426000
b11 N
b0 K
#430000
0+
#435000
b10 $
b10 7
b10 H
1+
#436000
b100 N
b0 K
#440000
0+
#445000
b1 $
b1 7
b1 H
1+
#446000
b101 N
b0 K
#450000
0+
#455000
1?
b11 E
b11 F
b1 C
b10 #
b10 @
16
b0 $
b0 7
b0 H
1+
#456000
b110 N
b0 K
#460000
0+
#465000
b1 #
b1 @
0?
b1 A
06
b11 $
b11 7
b11 H
1+
#466000
b1011 L
b11100000110010101100100011010010110010001101111001000000110111001101111001000000110100101101110011010010110001101101001011011110010000001100100011011110010000001110110011001010111001001100100011001010010000001101110011000010110111100100000011100110110111101101101011000010010000001100101011100110111000001100101011100100110000101110011 I
b111 .
b111 N
b0 K
#470000
0+
#475000
b10 $
b10 7
b10 H
1+
#476000
b1 K
#480000
0+
#485000
b1 $
b1 7
b1 H
1+
#486000
b10 K
#490000
0+
#495000
1?
b100 E
b100 F
b10 C
b1 #
b1 @
16
b0 $
b0 7
b0 H
1+
#496000
b11 K
#500000
0+
#505000
1!
b0 #
b0 @
0?
b10 A
06
b100 $
b100 7
b100 H
1+
#506000
b100 K
#510000
0+
#515000
b11 $
b11 7
b11 H
1+
#516000
b101 K
#520000
0+
#525000
b10 $
b10 7
b10 H
1+
#526000
b110 K
#530000
0+
#535000
b1 $
b1 7
b1 H
1+
#536000
b111 K
#540000
0+
#545000
1?
b101 E
b101 F
1"
b0 C
1!
16
b0 $
b0 7
b0 H
1+
#546000
b1000 K
#550000
0+
#555000
0?
b10 #
b10 @
0"
0!
06
b101 $
b101 7
b101 H
b0 A
0-
1+
#556000
b1001 K
#560000
0+
#565000
0D
b100 $
b100 7
b100 H
1+
#566000
b1010 K
#570000
0+
#575000
b11 $
b11 7
b11 H
1+
#576000
b110111001110101011011100110001101100001001000000111000001100101011001000110010101110011011101000111001001100101001000000111011001100101011100100110010001100101001000000110001101101111011011010010000001100011011000010111001001110010011011110010000001100110011011110111001001100001001000000110010001101111001000000111011001100101011100100110110101100101011011000110100001101111 I
b1011 K
