final_project/rtl/media_movel_dsp.v
// media_movel_dsp: media movel das ultimas 5 amostras de fluxo e
// classificacao do transito em baixo/medio/alto. A soma da janela e'
// mantida incrementalmente (soma + amostra nova - amostra que sai, lida
// da bram_historico) e a divisao por 5 vira uma multiplicacao pelo
// reciproco em ponto fixo, mapeada no bloco DSP (MULT18X18) da FPGA.
//
// Parametros:
//   LIMIAR_BAIXO - media <= LIMIAR_BAIXO  -> fluxo baixo
//   LIMIAR_ALTO  - media >  LIMIAR_ALTO   -> fluxo alto (entre os dois: medio)
// Portas:
//   nova_amostra   - 1 ciclo em 1: chegou a contagem de uma janela
//   amostra        - veiculos contados na janela que acabou de fechar
//   amostra_saindo - amostra de 5 janelas atras (da BRAM), que sai da media
//   media          - media arredondada das ultimas 5 amostras
//   nivel_fluxo    - 00 = baixo, 01 = medio, 10 = alto
module media_movel_dsp #(
    parameter integer LIMIAR_BAIXO = 1,
    parameter integer LIMIAR_ALTO  = 3
) (
    input  wire       clk,
    input  wire       rst_n,
    input  wire       nova_amostra,
    input  wire [7:0] amostra,
    input  wire [7:0] amostra_saindo,
    output reg  [7:0] media,
    output reg  [1:0] nivel_fluxo
);
    localparam integer N_JANELA      = 5;          // amostras na media
    localparam [16:0]  RECIPROCO_Q16 = 17'd13107;  // round(65536 / 5): 1/5 em ponto fixo Q16

    reg  [2:0]  amostras_validas;  // amostras ja na janela (satura em N_JANELA)
    reg  [10:0] soma;              // soma da janela (5 x 255 = 1275 cabe em 11 bits)
    wire [7:0]  valor_saindo;      // amostra_saindo, ou 0 enquanto a janela ainda enche
    wire [10:0] soma_nova;         // soma ja com a amostra que entra e sem a que sai
    (* syn_dspstyle = "dsp" *)
    wire [27:0] produto;           // soma_nova * (1/5) em Q16 -> bloco DSP
    wire [27:0] produto_arred;     // produto + 0,5 (arredonda ao descartar a parte fracionaria)
    wire [7:0]  media_nova;        // parte inteira de produto_arred = round(soma_nova / 5)

    assign valor_saindo  = (amostras_validas == N_JANELA) ? amostra_saindo : 8'd0;
    assign soma_nova     = soma - valor_saindo + amostra;
    assign produto       = soma_nova * RECIPROCO_Q16;
    assign produto_arred = produto + 28'd32768;
    assign media_nova    = produto_arred[23:16];

    always @(posedge clk or negedge rst_n) begin
        if (!rst_n) begin
            amostras_validas <= 3'd0;
            soma             <= 11'd0;
            media            <= 8'd0;
            nivel_fluxo      <= 2'b00;
        end else if (nova_amostra) begin
            if (amostras_validas != N_JANELA)
                amostras_validas <= amostras_validas + 3'd1;
            soma  <= soma_nova;
            media <= media_nova;

            if (media_nova <= LIMIAR_BAIXO)
                nivel_fluxo <= 2'b00;
            else if (media_nova <= LIMIAR_ALTO)
                nivel_fluxo <= 2'b01;
            else
                nivel_fluxo <= 2'b10;
        end
    end
endmodule

final_project/rtl/bram_historico.v
// bram_historico: historico circular de 256 amostras de fluxo (veiculos
// contados por janela de medicao), mapeado em um bloco BSRAM da Tang Nano
// 4K. top_semaforo grava cada amostra nova e le a amostra que esta saindo
// da janela da media movel (media_movel_dsp).
//
// A memoria nao tem reset (requisito para virar BSRAM); quem garante que
// conteudo antigo nao entra na media e' o contador de amostras validas
// do media_movel_dsp.
//
// Portas:
//   escreve          - 1 ciclo em 1: grava dado_escrita e avanca o ponteiro
//   dado_escrita     - amostra a gravar
//   endereco_leitura - posicao a ler
//   dado_leitura     - conteudo de endereco_leitura (leitura sincrona: 1 ciclo de atraso)
//   ponteiro_escrita - posicao onde a proxima amostra sera gravada (volta a 0 apos 255)
module bram_historico (
    input  wire       clk,
    input  wire       rst_n,
    input  wire       escreve,
    input  wire [7:0] dado_escrita,
    input  wire [7:0] endereco_leitura,
    output reg  [7:0] dado_leitura,
    output reg  [7:0] ponteiro_escrita
);
    (* ram_style = "block", syn_ramstyle = "block_ram" *)
    reg [7:0] memoria [0:255];   // 256 amostras de 8 bits

    always @(posedge clk) begin
        if (escreve)
            memoria[ponteiro_escrita] <= dado_escrita;
        dado_leitura <= memoria[endereco_leitura];
    end

    always @(posedge clk or negedge rst_n) begin
        if (!rst_n)
            ponteiro_escrita <= 8'd0;
        else if (escreve)
            ponteiro_escrita <= ponteiro_escrita + 8'd1;
    end
endmodule

final_project/tb/tb_media_movel_dsp.v
// tb_media_movel_dsp: liga bram_historico + media_movel_dsp do mesmo jeito
// que top_semaforo e compara, a cada amostra, a media e o nivel de fluxo
// com um modelo de referencia (media arredondada das ultimas 5 amostras).
// Antes do teste a BRAM e' suja com lixo para provar que conteudo antigo
// nao entra na media depois do reset.
`timescale 1ns/1ps
module tb_media_movel_dsp;
    localparam integer LIMIAR_BAIXO = 1;
    localparam integer LIMIAR_ALTO  = 3;
    localparam integer N_AMOSTRAS   = 14;

    reg        clk, rst_n, nova_amostra;
    reg  [7:0] amostra;
    wire [7:0] ponteiro, amostra_saindo, media;
    wire [1:0] nivel_fluxo;

    reg  [7:0] sequencia [0:N_AMOSTRAS-1];  // amostras aplicadas, em ordem
    integer    i, j, soma_ref, media_ref, nivel_ref, erros;

    bram_historico u_historico (
        .clk(clk), .rst_n(rst_n),
        .escreve(nova_amostra), .dado_escrita(amostra),
        .endereco_leitura(ponteiro - 8'd5), .dado_leitura(amostra_saindo),
        .ponteiro_escrita(ponteiro)
    );

    media_movel_dsp #(.LIMIAR_BAIXO(LIMIAR_BAIXO), .LIMIAR_ALTO(LIMIAR_ALTO)) dut (
        .clk(clk), .rst_n(rst_n),
        .nova_amostra(nova_amostra), .amostra(amostra), .amostra_saindo(amostra_saindo),
        .media(media), .nivel_fluxo(nivel_fluxo)
    );

    always #5 clk = ~clk;

    task espera(input integer n);
        integer k;
        for (k = 0; k < n; k = k + 1) begin @(posedge clk); #1; end
    endtask

    // aplica uma amostra e espera a BRAM atualizar a leitura (como no top,
    // onde as amostras chegam com segundos de intervalo)
    task aplica(input [7:0] valor);
        begin
            amostra = valor; nova_amostra = 1; espera(1);
            nova_amostra = 0; espera(3);
        end
    endtask

    initial begin
        $dumpfile("build/tb_media_movel_dsp.vcd");
        $dumpvars(0, tb_media_movel_dsp);
        clk = 0; rst_n = 0; nova_amostra = 0; amostra = 0; erros = 0;
        sequencia[0]  = 0;  sequencia[1]  = 1;  sequencia[2]  = 2;  sequencia[3]  = 3;
        sequencia[4]  = 4;  sequencia[5]  = 8;  sequencia[6]  = 8;  sequencia[7]  = 8;
        sequencia[8]  = 8;  sequencia[9]  = 0;  sequencia[10] = 0;  sequencia[11] = 0;
        sequencia[12] = 0;  sequencia[13] = 0;
        espera(2); rst_n = 1; espera(1);

        // suja as 8 primeiras posicoes da BRAM com 200 e reseta de novo
        // (o reset zera o ponteiro e a media, mas nao a memoria)
        for (i = 0; i < 8; i = i + 1) aplica(8'd200);
        rst_n = 0; espera(2); rst_n = 1; espera(1);

        // aplica cada amostra da sequencia; termina apos a ultima
        for (i = 0; i < N_AMOSTRAS; i = i + 1) begin
            aplica(sequencia[i]);

            soma_ref = 0;
            for (j = (i >= 4 ? i - 4 : 0); j <= i; j = j + 1)
                soma_ref = soma_ref + sequencia[j];
            media_ref = (2 * soma_ref + 5) / 10;   // round(soma / 5)
            nivel_ref = (media_ref <= LIMIAR_BAIXO) ? 0 : (media_ref <= LIMIAR_ALTO) ? 1 : 2;

            if (media !== media_ref || nivel_fluxo !== nivel_ref) begin
                erros = erros + 1;
                $display("[FALHA] amostra %0d=%0d: media=%0d nivel=%0d, esperado media=%0d nivel=%0d",
                         i, sequencia[i], media, nivel_fluxo, media_ref, nivel_ref);
            end else
                $display("[OK]    amostra %0d=%0d: media=%0d nivel=%0d", i, sequencia[i], media, nivel_fluxo);
        end

        if (erros == 0) $display("RESULTADO: TODOS OS CASOS PASSARAM");
        else            $display("RESULTADO: %0d CASO(S) FALHARAM", erros);
        $finish;
    end
endmodule

final_project/build/tb_media_movel_dsp.vcd
$date
	Tue Oct  6 23:32:54 2026
$end
$version
	Icarus Verilog
$end
$timescale
	1ps
$end
$scope module tb_media_movel_dsp $end
$var wire 8 ! ponteiro [7:0] $end
$var wire 2 " nivel_fluxo [1:0] $end
$var wire 8 # media [7:0] $end
$var wire 8 $ amostra_saindo [7:0] $end
$var parameter 32 % LIMIAR_ALTO $end
$var parameter 32 & LIMIAR_BAIXO $end
$var parameter 32 ' N_AMOSTRAS $end
$var reg 8 ( amostra [7:0] $end
$var reg 1 ) clk $end
$var reg 1 * nova_amostra $end
$var reg 1 + rst_n $end
$var integer 32 , erros [31:0] $end
$var integer 32 - i [31:0] $end
$var integer 32 . j [31:0] $end
$var integer 32 / media_ref [31:0] $end
$var integer 32 0 nivel_ref [31:0] $end
$var integer 32 1 soma_ref [31:0] $end
$scope module dut $end
$var wire 8 2 amostra [7:0] $end
$var wire 1 ) clk $end
$var wire 1 * nova_amostra $end
$var wire 1 + rst_n $end
$var wire 8 3 valor_saindo [7:0] $end
$var wire 11 4 soma_nova [10:0] $end
$var wire 28 5 produto_arred [27:0] $end
$var wire 28 6 produto [27:0] $end
$var wire 8 7 media_nova [7:0] $end
$var wire 8 8 amostra_saindo [7:0] $end
$var parameter 32 9 LIMIAR_ALTO $end
$var parameter 32 : LIMIAR_BAIXO $end
$var parameter 32 ; N_JANELA $end
$var parameter 17 < RECIPROCO_Q16 $end
$var reg 3 = amostras_validas [2:0] $end
$var reg 8 > media [7:0] $end
$var reg 2 ? nivel_fluxo [1:0] $end
$var reg 11 @ soma [10:0] $end
$upscope $end
$scope module u_historico $end
$var wire 1 ) clk $end
$var wire 8 A dado_escrita [7:0] $end
$var wire 8 B endereco_leitura [7:0] $end
$var wire 1 * escreve $end
$var wire 1 + rst_n $end
$var reg 8 C dado_leitura [7:0] $end
$var reg 8 D ponteiro_escrita [7:0] $end
$upscope $end
$scope task aplica $end
$var reg 8 E valor [7:0] $end
$upscope $end
$scope task espera $end
$var integer 32 F k [31:0] $end
$var integer 32 G n [31:0] $end
$upscope $end
$upscope $end
$enddefinitions $end
$comment Show the parameter values. $end
$dumpall
b11001100110011 <
b101 ;
b1 :
b11 9
b1110 '
b1 &
b11 %
$end
#0
$dumpvars
b10 G
b0 F
bx E
b0 D
bx C
b11111011 B
b0 A
b0 @
b0 ?
b0 >
b0 =
bx 8
b0 7
b0 6
b1000000000000000 5
b0 4
b0 3
b0 2
bx 1
bx 0
bx /
bx .
bx -
b0 ,
0+
0*
0)
b0 (
bx $
b0 #
b0 "
b0 !
$end
#5000
1)
#6000
b1 F
#10000
0)
#15000
1)
#16000
b1 G
1+
b0 F
#20000
0)
#25000
1)
#26000
b101000 7
1*
b1010000111111111011000 5
b1001111111111111011000 6
b11001000 4
b11001000 (
b11001000 2
b11001000 A
b11001000 E
b0 -
b0 F
#30000
0)
#35000
b1010000 7
b11111100 B
b1 !
b1 D
b10 "
b10 ?
b101000 #
b101000 >
b10100000111111110110000 5
b10011111111111110110000 6
b110010000 4
b11001000 @
b1 =
1)
#36000
b11 G
0*
b0 F
#40000
0)
#45000
1)
#46000
b1 F
#50000
0)
#55000
1)
#56000
b10 F
#60000
0)
#65000
1)
#66000
b1 G
1*
b1 -
b0 F
#70000
0)
#75000
b1111000 7
b11111101 B
b10 !
b10 D
b1010000 #
b1010000 >
b11110000111111110001000 5
b11101111111111110001000 6
b1001011000 4
b110010000 @
b10 =
1)
#76000
b11 G
0*
b0 F
#80000
0)
#85000
1)
#86000
b1 F
#90000
0)
#95000
1)
#96000
b10 F
#100000
0)
#105000
1)
#106000
b1 G
1*
b10 -
b0 F
#110000
0)
#115000
b10100000 7
b11111110 B
b11 !
b11 D
b1111000 #
b1111000 >
b101000000111111101100000 5
b100111111111111101100000 6
b1100100000 4
b1001011000 @
b11 =
1)
#116000
b11 G
0*
b0 F
#120000
0)
#125000
1)
#126000
b1 F
#130000
0)
#135000
1)
#136000
b10 F
#140000
0)
#145000
1)
#146000
b1 G
1*
b11 -
b0 F
#150000
0)
#155000
b11001000 7
b11111111 B
b100 !
b100 D
b10100000 #
b10100000 >
b110010000111111100111000 5
b110001111111111100111000 6
b1111101000 4
b1100100000 @
b100 =
1)
#156000
b11 G
0*
b0 F
#160000
0)
#165000
1)
#166000
b1 F
#170000
0)
#175000
1)
#176000
b10 F
#180000
0)
#185000
1)
#186000
b1 G
1*
b100 -
b0 F
#190000
0)
#195000
bx 7
bx 3
b0 B
b101 !
b101 D
b11001000 #
b11001000 >
bx 5
bx 6
bx 4
b1111101000 @
b101 =
1)
#196000
b11 G
0*
b0 F
#200000
0)
#205000
b11001000 7
b110010000111111100111000 5
b110001111111111100111000 6
b1111101000 4
b11001000 3
b11001000 $
b11001000 8
b11001000 C
1)
#206000
b1 F
#210000
0)
#215000
1)
#216000
b10 F
#220000
0)
#225000
1)
#226000
b1 G
1*
b101 -
b0 F
#230000
0)
#235000
b1 B
b110 !
b110 D
1)
#236000
b11 G
0*
b0 F
#240000
0)
#245000
1)
#246000
b1 F
#250000
0)
#255000
1)
#256000
b10 F
#260000
0)
#265000
1)
#266000
b1 G
1*
b110 -
b0 F
#270000
0)
#275000
b10 B
b111 !
b111 D
1)
#276000
b11 G
0*
b0 F
#280000
0)
#285000
1)
#286000
b1 F
#290000
0)
#295000
1)
#296000
b10 F
#300000
0)
#305000
1)
#306000
b1 G
1*
b111 -
b0 F
#310000
0)
#315000
b11 B
b1000 !
b1000 D
1)
#316000
b11 G
0*
b0 F
#320000
0)
#325000
1)
#326000
b1 F
#330000
0)
#335000
1)
#336000
b10 F
#340000
0)
#345000
1)
#346000
b101000 7
b0 3
b11111011 B
b0 !
b0 D
b0 "
b0 ?
b0 #
b0 >
b1010000111111111011000 5
b1001111111111111011000 6
b11001000 4
b0 @
b0 =
b10 G
0+
b1000 -
b0 F
#350000
0)
#355000
bx $
bx 8
bx C
1)
#356000
b1 F
#360000
0)
#365000
1)
#366000
b1 G
1+
b0 F
#370000
0)
#375000
1)
#376000
b0 7
1*
b1000000000000000 5
b0 6
b0 4
b0 (
b0 2
b0 A
b0 E
b0 -
b0 F
#380000
0)
#385000
b11111100 B
b1 !
b1 D
b1 =
1)
#386000
b11 G
0*
b0 F
#390000
0)
#395000
1)
#396000
b1 F
#400000
0)
#405000
1)
#406000
b10 F
#410000
0)
#415000
1)
#416000
b1 G
1*
b1011001100110011 5
b11001100110011 6
b1 4
b1 (
b1 2
b1 A
b1 E
b1 -
b0 0
b0 /
b1 .
b0 1
b0 F
#420000
0)
#425000
b11111101 B
b10 !
b10 D
b1110011001100110 5
b110011001100110 6
b10 4
b1 @
b10 =
1)
#426000
b11 G
0*
b0 F
#430000
0)
#435000
1)
#436000
b1 F
#440000
0)
#445000
1)
#446000
b10 F
#450000
0)
#455000
1)
#456000
b1 7
b1 G
1*
b10001100110011001 5
b1001100110011001 6
b11 4
b10 (
b10 2
b10 A
b10 E
b10 -
b1 1
b10 .
b0 F
#460000
0)
#465000
b11111110 B
b11 !
b11 D
b1 #
b1 >
b10111111111111111 5
b1111111111111111 6
b101 4
b11 @
b11 =
1)
#466000
b11 G
0*
b0 F
#470000
0)
#475000
1)
#476000
b1 F
#480000
0)
#485000
1)
#486000
b10 F
#490000
0)
#495000
1)
#496000
b1 G
1*
b11011001100110010 5
b10011001100110010 6
b110 4
b11 (
b11 2
b11 A
b11 E
b11 -
b1 /
b11 .
b11 1
b0 F
#500000
0)
#505000
b10 7
b11111111 B
b100 !
b100 D
b100100110011001011 5
b11100110011001011 6
b1001 4
b110 @
b100 =
1)
#506000
b11 G
0*
b0 F
#510000
0)
#515000
1)
#516000
b1 F
#520000
0)
#525000
1)
#526000
b10 F
#530000
0)
#535000
1)
#536000
b1 G
1*
b100111111111111110 5
b11111111111111110 6
b1010 4
b100 (
b100 2
b100 A
b100 E
b100 -
b100 .
b110 1
b0 F
#540000
0)
#545000
bx 7
bx 3
b0 B
b101 !
b101 D
b1 "
b1 ?
b10 #
b10 >
bx 5
bx 6
bx 4
b1010 @
b101 =
1)
#546000
b11 G
0*
b0 F
#550000
0)
#555000
b11 7
b110100110011001010 5
b101100110011001010 6
b1110 4
b0 3
b0 $
b0 8
b0 C
1)
#556000
b1 F
#560000
0)
#565000
1)
#566000
b10 F
#570000
0)
#575000
1)
#576000
b100 7
b1 G
1*
b1000001100110010110 5
b111001100110010110 6
b10010 4
b1000 (
b1000 2
b1000 A
b1000 E
b101 -
b1 0
b10 /
b101 .
b1010 1
b0 F
#580000
0)
#585000
b101 7
b1 B
b110 !
b110 D
b10 "
b10 ?
b100 #
b100 >
b1011011001100101110 5
b1010011001100101110 6
b11010 4
b10010 @
1)
#586000
b11 G
0*
b0 F
#590000
0)
#595000
b1010111111111111011 5
b1001111111111111011 6
b11001 4
b1 3
b1 $
b1 8
b1 C
1)
#596000
b1 F
#600000
0)
#605000
1)
#606000
b10 F
#610000
0)
#615000
1)
#616000
b1 G
1*
b110 -
b10 0
b100 /
b110 .
b10010 1
b0 F
#620000
0)
#625000
b110 7
b10 B
b111 !
b111 D
b101 #
b101 >
b1101110011001100000 5
b1100110011001100000 6
b100000 4
b11001 @
1)
#626000
b11 G
0*
b0 F
#630000
0)
#635000
b1101011001100101101 5
b1100011001100101101 6
b11111 4
b10 3
b10 $
b10 8
b10 C
1)
#636000
b1 F
#640000
0)
#645000
1)
#646000
b10 F
#650000
0)
#655000
1)
#656000
b1 G
1*
b111 -
b101 /
b111 .
b11001 1
b0 F
#660000
0)
#665000
b111 7
b11 B
b1000 !
b1000 D
b110 #
b110 >
b1111110011001011111 5
b1110110011001011111 6
b100101 4
b11111 @
1)
#666000
b11 G
0*
b0 F
#670000
0)
#675000
b1111011001100101100 5
b1110011001100101100 6
b100100 4
b11 3
b11 $
b11 8
b11 C
1)
#676000
b1 F
#680000
0)
#685000
1)
#686000
b10 F
#690000
0)
#695000
1)
#696000
b1 G
1*
b1000 -
b110 /
b1000 .
b11111 1
b0 F
#700000
0)
#705000
b1000 7
b100 B
b1001 !
b1001 D
b111 #
b111 >
b10001011001100101011 5
b10000011001100101011 6
b101001 4
b100100 @
1)
#706000
b11 G
0*
b0 F
#710000
0)
#715000
b10000111111111111000 5
b1111111111111111000 6
b101000 4
b100 3
b100 $
b100 8
b100 C
1)
#716000
b1 F
#720000
0)
#725000
1)
#726000
b10 F
#730000
0)
#735000
1)
#736000
b110 7
b1 G
1*
b1101110011001100000 5
b1100110011001100000 6
b100000 4
b0 (
b0 2
b0 A
b0 E
b1001 -
b111 /
b1001 .
b100100 1
b0 F
#740000
0)
#745000
b101 B
b1010 !
b1010 D
b110 #
b110 >
b1100001100110010100 5
b1011001100110010100 6
b11100 4
b100000 @
1)
#746000
b11 G
0*
b0 F
#750000
0)
#755000
b101 7
b1010100110011001000 5
b1001100110011001000 6
b11000 4
b1000 3
b1000 $
b1000 8
b1000 C
1)
#756000
b1 F
#760000
0)
#765000
1)
#766000
b10 F
#770000
0)
#775000
1)
#776000
b1 G
1*
b1010 -
b110 /
b1010 .
b100000 1
b0 F
#780000
0)
#785000
b11 7
b110 B
b1011 !
b1011 D
b101 #
b101 >
b111011001100110000 5
b110011001100110000 6
b10000 4
b11000 @
1)
#786000
b11 G
0*
b0 F
#790000
0)
#795000
1)
#796000
b1 F
#800000
0)
#805000
1)
#806000
b10 F
#810000
0)
#815000
1)
#816000
b1 G
1*
b1011 -
b101 /
b1011 .
b11000 1
b0 F
#820000
0)
#825000
b10 7
b111 B
b1100 !
b1100 D
b1 "
b1 ?
b11 #
b11 >
b100001100110011000 5
b11001100110011000 6
b1000 4
b10000 @
1)
#826000
b11 G
0*
b0 F
#830000
0)
#835000
1)
#836000
b1 F
#840000
0)
#845000
1)
#846000
b10 F
#850000
0)
#855000
1)
#856000
b1 G
1*
b1100 -
b1 0
b11 /
b1100 .
b10000 1
b0 F
#860000
0)
#865000
b0 7
b1000 B
b1101 !
b1101 D
b10 #
b10 >
b1000000000000000 5
b0 6
b0 4
b1000 @
1)
#866000
b11 G
0*
b0 F
#870000
0)
#875000
1)
#876000
b1 F
#880000
0)
#885000
1)
#886000
b10 F
#890000
0)
#895000
1)
#896000
b1 G
1*
b1101 -
b10 /
b1101 .
b1000 1
b0 F
#900000
0)
#905000
b10011000 7
b1001 B
b1110 !
b1110 D
b0 "
b0 ?
b0 #
b0 >
b1100110000111111001101000 5
b1100101111111111001101000 6
b11111111000 4
b0 @
1)
#906000
b11 G
0*
b0 F
#910000
0)
#915000
b0 7
b1000000000000000 5
b0 6
b0 4
b0 3
b0 $
b0 8
b0 C
1)
#916000
b1 F
#920000
0)
#925000
1)
#926000
b10 F
#930000
0)
#935000
1)
#936000
b1110 -
b0 0
b0 /
b1110 .
b0 1
b11 F
