final_project/rtl/protocolo_serial.v
// protocolo_serial: envia a telemetria do semaforo para a Raspberry Pi por
// um link serial sincrono estilo SPI (modo 0, MSB primeiro), somente
// leitura. A Raspberry e' o mestre: gera sclk e cs_n; a FPGA so' responde
// em miso. Nenhum dado vai da Raspberry para a FPGA.
//
// Quadro (16 bits, delimitado por cs_n em nivel baixo):
//   - enquanto cs_n = 1, o registrador acompanha "quadro" a cada ciclo;
//   - quando cs_n desce, o valor fica congelado (todos os campos sao do
//     mesmo instante) e miso ja mostra o bit 15;
//   - a cada borda de SUBIDA de sclk, miso avanca para o proximo bit.
//     A Raspberry le miso ANTES de cada subida (16 leituras).
// O formato dos campos e' montado em top_semaforo.
//
// sclk e cs_n vem de outra placa (assincronos ao clk): passam por 2
// flip-flops de sincronizacao. Por isso cada nivel de sclk precisa durar
// mais que ~4 ciclos de clk (150 ns); a Raspberry usa dezenas de us.
//
// Portas:
//   sclk, cs_n - clock serial e selecao de quadro, vindos da Raspberry
//   quadro     - 16 bits de telemetria do instante atual
//   miso       - bit atual do quadro para a Raspberry
module protocolo_serial (
    input  wire        clk,
    input  wire        rst_n,
    input  wire        sclk,
    input  wire        cs_n,
    input  wire [15:0] quadro,
    output wire        miso
);
    reg [2:0]  sclk_sinc;     // [1:0] sincronizam sclk; [2] guarda o valor anterior para achar a borda
    reg [1:0]  cs_n_sinc;     // cs_n sincronizado em cs_n_sinc[1]
    reg [15:0] deslocamento;  // quadro sendo enviado; o bit 15 esta em miso
    wire       sclk_subiu;    // 1 ciclo em 1 na borda de subida de sclk

    assign sclk_subiu = sclk_sinc[1] & ~sclk_sinc[2];
    assign miso       = deslocamento[15];

    always @(posedge clk or negedge rst_n) begin
        if (!rst_n) begin
            sclk_sinc    <= 3'b000;
            cs_n_sinc    <= 2'b11;
            deslocamento <= 16'd0;
        end else begin
            sclk_sinc <= {sclk_sinc[1:0], sclk};
            cs_n_sinc <= {cs_n_sinc[0], cs_n};

            if (cs_n_sinc[1])
                deslocamento <= quadro;                      // fora do quadro: fotografa o estado atual
            else if (sclk_subiu)
                deslocamento <= {deslocamento[14:0], 1'b0};  // dentro do quadro: proximo bit
        end
    end
endmodule

final_project/tb/tb_protocolo_serial.v
// tb_protocolo_serial: le quadros de 16 bits como a Raspberry Pi faz (le
// miso antes de cada subida de sclk) e confere que o valor lido e' o
// quadro do instante em que cs_n desceu, mesmo que "quadro" mude durante
// a transferencia.
`timescale 1ns/1ps
module tb_protocolo_serial;
    reg         clk, rst_n, sclk, cs_n;
    reg  [15:0] quadro;
    wire        miso;
    reg  [15:0] lido;    // quadro recebido pelo "mestre" do testbench
    integer     erros;

    protocolo_serial dut (
        .clk(clk), .rst_n(rst_n), .sclk(sclk), .cs_n(cs_n), .quadro(quadro), .miso(miso)
    );

    always #5 clk = ~clk;

    task espera(input integer n);
        integer i;
        for (i = 0; i < n; i = i + 1) begin @(posedge clk); #1; end
    endtask

    // transferencia completa; cada nivel de sclk dura 6 ciclos de clk
    task le_quadro(output [15:0] valor);
        integer b;
        begin
            cs_n = 0; espera(6);
            // 16 bits, MSB primeiro; termina apos o bit 0
            for (b = 15; b >= 0; b = b - 1) begin
                valor[b] = miso;
                sclk = 1; espera(6);
                sclk = 0; espera(6);
            end
            cs_n = 1; espera(6);
        end
    endtask

    task confere(input [15:0] esperado, input [8*48-1:0] descricao);
        if (lido !== esperado) begin
            erros = erros + 1;
            $display("[FALHA] %0s (lido=%h esperado=%h)", descricao, lido, esperado);
        end else
            $display("[OK]    %0s (%h)", descricao, lido);
    endtask

    initial begin
        $dumpfile("build/tb_protocolo_serial.vcd");
        $dumpvars(0, tb_protocolo_serial);
        clk = 0; rst_n = 0; sclk = 0; cs_n = 1; quadro = 16'hA9C5; erros = 0;
        espera(2); rst_n = 1; espera(4);

        le_quadro(lido);
        confere(16'hA9C5, "quadro lido bit a bit");

        quadro = 16'hA001; espera(4);
        le_quadro(lido);
        confere(16'hA001, "quadro atualizado entre transferencias");

        // muda o quadro no meio da transferencia: deve valer o valor antigo
        quadro = 16'hA5A5; espera(4);
        fork
            le_quadro(lido);
            begin espera(40); quadro = 16'hAFFF; end
        join
        confere(16'hA5A5, "quadro congelado durante a transferencia");

        if (erros == 0) $display("RESULTADO: TODOS OS CASOS PASSARAM");
        else            $display("RESULTADO: %0d CASO(S) FALHARAM", erros);
        $finish;
    end
endmodule

final_project/build/tb_protocolo_serial.vcd
$date
	Tue Oct  6 20:22:25 2026
$end
$version
	Icarus Verilog
$end
$timescale
	1ps
$end
$scope module tb_protocolo_serial $end
$var wire 1 ! miso $end
$var reg 1 " clk $end
$var reg 1 # cs_n $end
$var reg 16 $ lido [15:0] $end
$var reg 16 % quadro [15:0] $end
$var reg 1 & rst_n $end
$var reg 1 ' sclk $end
$var integer 32 ( erros [31:0] $end
$scope module dut $end
$var wire 1 " clk $end
$var wire 1 # cs_n $end
$var wire 16 ) quadro [15:0] $end
$var wire 1 & rst_n $end
$var wire 1 ' sclk $end
$var wire 1 * sclk_subiu $end
$var wire 1 ! miso $end
$var reg 2 + cs_n_sinc [1:0] $end
$var reg 16 , deslocamento [15:0] $end
$var reg 3 - sclk_sinc [2:0] $end
$upscope $end
$scope task confere $end
$var reg 384 . descricao [383:0] $end
$var reg 16 / esperado [15:0] $end
$upscope $end
$scope task espera $end
$var integer 32 0 i [31:0] $end
$var integer 32 1 n [31:0] $end
$upscope $end
$scope task le_quadro $end
$var reg 16 2 valor [15:0] $end
$var integer 32 3 b [31:0] $end
$upscope $end
$upscope $end
$enddefinitions $end
$comment Show the parameter values. $end
$dumpall
$end
#0
$dumpvars
bx 3
bx 2
b10 1
b0 0
bx /
bx .
b0 -
b0 ,
b11 +
0*
b1010100111000101 )
b0 (
0'
0&
b1010100111000101 %
bx $
1#
0"
0!
$end
#5000
1"
#6000
b1 0
#10000
0"
#15000
1"
#16000
b100 1
1&
b0 0
#20000
0"
#25000
1!
b1010100111000101 ,
1"
#26000
b1 0
#30000
0"
#35000
1"
#36000
b10 0
#40000
0"
#45000
1"
#46000
b11 0
#50000
0"
#55000
1"
#56000
b110 1
0#
b0 0
#60000
0"
#65000
b10 +
1"
#66000
b1 0
#70000
0"
#75000
b0 +
1"
#76000
b10 0
#80000
0"
#85000
1"
#86000
b11 0
#90000
0"
#95000
1"
#96000
b100 0
#100000
0"
#105000
1"
#106000
b101 0
#110000
0"
#115000
1"
#116000
1'
b1xxxxxxxxxxxxxxx 2
b1111 3
b0 0
#120000
0"
#125000
b1 -
1"
#126000
b1 0
#130000
0"
#135000
1*
b11 -
1"
#136000
b10 0
#140000
0"
#145000
0*
0!
b101001110001010 ,
b111 -
1"
#146000
b11 0
#150000
0"
#155000
1"
#156000
b100 0
#160000
0"
#165000
1"
#166000
b101 0
#170000
0"
#175000
1"
#176000
0'
b0 0
#180000
0"
#185000
b110 -
1"
#186000
b1 0
#190000
0"
#195000
b100 -
1"
#196000
b10 0
#200000
0"
#205000
b0 -
1"
#206000
b11 0
#210000
0"
#215000
1"
#216000
b100 0
#220000
0"
#225000
1"
#226000
b101 0
#230000
0"
#235000
1"
#236000
1'
b10xxxxxxxxxxxxxx 2
b1110 3
b0 0
#240000
0"
#245000
b1 -
1"
#246000
b1 0
#250000
0"
#255000
1*
b11 -
1"
#256000
b10 0
#260000
0"
#265000
0*
1!
b1010011100010100 ,
b111 -
1"
#266000
b11 0
#270000
0"
#275000
1"
#276000
b100 0
#280000
0"
#285000
1"
#286000
b101 0
#290000
0"
#295000
1"
#296000
0'
b0 0
#300000
0"
#305000
b110 -
1"
#306000
b1 0
#310000
0"
#315000
b100 -
1"
#316000
b10 0
#320000
0"
#325000
b0 -
1"
#326000
b11 0
#330000
0"
#335000
1"
#336000
b100 0
#340000
0"
#345000
1"
#346000
b101 0
#350000
0"
#355000
1"
#356000
1'
b101xxxxxxxxxxxxx 2
b1101 3
b0 0
#360000
0"
#365000
b1 -
1"
#366000
b1 0
#370000
0"
#375000
1*
b11 -
1"
#376000
b10 0
#380000
0"
#385000
0*
0!
b100111000101000 ,
b111 -
1"
#386000
b11 0
#390000
0"
#395000
1"
#396000
b100 0
#400000
0"
#405000
1"
#406000
b101 0
#410000
0"
#415000
1"
#416000
0'
b0 0
#420000
0"
#425000
b110 -
1"
#426000
b1 0
#430000
0"
#435000
b100 -
1"
#436000
b10 0
#440000
0"
#445000
b0 -
1"
#446000
b11 0
#450000
0"
#455000
1"
#456000
b100 0
#460000
0"
#465000
1"
#466000
b101 0
#470000
0"
#475000
1"
#476000
1'
b1010xxxxxxxxxxxx 2
b1100 3
b0 0
#480000
0"
#485000
b1 -
1"
#486000
b1 0
#490000
0"
#495000
1*
b11 -
1"
#496000
b10 0
#500000
0"
#505000
0*
1!
b1001110001010000 ,
b111 -
1"
#506000
b11 0
#510000
0"
#515000
1"
#516000
b100 0
#520000
0"
#525000
1"
#526000
b101 0
#530000
0"
#535000
1"
#536000
0'
b0 0
#540000
0"
#545000
b110 -
1"
#546000
b1 0
#550000
0"
#555000
b100 -
1"
#556000
b10 0
#560000
0"
#565000
b0 -
1"
#566000
b11 0
#570000
0"
#575000
1"
#576000
b100 0
#580000
0"
#585000
1"
#586000
b101 0
#590000
0"
#595000
1"
#596000
1'
b10101xxxxxxxxxxx 2
b1011 3
b0 0
#600000
0"
#605000
b1 -
1"
#606000
b1 0
#610000
0"
#615000
1*
b11 -
1"
#616000
b10 0
#620000
0"
#625000
0*
0!
b11100010100000 ,
b111 -
1"
#626000
b11 0
#630000
0"
#635000
1"
#636000
b100 0
#640000
0"
#645000
1"
#646000
b101 0
#650000
0"
#655000
1"
#656000
0'
b0 0
#660000
0"
#665000
b110 -
1"
#666000
b1 0
#670000
0"
#675000
b100 -
1"
#676000
b10 0
#680000
0"
#685000
b0 -
1"
#686000
b11 0
#690000
0"
#695000
1"
#696000
b100 0
#700000
0"
#705000
1"
#706000
b101 0
#710000
0"
#715000
1"
#716000
1'
b101010xxxxxxxxxx 2
b1010 3
b0 0
#720000
0"
#725000
b1 -
1"
#726000
b1 0
#730000
0"
#735000
1*
b11 -
1"
#736000
b10 0
#740000
0"
#745000
0*
b111000101000000 ,
b111 -
1"
#746000
b11 0
#750000
0"
#755000
1"
#756000
b100 0
#760000
0"
#765000
1"
#766000
b101 0
#770000
0"
#775000
1"
#776000
0'
b0 0
#780000
0"
#785000
b110 -
1"
#786000
b1 0
#790000
0"
#795000
b100 -
1"
#796000
b10 0
#800000
0"
#805000
b0 -
1"
#806000
b11 0
#810000
0"
#815000
1"
#816000
b100 0
#820000
0"
#825000
1"
#826000
b101 0
#830000
0"
#835000
1"
#836000
1'
b1010100xxxxxxxxx 2
b1001 3
b0 0
#840000
0"
#845000
b1 -
1"
#846000
b1 0
#850000
0"
#855000
1*
b11 -
1"
#856000
b10 0
#860000
0"
#865000
0*
1!
b1110001010000000 ,
b111 -
1"
#866000
b11 0
#870000
0"
#875000
1"
#876000
b100 0
#880000
0"
#885000
1"
#886000
b101 0
#890000
0"
#895000
1"
#896000
0'
b0 0
#900000
0"
#905000
b110 -
1"
#906000
b1 0
#910000
0"
#915000
b100 -
1"
#916000
b10 0
#920000
0"
#925000
b0 -
1"
#926000
b11 0
#930000
0"
#935000
1"
#936000
b100 0
#940000
0"
#945000
1"
#946000
b101 0
#950000
0"
#955000
1"
#956000
1'
b10101001xxxxxxxx 2
b1000 3
b0 0
#960000
0"
#965000
b1 -
1"
#966000
b1 0
#970000
0"
#975000
1*
b11 -
1"
#976000
b10 0
#980000
0"
#985000
0*
b1100010100000000 ,
b111 -
1"
#986000
b11 0
#990000
0"
#995000
1"
#996000
b100 0
#1000000
0"
#1005000
1"
#1006000
b101 0
#1010000
0"
#1015000
1"
#1016000
0'
b0 0
#1020000
0"
#1025000
b110 -
1"
#1026000
b1 0
#1030000
0"
#1035000
b100 -
1"
#1036000
b10 0
#1040000
0"
#1045000
b0 -
1"
#1046000
b11 0
#1050000
0"
#1055000
1"
#1056000
b100 0
#1060000
0"
#1065000
1"
#1066000
b101 0
#1070000
0"
#1075000
1"
#1076000
1'
b101010011xxxxxxx 2
b111 3
b0 0
#1080000
0"
#1085000
b1 -
1"
#1086000
b1 0
#1090000
0"
#1095000
1*
b11 -
1"
#1096000
b10 0
#1100000
0"
#1105000
0*
b1000101000000000 ,
b111 -
1"
#1106000
b11 0
#1110000
0"
#1115000
1"
#1116000
b100 0
#1120000
0"
#1125000
1"
#1126000
b101 0
#1130000
0"
#1135000
1"
#1136000
0'
b0 0
#1140000
0"
#1145000
b110 -
1"
#1146000
b1 0
#1150000
0"
#1155000
b100 -
1"
#1156000
b10 0
#1160000
0"
#1165000
b0 -
1"
#1166000
b11 0
#1170000
0"
#1175000
1"
#1176000
b100 0
#1180000
0"
#1185000
1"
#1186000
b101 0
#1190000
0"
#1195000
1"
#1196000
1'
b1010100111xxxxxx 2
b110 3
b0 0
#1200000
0"
#1205000
b1 -
1"
#1206000
b1 0
#1210000
0"
#1215000
1*
b11 -
1"
#1216000
b10 0
#1220000
0"
#1225000
0*
0!
b1010000000000 ,
b111 -
1"
#1226000
b11 0
#1230000
0"
#1235000
1"
#1236000
b100 0
#1240000
0"
#1245000
1"
#1246000
b101 0
#1250000
0"
#1255000
1"
#1256000
0'
b0 0
#1260000
0"
#1265000
b110 -
1"
#1266000
b1 0
#1270000
0"
#1275000
b100 -
1"
#1276000
b10 0
#1280000
0"
#1285000
b0 -
1"
#1286000
b11 0
#1290000
0"
#1295000
1"
#1296000
b100 0
#1300000
0"
#1305000
1"
#1306000
b101 0
#1310000
0"
#1315000
1"
#1316000
1'
b10101001110xxxxx 2
b101 3
b0 0
#1320000
0"
#1325000
b1 -
1"
#1326000
b1 0
#1330000
0"
#1335000
1*
b11 -
1"
#1336000
b10 0
#1340000
0"
#1345000
0*
b10100000000000 ,
b111 -
1"
#1346000
b11 0
#1350000
0"
#1355000
1"
#1356000
b100 0
#1360000
0"
#1365000
1"
#1366000
b101 0
#1370000
0"
#1375000
1"
#1376000
0'
b0 0
#1380000
0"
#1385000
b110 -
1"
#1386000
b1 0
#1390000
0"
#1395000
b100 -
1"
#1396000
b10 0
#1400000
0"
#1405000
b0 -
1"
#1406000
b11 0
#1410000
0"
#1415000
1"
#1416000
b100 0
#1420000
0"
#1425000
1"
#1426000
b101 0
#1430000
0"
#1435000
1"
#1436000
1'
b101010011100xxxx 2
b100 3
b0 0
#1440000
0"
#1445000
b1 -
1"
#1446000
b1 0
#1450000
0"
#1455000
1*
b11 -
1"
#1456000
b10 0
#1460000
0"
#1465000
0*
b101000000000000 ,
b111 -
1"
#1466000
b11 0
#1470000
0"
#1475000
1"
#1476000
b100 0
#1480000
0"
#1485000
1"
#1486000
b101 0
#1490000
0"
#1495000
1"
#1496000
0'
b0 0
#1500000
0"
#1505000
b110 -
1"
#1506000
b1 0
#1510000
0"
#1515000
b100 -
1"
#1516000
b10 0
#1520000
0"
#1525000
b0 -
1"
#1526000
b11 0
#1530000
0"
#1535000
1"
#1536000
b100 0
#1540000
0"
#1545000
1"
#1546000
b101 0
#1550000
0"
#1555000
1"
#1556000
1'
b1010100111000xxx 2
b11 3
b0 0
#1560000
0"
#1565000
b1 -
1"
#1566000
b1 0
#1570000
0"
#1575000
1*
b11 -
1"
#1576000
b10 0
#1580000
0"
#1585000
0*
1!
b1010000000000000 ,
b111 -
1"
#1586000
b11 0
#1590000
0"
#1595000
1"
#1596000
b100 0
#1600000
0"
#1605000
1"
#1606000
b101 0
#1610000
0"
#1615000
1"
#1616000
0'
b0 0
#1620000
0"
#1625000
b110 -
1"
#1626000
b1 0
#1630000
0"
#1635000
b100 -
1"
#1636000
b10 0
#1640000
0"
#1645000
b0 -
1"
#1646000
b11 0
#1650000
0"
#1655000
1"
#1656000
b100 0
#1660000
0"
#1665000
1"
#1666000
b101 0
#1670000
0"
#1675000
1"
#1676000
1'
b10101001110001xx 2
b10 3
b0 0
#1680000
0"
#1685000
b1 -
1"
#1686000
b1 0
#1690000
0"
#1695000
1*
b11 -
1"
#1696000
b10 0
#1700000
0"
#1705000
0*
0!
b100000000000000 ,
b111 -
1"
#1706000
b11 0
#1710000
0"
#1715000
1"
#1716000
b100 0
#1720000
0"
#1725000
1"
#1726000
b101 0
#1730000
0"
#1735000
1"
#1736000
0'
b0 0
#1740000
0"
#1745000
b110 -
1"
#1746000
b1 0
#1750000
0"
#1755000
b100 -
1"
#1756000
b10 0
#1760000
0"
#1765000
b0 -
1"
#1766000
b11 0
#1770000
0"
#1775000
1"
#1776000
b100 0
#1780000
0"
#1785000
1"
#1786000
b101 0
#1790000
0"
#1795000
1"
#1796000
1'
b101010011100010x 2
b1 3
b0 0
#1800000
0"
#1805000
b1 -
1"
#1806000
b1 0
#1810000
0"
#1815000
1*
b11 -
1"
#1816000
b10 0
#1820000
0"
#1825000
0*
1!
b1000000000000000 ,
b111 -
1"
#1826000
b11 0
#1830000
0"
#1835000
1"
#1836000
b100 0
#1840000
0"
#1845000
1"
#1846000
b101 0
#1850000
0"
#1855000
1"
#1856000
0'
b0 0
#1860000
0"
#1865000
b110 -
1"
#1866000
b1 0
#1870000
0"
#1875000
b100 -
1"
#1876000
b10 0
#1880000
0"
#1885000
b0 -
1"
#1886000
b11 0
#1890000
0"
#1895000
1"
#1896000
b100 0
#1900000
0"
#1905000
1"
#1906000
b101 0
#1910000
0"
#1915000
1"
#1916000
1'
b1010100111000101 2
b0 3
b0 0
#1920000
0"
#1925000
b1 -
1"
#1926000
b1 0
#1930000
0"
#1935000
1*
b11 -
1"
#1936000
b10 0
#1940000
0"
#1945000
0*
0!
b0 ,
b111 -
1"
#1946000
b11 0
#1950000
0"
#1955000
1"
#1956000
b100 0
#1960000
0"
#1965000
1"
#1966000
b101 0
#1970000
0"
#1975000
1"
#1976000
0'
b0 0
#1980000
0"
#1985000
b110 -
1"
#1986000
b1 0
#1990000
0"
#1995000
b100 -
1"
#1996000
b10 0
#2000000
0"
#2005000
b0 -
1"
#2006000
b11 0
#2010000
0"
#2015000
1"
#2016000
b100 0
#2020000
0"
#2025000
1"
#2026000
b101 0
#2030000
0"
#2035000
1"
#2036000
1#
b11111111111111111111111111111111 3
b0 0
#2040000
0"
#2045000
b1 +
1"
#2046000
b1 0
#2050000
0"
#2055000
b11 +
1"
#2056000
b10 0
#2060000
0"
#2065000
1!
b1010100111000101 ,
1"
#2066000
b11 0
#2070000
0"
#2075000
1"
#2076000
b100 0
#2080000
0"
#2085000
1"
#2086000
b101 0
#2090000
0"
#2095000
1"
#2096000
b100 1
b1010000000000001 %
b1010000000000001 )
b11100010111010101100001011001000111001001101111001000000110110001101001011001000110111100100000011000100110100101110100001000000110000100100000011000100110100101110100 .
b1010100111000101 /
b1010100111000101 $
b0 0
#2100000
0"
#2105000
b1010000000000001 ,
1"
#2106000
b1 0
#2110000
0"
#2115000
1"
#2116000
b10 0
#2120000
0"
#2125000
1"
#2126000
b11 0
#2130000
0"
#2135000
1"
#2136000
b110 1
0#
b0 0
#2140000
0"
#2145000
b10 +
1"
#2146000
b1 0
#2150000
0"
#2155000
b0 +
1"
#2156000
b10 0
#2160000
0"
#2165000
1"
#2166000
b11 0
#2170000
0"
#2175000
1"
#2176000
b100 0
#2180000
0"
#2185000
1"
#2186000
b101 0
#2190000
0"
#2195000
1"
#2196000
1'
b1111 3
b0 0
#2200000
0"
#2205000
b1 -
1"
#2206000
b1 0
#2210000
0"
#2215000
1*
b11 -
1"
#2216000
b10 0
#2220000
0"
#2225000
0*
0!
b100000000000010 ,
b111 -
1"
#2226000
b11 0
#2230000
0"
#2235000
1"
#2236000
b100 0
#2240000
0"
#2245000
1"
#2246000
b101 0
#2250000
0"
#2255000
1"
#2256000
0'
b0 0
#2260000
0"
#2265000
b110 -
1"
#2266000
b1 0
#2270000
0"
#2275000
b100 -
1"
#2276000
b10 0
#2280000
0"
#2285000
b0 -
1"
#2286000
b11 0
#2290000
0"
#2295000
1"
#2296000
b100 0
#2300000
0"
#2305000
1"
#2306000
b101 0
#2310000
0"
#2315000
1"
#2316000
1'
b1110 3
b0 0
#2320000
0"
#2325000
b1 -
1"
#2326000
b1 0
#2330000
0"
#2335000
1*
b11 -
1"
#2336000
b10 0
#2340000
0"
#2345000
0*
1!
b1000000000000100 ,
b111 -
1"
#2346000
b11 0
#2350000
0"
#2355000
1"
#2356000
b100 0
#2360000
0"
#2365000
1"
#2366000
b101 0
#2370000
0"
#2375000
1"
#2376000
0'
b0 0
#2380000
0"
#2385000
b110 -
1"
#2386000
b1 0
#2390000
0"
#2395000
b100 -
1"
#2396000
b10 0
#2400000
0"
#2405000
b0 -
1"
#2406000
b11 0
#2410000
0"
#2415000
1"
#2416000
b100 0
#2420000
0"
#2425000
1"
#2426000
b101 0
#2430000
0"
#2435000
1"
#2436000
1'
b1101 3
b0 0
#2440000
0"
#2445000
b1 -
1"
#2446000
b1 0
#2450000
0"
#2455000
1*
b11 -
1"
#2456000
b10 0
#2460000
0"
#2465000
0*
0!
b1000 ,
b111 -
1"
#2466000
b11 0
#2470000
0"
#2475000
1"
#2476000
b100 0
#2480000
0"
#2485000
1"
#2486000
b101 0
#2490000
0"
#2495000
1"
#2496000
0'
b0 0
#2500000
0"
#2505000
b110 -
1"
#2506000
b1 0
#2510000
0"
#2515000
b100 -
1"
#2516000
b10 0
#2520000
0"
#2525000
b0 -
1"
#2526000
b11 0
#2530000
0"
#2535000
1"
#2536000
b100 0
#2540000
0"
#2545000
1"
#2546000
b101 0
#2550000
0"
#2555000
1"
#2556000
1'
b1100 3
b0 0
#2560000
0"
#2565000
b1 -
1"
#2566000
b1 0
#2570000
0"
#2575000
1*
b11 -
1"
#2576000
b10 0
#2580000
0"
#2585000
0*
b10000 ,
b111 -
1"
#2586000
b11 0
#2590000
0"
#2595000
1"
#2596000
b100 0
#2600000
0"
#2605000
1"
#2606000
b101 0
#2610000
0"
#2615000
1"
#2616000
0'
b0 0
#2620000
0"
#2625000
b110 -
1"
#2626000
b1 0
#2630000
0"
#2635000
b100 -
1"
#2636000
b10 0
#2640000
0"
#2645000
b0 -
1"
#2646000
b11 0
#2650000
0"
#2655000
1"
#2656000
b100 0
#2660000
0"
#2665000
1"
#2666000
b101 0
#2670000
0"
#2675000
1"
#2676000
1'
b1010000111000101 2
b1011 3
b0 0
#2680000
0"
#2685000
b1 -
1"
#2686000
b1 0
#2690000
0"
#2695000
1*
b11 -
1"
#2696000
b10 0
#2700000
0"
#2705000
0*
b100000 ,
b111 -
1"
#2706000
b11 0
#2710000
0"
#2715000
1"
#2716000
b100 0
#2720000
0"
#2725000
1"
#2726000
b101 0
#2730000
0"
#2735000
1"
#2736000
0'
b0 0
#2740000
0"
#2745000
b110 -
1"
#2746000
b1 0
#2750000
0"
#2755000
b100 -
1"
#2756000
b10 0
#2760000
0"
#2765000
b0 -
1"
#2766000
b11 0
#2770000
0"
#2775000
1"
#2776000
b100 0
#2780000
0"
#2785000
1"
#2786000
b101 0
#2790000
0"
#2795000
1"
#2796000
1'
b1010 3
b0 0
#2800000
0"
#2805000
b1 -
1"
#2806000
b1 0
#2810000
0"
#2815000
1*
b11 -
1"
#2816000
b10 0
#2820000
0"
#2825000
0*
b1000000 ,
b111 -
1"
#2826000
b11 0
#2830000
0"
#2835000
1"
#2836000
b100 0
#2840000
0"
#2845000
1"
#2846000
b101 0
#2850000
0"
#2855000
1"
#2856000
0'
b0 0
#2860000
0"
#2865000
b110 -
1"
#2866000
b1 0
#2870000
0"
#2875000
b100 -
1"
#2876000
b10 0
#2880000
0"
#2885000
b0 -
1"
#2886000
b11 0
#2890000
0"
#2895000
1"
#2896000
b100 0
#2900000
0"
#2905000
1"
#2906000
b101 0
#2910000
0"
#2915000
1"
#2916000
1'
b1001 3
b0 0
#2920000
0"
#2925000
b1 -
1"
#2926000
b1 0
#2930000
0"
#2935000
1*
b11 -
1"
#2936000
b10 0
#2940000
0"
#2945000
0*
b10000000 ,
b111 -
1"
#2946000
b11 0
#2950000
0"
#2955000
1"
#2956000
b100 0
#2960000
0"
#2965000
1"
#2966000
b101 0
#2970000
0"
#2975000
1"
#2976000
0'
b0 0
#2980000
0"
#2985000
b110 -
1"
#2986000
b1 0
#2990000
0"
#2995000
b100 -
1"
#2996000
b10 0
#3000000
0"
#3005000
b0 -
1"
#3006000
b11 0
#3010000
0"
#3015000
1"
#3016000
b100 0
#3020000
0"
#3025000
1"
#3026000
b101 0
#3030000
0"
#3035000
1"
#3036000
1'
b1010000011000101 2
b1000 3
b0 0
#3040000
0"
#3045000
b1 -
1"
#3046000
b1 0
#3050000
0"
#3055000
1*
b11 -
1"
#3056000
b10 0
#3060000
0"
#3065000
0*
b100000000 ,
b111 -
1"
#3066000
b11 0
#3070000
0"
#3075000
1"
#3076000
b100 0
#3080000
0"
#3085000
1"
#3086000
b101 0
#3090000
0"
#3095000
1"
#3096000
0'
b0 0
#3100000
0"
#3105000
b110 -
1"
#3106000
b1 0
#3110000
0"
#3115000
b100 -
1"
#3116000
b10 0
#3120000
0"
#3125000
b0 -
1"
#3126000
b11 0
#3130000
0"
#3135000
1"
#3136000
b100 0
#3140000
0"
#3145000
1"
#3146000
b101 0
#3150000
0"
#3155000
1"
#3156000
1'
b1010000001000101 2
b111 3
b0 0
#3160000
0"
#3165000
b1 -
1"
#3166000
b1 0
#3170000
0"
#3175000
1*
b11 -
1"
#3176000
b10 0
#3180000
0"
#3185000
0*
b1000000000 ,
b111 -
1"
#3186000
b11 0
#3190000
0"
#3195000
1"
#3196000
b100 0
#3200000
0"
#3205000
1"
#3206000
b101 0
#3210000
0"
#3215000
1"
#3216000
0'
b0 0
#3220000
0"
#3225000
b110 -
1"
#3226000
b1 0
#3230000
0"
#3235000
b100 -
1"
#3236000
b10 0
#3240000
0"
#3245000
b0 -
1"
#3246000
b11 0
#3250000
0"
#3255000
1"
#3256000
b100 0
#3260000
0"
#3265000
1"
#3266000
b101 0
#3270000
0"
#3275000
1"
#3276000
1'
b1010000000000101 2
b110 3
b0 0
#3280000
0"
#3285000
b1 -
1"
#3286000
b1 0
#3290000
0"
#3295000
1*
b11 -
1"
#3296000
b10 0
#3300000
0"
#3305000
0*
b10000000000 ,
b111 -
1"
#3306000
b11 0
#3310000
0"
#3315000
1"
#3316000
b100 0
#3320000
0"
#3325000
1"
#3326000
b101 0
#3330000
0"
#3335000
1"
#3336000
0'
b0 0
#3340000
0"
#3345000
b110 -
1"
#3346000
b1 0
#3350000
0"
#3355000
b100 -
1"
#3356000
b10 0
#3360000
0"
#3365000
b0 -
1"
#3366000
b11 0
#3370000
0"
#3375000
1"
#3376000
b100 0
#3380000
0"
#3385000
1"
#3386000
b101 0
#3390000
0"
#3395000
1"
#3396000
1'
b101 3
b0 0
#3400000
0"
#3405000
b1 -
1"
#3406000
b1 0
#3410000
0"
#3415000
1*
b11 -
1"
#3416000
b10 0
#3420000
0"
#3425000
0*
b100000000000 ,
b111 -
1"
#3426000
b11 0
#3430000
0"
#3435000
1"
#3436000
b100 0
#3440000
0"
#3445000
1"
#3446000
b101 0
#3450000
0"
#3455000
1"
#3456000
0'
b0 0
#3460000
0"
#3465000
b110 -
1"
#3466000
b1 0
#3470000
0"
#3475000
b100 -
1"
#3476000
b10 0
#3480000
0"
#3485000
b0 -
1"
#3486000
b11 0
#3490000
0"
#3495000
1"
#3496000
b100 0
#3500000
0"
#3505000
1"
#3506000
b101 0
#3510000
0"
#3515000
1"
#3516000
1'
b100 3
b0 0
#3520000
0"
#3525000
b1 -
1"
#3526000
b1 0
#3530000
0"
#3535000
1*
b11 -
1"
#3536000
b10 0
#3540000
0"
#3545000
0*
b1000000000000 ,
b111 -
1"
#3546000
b11 0
#3550000
0"
#3555000
1"
#3556000
b100 0
#3560000
0"
#3565000
1"
#3566000
b101 0
#3570000
0"
#3575000
1"
#3576000
0'
b0 0
#3580000
0"
#3585000
b110 -
1"
#3586000
b1 0
#3590000
0"
#3595000
b100 -
1"
#3596000
b10 0
#3600000
0"
#3605000
b0 -
1"
#3606000
b11 0
#3610000
0"
#3615000
1"
#3616000
b100 0
#3620000
0"
#3625000
1"
#3626000
b101 0
#3630000
0"
#3635000
1"
#3636000
1'
b11 3
b0 0
#3640000
0"
#3645000
b1 -
1"
#3646000
b1 0
#3650000
0"
#3655000
1*
b11 -
1"
#3656000
b10 0
#3660000
0"
#3665000
0*
b10000000000000 ,
b111 -
1"
#3666000
b11 0
#3670000
0"
#3675000
1"
#3676000
b100 0
#3680000
0"
#3685000
1"
#3686000
b101 0
#3690000
0"
#3695000
1"
#3696000
0'
b0 0
#3700000
0"
#3705000
b110 -
1"
#3706000
b1 0
#3710000
0"
#3715000
b100 -
1"
#3716000
b10 0
#3720000
0"
#3725000
b0 -
1"
#3726000
b11 0
#3730000
0"
#3735000
1"
#3736000
b100 0
#3740000
0"
#3745000
1"
#3746000
b101 0
#3750000
0"
#3755000
1"
#3756000
1'
b1010000000000001 2
b10 3
b0 0
#3760000
0"
#3765000
b1 -
1"
#3766000
b1 0
#3770000
0"
#3775000
1*
b11 -
1"
#3776000
b10 0
#3780000
0"
#3785000
0*
b100000000000000 ,
b111 -
1"
#3786000
b11 0
#3790000
0"
#3795000
1"
#3796000
b100 0
#3800000
0"
#3805000
1"
#3806000
b101 0
#3810000
0"
#3815000
1"
#3816000
0'
b0 0
#3820000
0"
#3825000
b110 -
1"
#3826000
b1 0
#3830000
0"
#3835000
b100 -
1"
#3836000
b10 0
#3840000
0"
#3845000
b0 -
1"
#3846000
b11 0
#3850000
0"
#3855000
1"
#3856000
b100 0
#3860000
0"
#3865000
1"
#3866000
b101 0
#3870000
0"
#3875000
1"
#3876000
1'
b1 3
b0 0
#3880000
0"
