final_project/rtl/debounce.v
// debounce: filtra uma entrada mecanica/ruidosa (botao ou sensor IR).
// Sincroniza a entrada assincrona com 2 flip-flops (evita metaestabilidade)
// e so' muda a saida depois que a entrada fica N_CICLOS ciclos seguidos
// no novo nivel. Usado por botao_pedestre e sensor_veiculo.
//
// Parametro:
//   N_CICLOS - ciclos de clk que a entrada precisa ficar estavel
//              (ex.: 540_000 ciclos = 20 ms a 27 MHz)
// Portas:
//   entrada - sinal bruto, ativo em nivel ALTO (assincrono ao clk)
//   saida   - sinal filtrado e sincronizado ao clk (repouso = 0)
module debounce #(
    parameter integer N_CICLOS = 540_000
) (
    input  wire clk,
    input  wire rst_n,
    input  wire entrada,
    output reg  saida
);
    localparam integer LARGURA_CONT = $clog2(N_CICLOS + 1);

    reg [1:0]              sinc;      // cadeia de sincronizacao; sinc[1] = entrada ja sincronizada
    reg [LARGURA_CONT-1:0] contador;  // ciclos seguidos em que sinc[1] difere de saida

    always @(posedge clk or negedge rst_n) begin
        if (!rst_n) begin
            sinc     <= 2'b00;
            contador <= {LARGURA_CONT{1'b0}};
            saida    <= 1'b0;
        end else begin
            sinc <= {sinc[0], entrada};

            if (sinc[1] == saida)
                contador <= {LARGURA_CONT{1'b0}};       // qualquer repique reinicia a contagem
            else if (contador == N_CICLOS - 1) begin
                saida    <= sinc[1];                    // estavel tempo suficiente: aceita o novo nivel
                contador <= {LARGURA_CONT{1'b0}};
            end else
                contador <= contador + 1'b1;
        end
    end
endmodule

final_project/rtl/sensor_veiculo.v
// sensor_veiculo: le o sensor IR de obstaculo (tipo FC-51) que detecta
// veiculos. Filtra o sinal com debounce e gera 1 pulso por veiculo (borda
// de subida da deteccao). Os pulsos alimentam a contagem de fluxo em
// top_semaforo.
//
// Parametro:
//   N_CICLOS - ciclos de estabilidade exigidos pelo debounce
// Portas:
//   sensor_ativo  - saida do sensor ja convertida para ativo em ALTO
//                   (1 = obstaculo na frente do sensor)
//   veiculo_pulso - 1 ciclo em 1 a cada nova deteccao de veiculo
module sensor_veiculo #(
    parameter integer N_CICLOS = 135_000
) (
    input  wire clk,
    input  wire rst_n,
    input  wire sensor_ativo,
    output wire veiculo_pulso
);
    wire sensor_estavel;   // deteccao filtrada (1 enquanto ha veiculo na frente do sensor)
    reg  estavel_ant;      // sensor_estavel no ciclo anterior, para detectar a borda

    debounce #(.N_CICLOS(N_CICLOS)) u_debounce (
        .clk(clk), .rst_n(rst_n),
        .entrada(sensor_ativo), .saida(sensor_estavel)
    );

    always @(posedge clk or negedge rst_n) begin
        if (!rst_n)
            estavel_ant <= 1'b0;
        else
            estavel_ant <= sensor_estavel;
    end

    assign veiculo_pulso = sensor_estavel & ~estavel_ant;
endmodule

final_project/tb/tb_sensor_veiculo.v
// tb_sensor_veiculo: verifica que cada passagem de veiculo gera exatamente
// 1 pulso e que repiques do sensor nao geram pulsos extras.
`timescale 1ns/1ps
module tb_sensor_veiculo;
    localparam integer N = 4;

    reg  clk, rst_n, sensor_ativo;
    wire veiculo_pulso;
    integer pulsos;   // pulsos contados desde o ultimo zeramento
    integer erros;

    sensor_veiculo #(.N_CICLOS(N)) dut (
        .clk(clk), .rst_n(rst_n), .sensor_ativo(sensor_ativo), .veiculo_pulso(veiculo_pulso)
    );

    always #5 clk = ~clk;
    always @(posedge clk) if (veiculo_pulso) pulsos = pulsos + 1;

    task espera(input integer n);
        integer i;
        for (i = 0; i < n; i = i + 1) begin @(posedge clk); #1; end
    endtask

    // um veiculo: com repique na chegada, fica na frente do sensor e sai
    task passa_veiculo;
        begin
            sensor_ativo = 1; espera(1); sensor_ativo = 0; espera(1);
            sensor_ativo = 1; espera(N + 6);
            sensor_ativo = 0; espera(N + 6);
        end
    endtask

    task confere(input integer esperado, input [8*40-1:0] descricao);
        if (pulsos != esperado) begin
            erros = erros + 1;
            $display("[FALHA] %0s (pulsos=%0d, esperado=%0d)", descricao, pulsos, esperado);
        end else
            $display("[OK]    %0s (%0d pulsos)", descricao, pulsos);
    endtask

    initial begin
        $dumpfile("build/tb_sensor_veiculo.vcd");
        $dumpvars(0, tb_sensor_veiculo);
        clk = 0; rst_n = 0; sensor_ativo = 0; erros = 0; pulsos = 0;
        espera(2); rst_n = 1; espera(2);

        passa_veiculo;
        confere(1, "1 veiculo com repique = 1 pulso");

        pulsos = 0;
        repeat (3) passa_veiculo;
        confere(3, "3 veiculos = 3 pulsos");

        if (erros == 0) $display("RESULTADO: TODOS OS CASOS PASSARAM");
        else            $display("RESULTADO: %0d CASO(S) FALHARAM", erros);
        $finish;
    end
endmodule

final_project/build/tb_sensor_veiculo.vcd
$date
	Tue Oct  6 20:22:25 2026
$end
$version
	Icarus Verilog
$end
$timescale
	1ps
$end
$scope module tb_sensor_veiculo $end
$var wire 1 ! veiculo_pulso $end
$var parameter 32 " N $end
$var reg 1 # clk $end
$var reg 1 $ rst_n $end
$var reg 1 % sensor_ativo $end
$var integer 32 & erros [31:0] $end
$var integer 32 ' pulsos [31:0] $end
$scope module dut $end
$var wire 1 # clk $end
$var wire 1 $ rst_n $end
$var wire 1 % sensor_ativo $end
$var wire 1 ! veiculo_pulso $end
$var wire 1 ( sensor_estavel $end
$var parameter 32 ) N_CICLOS $end
$var reg 1 * estavel_ant $end
$scope module u_debounce $end
$var wire 1 # clk $end
$var wire 1 % entrada $end
$var wire 1 $ rst_n $end
$var parameter 32 + LARGURA_CONT $end
$var parameter 32 , N_CICLOS $end
$var reg 3 - contador [2:0] $end
$var reg 1 ( saida $end
$var reg 2 . sinc [1:0] $end
$upscope $end
$upscope $end
$scope task confere $end
$var reg 320 / descricao [319:0] $end
$var integer 32 0 esperado [31:0] $end
$upscope $end
$scope task espera $end
$var integer 32 1 i [31:0] $end
$var integer 32 2 n [31:0] $end
$upscope $end
$scope task passa_veiculo $end
$upscope $end
$upscope $end
$enddefinitions $end
$comment Show the parameter values. $end
$dumpall
b100 ,
b11 +
b100 )
b100 "
$end
#0
$dumpvars
b10 2
b0 1
bx 0
bx /
b0 .
b0 -
0*
0(
b0 '
b0 &
0%
0$
0#
0!
$end
#5000
1#
#6000
b1 1
#10000
0#
#15000
1#
#16000
1$
b0 1
#20000
0#
#25000
1#
#26000
b1 1
#30000
0#
#35000
1#
#36000
b1 2
1%
b0 1
#40000
0#
#45000
b1 .
1#
#46000
0%
b0 1
#50000
0#
#55000
b10 .
1#
#56000
b1010 2
1%
b0 1
#60000
0#
#65000
b1 -
b1 .
1#
#66000
b1 1
#70000
0#
#75000
b0 -
b11 .
1#
#76000
b10 1
#80000
0#
#85000
b1 -
1#
#86000
b11 1
#90000
0#
#95000
b10 -
1#
#96000
b100 1
#100000
0#
#105000
b11 -
1#
#106000
b101 1
#110000
0#
#115000
1!
b0 -
1(
1#
#116000
b110 1
#120000
0#
#125000
0!
1*
b1 '
1#
#126000
b111 1
#130000
0#
#135000
1#
#136000
b1000 1
#140000
0#
#145000
1#
#146000
b1001 1
#150000
0#
#155000
1#
#156000
0%
b0 1
#160000
0#
#165000
b10 .
1#
#166000
b1 1
#170000
0#
#175000
b0 .
1#
#176000
b10 1
#180000
0#
#185000
b1 -
1#
#186000
b11 1
#190000
0#
#195000
b10 -
1#
#196000
b100 1
#200000
0#
#205000
b11 -
1#
#206000
b101 1
#210000
0#
#215000
b0 -
0(
1#
#216000
b110 1
#220000
0#
#225000
0*
1#
#226000
b111 1
#230000
0#
#235000
1#
#236000
b1000 1
#240000
0#
#245000
1#
#246000
b1001 1
#250000
0#
#255000
1#
#256000
b1 2
1%
b0 '
b110001001000000111011001100101011010010110001101110101011011000110111100100000011000110110111101101101001000000111001001100101011100000110100101110001011101010110010100100000001111010010000000110001001000000111000001110101011011000111001101101111 /
b1 0
b0 1
#260000
0#
#265000
b1 .
1#
#266000
0%
b0 1
#270000
0#
#275000
b10 .
1#
#276000
b1010 2
1%
b0 1
#280000
0#
#285000
b1 -
b1 .
1#
#286000
b1 1
#290000
0#
#295000
b0 -
b11 .
1#
#296000
b10 1
#300000
0#
#305000
b1 -
1#
#306000
b11 1
#310000
0#
#315000
b10 -
1#
#316000
b100 1
#320000
0#
#325000
b11 -
1#
#326000
b101 1
#330000
0#
#335000
1!
b0 -
1(
1#
#336000
b110 1
#340000
0#
#345000
0!
1*
b1 '
1#
#346000
b111 1
#350000
0#
#355000
1#
#356000
b1000 1
#360000
0#
#365000
1#
#366000
b1001 1
#370000
0#
#375000
1#
#376000
0%
b0 1
#380000
0#
#385000
b10 .
1#
#386000
b1 1
#390000
0#
#395000
b0 .
1#
#396000
b10 1
#400000
0#
#405000
b1 -
1#
#406000
b11 1
#410000
0#
#415000
b10 -
1#
#416000
b100 1
#420000
0#
#425000
b11 -
1#
#426000
b101 1
#430000
0#
#435000
b0 -
0(
1#
#436000
b110 1
#440000
0#
#445000
0*
1#
#446000
b111 1
#450000
0#
#455000
1#
#456000
b1000 1
#460000
0#
#465000
1#
#466000
b1001 1
#470000
0#
#475000
1#
#476000
b1 2
1%
b0 1
#480000
0#
#485000
b1 .
1#
#486000
0%
b0 1
#490000
0#
#495000
b10 .
1#
#496000
b1010 2
1%
b0 1
#500000
0#
#505000
b1 -
b1 .
1#
#506000
b1 1
#510000
0#
#515000
b0 -
b11 .
1#
#516000
b10 1
#520000
0#
#525000
b1 -
1#
#526000
b11 1
#530000
0#
#535000
b10 -
1#
#536000
b100 1
#540000
0#
#545000
b11 -
1#
#546000
b101 1
#550000
0#
#555000
1!
b0 -
1(
1#
#556000
b110 1
#560000
0#
#565000
0!
1*
b10 '
1#
#566000
b111 1
#570000
0#
#575000
1#
#576000
b1000 1
#580000
0#
#585000
1#
#586000
b1001 1
#590000
0#
#595000
1#
#596000
0%
b0 1
#600000
0#
#605000
b10 .
1#
#606000
b1 1
#610000
0#
#615000
b0 .
1#
#616000
b10 1
#620000
0#
#625000
b1 -
1#
#626000
b11 1
#630000
0#
#635000
b10 -
1#
#636000
b100 1
#640000
0#
#645000
b11 -
1#
#646000
b101 1
#650000
0#
#655000
b0 -
0(
1#
#656000
b110 1
#660000
0#
#665000
0*
1#
#666000
b111 1
#670000
0#
#675000
1#
#676000
b1000 1
#680000
0#
#685000
1#
#686000
b1001 1
#690000
0#
#695000
1#
#696000
b1 2
1%
b0 1
#700000
0#
#705000
b1 .
1#
#706000
0%
b0 1
#710000
0#
#715000
b10 .
1#
#716000
b1010 2
1%
b0 1
#720000
0#
#725000
b1 -
b1 .
1#
#726000
b1 1
#730000
0#
#735000
b0 -
b11 .
1#
#736000
b10 1
#740000
0#
#745000
b1 -
1#
#746000
b11 1
#750000
0#
#755000
b10 -
1#
#756000
b100 1
#760000
0#
#765000
b11 -
1#
#766000
b101 1
#770000
0#
#775000
1!
b0 -
1(
1#
#776000
b110 1
#780000
0#
#785000
0!
1*
b11 '
1#
#786000
b111 1
#790000
0#
#795000
1#
#796000
b1000 1
#800000
0#
#805000
1#
#806000
b1001 1
#810000
0#
#815000
1#
#816000
0%
b0 1
#820000
0#
#825000
b10 .
1#
#826000
b1 1
#830000
0#
#835000
b0 .
1#
#836000
b10 1
#840000
0#
#845000
b1 -
1#
#846000
b11 1
#850000
0#
#855000
b10 -
1#
#856000
b100 1
#860000
0#
#865000
b11 -
1#
#866000
b101 1
#870000
0#
#875000
b0 -
0(
1#
#876000
b110 1
#880000
0#
#885000
0*
1#
#886000
b111 1
#890000
0#
#895000
1#
#896000
b1000 1
#900000
0#
#905000
1#
#906000
b1001 1
#910000
0#
#915000
1#
#916000
b1100110010000001110110011001010110100101100011011101010110110001101111011100110010000000111101001000000011001100100000011100000111010101101100011100110110111101110011 /
b11 0
b1010 1
